Workbook

Sheet Показатели
B1: 2022 | C1: 2023 | D1: 2024 | G1: Данные VK видео | H1: 2022 | I1: 2023 | J1: 2024
A2: Операционные показатели VK | G2: Среднесуточное количество просмотров
A3: средняя дневная аудитория (млн. пользователей) | D3: 77 | G3: новых авторов появилось на платформе за год (тыс.) | J3: 42 | K3: Новый какнал монетизации запустили
A4: Time spent — среднее время, которое пользователи проводят в сервисах VK (млрд. минут в день) | D4: 4.4 | G4: Объем нативной рекламы (млрд) | J4: 2.4
A5: Финансовые показатели VK | G5: Кол-во шоу | J5: 38
A6: выручка (млрд.) | C6: 120.3 | D6: 148 | G6: рост совокупного времени смотрения на платформе на конец 2024 года | J6: 4.5
A7: выручка от онлайн-рекламы | C7: 79.7 | D7: 96 | G7: среднее время смотрения в приложении на Smart TV на конец 2024 года (минут в день) | J7: 216
A8: Пользовательские платежи | C8: 19.3 | D8: 22.3 | G8: установок приложения VK Видео (млн) | J8: 60
A9: Образовательные технологии | B9: 11 | C9: 3.4 | D9: 6.3 | G9: единиц эксклюзивного контента вышло на VK Видео в 2024 году (тыс) | J9: 3
A10: VK Tech | C10: 9.6 | D10: 13.6 | G10: продуктовых обновлений в 2024 году | J10: 300
A11: Прочая выручка | C11: 8.3 | D11: 9.4
A13: Развитие команды VK
A14: тыс. сотрудников | D14: 13
A15: Офисов и коворкингов | D15: 15
A16: городов присутствия | D16: 9
A17: доля ИТ-специалистов | D17: =2/3 -> 0.66666667
A21: Кол0во интернет пользователей (млн) | D21: 103.1
A22: населения страны старше 12 лет | D22: 0.85
A23: Итоги 2024
A24: Корпоративное ПО
A25: №3 в рейтинге крупнейших поставщиков собственных ИТ-решений5 | D25: VK tech
A26: №2 на рынке корпоративной связи и взаимодействия4 | D26: VK Workspace
A27: Видеосервисы
A28: №1 российская видеоплатформа1 | D28: VK видео
A29: №1 российская платформа коротких вертикальных роликов1 | D29: Vk клипы
A30: Почтовые сервисы
A31: №1 почтовый сервис1 | D31: mail
A32: Социальные сети
A33: №1 по числу активных авторов и по объему создаваемого контента2 | D33: вконтакте
A36: Ключевые сегменты

Sheet Предпосылки
A1: № | B1: Среднее число шоу в месяц | C1: Среднее число брендов в месяц | E1: Кол-во зрителей в месяц (июнь 2025) по MediaScope | F1: План показов (Среднемесячное количество просмотров ВК видео за 2 кв. 2025 года - данные отчетности) | H1: В онлайн‑образовании учатся (примерно) | I1: Количество студентов на дистанционных программах | J1: Количество просмотров : 1 курс в год × 30 видеоуроков В России с каждым годом количество онлайн курсов растет: возьмем 500 курсов в год в онлайн-формате
B2: 50 | C2: 20 | E2: 76400000 | F2: 7383333.3 | H2: 7000000 | I2: 2300000 | J2: =30*500 -> 15000
B3: У ВК ВИДЕО | C3: Данные MediaScope | E3: https://corp.vkcdn.ru/media/files/VK_IR_Presentation_H1_2025_OwIezHP.pdf | H3: https://www.tadviser.ru/index.php/Статья:Онлайн-образование_(рынок_России) | I3: https://marketing.rbc.ru/articles/16072/ | J3: https://sberbusiness.live/publications/trendi-rinka-onlain-obrazovaniya-2024-chto-nuzhno-znat-esli-vi-reshili-otkrit-onlain-shkolu
B5: Статьи доходов | C5: Описание | D5: Эффект Стоимость контранкта или CRM на 1000 показов | E5: Количество показов | F5: Средний процент | G5: Сумма
A6: 1 | B6: Брендированные плейлисты/каналы | D6: 500000 | F6: Месячные контракты | G6: =D6*C2 -> 10000000
B7: Спонсорские интеграции в шоу | D7: 900000 | F7: Месячные контракты | G7: =D7*B2 -> 45000000 | I7: Описание сценариев | J7: Оптимистичный | K7: Базовый | L7: Пессимистичный
A8: 2 | B8: Реклама перед/после видео | C8: Оптимизация интерфейса и алгоритмов увеличивает вовлечённость пользователей и среднее время просмотра, что приводит к росту показов рекламы. | D8: 150 | E8: =F2/1000*1.8 -> 13290 | F8: Оплата за показ | G8: =E8*D8 -> 1993500 | I8: На 2 года | J8: Более агрессивный рост Куммулятивная конверсия достигается в 18 месяц Коллаборационный контент от онлайн-школ дает весь расчитанный контент | K8: Спокойный рост конверсии Куммулятивная конверсия достигается в 18 месяц Коллаборационный контент от онлайн-школ дает половину контента | L8: Первый месяц конверсия 1%, далее прирост накуммулятивную конверсию Коллаборационный контент дает четверть рассчитаной конверсии
B9: реклама от авторов | D9: 40 | E9: =F2/1000*1.8 -> 13290 | F9: 0.2 | G9: =E9*F9*D9 -> 106320
A10: 3 | B10: Просмотры контента от онлайн школ | D10: =I2/4 -> 575000 | E10: =J2 -> 15000 | F10: 0.1 | G10: =E10*F10*D10 -> 862500000
B11: Подписка на "без рекламы" | C11: Тестовая версия На данным момент не работает | D11: 99 | G11: =D11*E11 -> 0
B13: Гипотеза | C13: Конверсии
B14: Классический рост | C14: 0.3
B15: Общий рост времени в приложении | C15: 0.05
B16: Рост количества взаимодействий | C16: 0.3
B17: Рост в разделе | C17: 0.04
B18: Куммулятивная конверсия | C18: =C14*(1+(C15+C16+C17)/12) -> 0.30975
B20: Другие данные для расчетов
C21: Инфляция мес. | D21: Премия за риск | E21: WACC
B22: На 2026 | C22: 0.049 | D22: 0.03 | E22: =(1 + $C$25+D22)/(1+C22)-1 -> 0.1534795
B23: На 2027 | C23: 0.04 | D23: 0.03 | E23: =(1 + $C$25+D23)/(1+C23)-1 -> 0.16346154
B24: На 2028 | C24: 0.04 | D24: 0.03 | E24: =(1 + $C$25+D24)/(1+C24)-1 -> 0.16346154
B25: Безрисковая ставка | C25: 0.18
B26: Источник | C26: https://cbr.ru/Content/Document/File/184551/forecast_251024.pdf | D26: Стандартная премия за операционные и отраслевые риски, характерная для цифровых и IT-секторов. | E26: Облигации федерального займа со сроком погашения 2-3 года используются как безрисковая ставка
B27: Обоснование | C27: Прогноз инфляции Банка России и Минэкономразвития с учетом постепенного замедления инфляционных процессов.

Sheet Расходники
A1: Статья расходов | B1: Что входит
A2: Капитальные затраты (CapEx) | B2: Ежегодный (Сумма млн руб.) | C2: =SUM(C3:C10) -> 9
A3: Разработка | B3: Frontend + backend, интеграция с API VK, админка | C3: 4.5
A4: Адаптация алгоритма рекомендаций | B4: На основе поведения пользователя | C4: 2
A5: Дизайн интерфейса (UI/UX) | B5: Визуальное оформление, анимации, переходы | C5: 0.7
A6: Тестирование и QA | B6: Бета-тестирование, исправление багов | C6: 0.8
A7: Закупка оборудования
A8: Ремонт/обустройство помещения
A9: Лицензии, патенты
A10: Первичный маркетинг (сайт, брендбук, рекламные материалы) | C10: 1
A11: Операционные расходы (OpEx) | B11: Мес. | C11: =(1+C28)*SUM(C12,C16,C19,C22,C24) -> 7245000
A12: Техническая поддержка и разработка | C12: =SUM(C13:C15) -> 2800000
A13: Инженеры (2 чел.) | B13: Поддержка алгоритма рекомендаций, багфиксы, A/B тесты | C13: 900000 | D13: Средняя зарплата backend/frontend + ML-инженер
A14: Серверы и CDN | B14: Хранение и потоковая передача видео (1000+ Reels в день) | C14: 1500000 | D14: AWS / Yandex Cloud, оптимизация под мобильный трафик
A15: Аналитика (внутренние системы) | B15: Интеграция с GA4, Amplitude, внутренние дашборды | C15: 400000
A16: Модерация и безопасность | C16: =SUM(C17:C18) -> 1700000
A17: Автоматическая модерация (AI) | B17: Обнаружение спама, фейковых аккаунтов, неприемлемого контента | C17: 800000 | D17: Платформа LikeAPro / Yandex Cloud Vision + кастомный ML
A18: Ручная модерация (3 человека) | B18: Проверка спорных случаев, жалобы | C18: 900000 | D18: 3 модератора × 150 тыс. руб.
A19: Анализ, тестирование и оптимизация | C19: =SUM(C20:C21) -> 900000
A20: A/B тесты (UI/UX, алгоритмы) | B20: 2–3 теста в месяц, включая инструменты | C20: 500000 | D20: Платформы: Optimizely, Google Optimize, внутренние
A21: Исследования пользователей | B21: Фокус-группы, интервью, опросы | C21: 400000 | D21: 2–3 фокус-группы в месяц
A22: Юридические и лицензионные расходы | C22: =SUM(C23) -> 500000
A23: Права на использование контента | B23: Договоры с создателями, лицензии на музыку, бренды | C23: 500000 | D23: Юрист + договоры с 50+ авторами в месяц
A24: Статья расходов на коллаборацию с онлайн-школами | B24: Расходы, направленные на продвижение образовательного контента (IT, научпоп, маркетинг, AI) | C24: =SUM(C25:C27) -> 1000000
A25: Затраты на алгоритмы | B25: ЗП инженера | C25: 500000
A26: Таргетирование | C26: 500000
A28: Непредвиденные расходы | C28: 0.05 | D28: =C28*SUM(C12,C16,C19,C22) -> 295000
A30: Статья маркетинговых расходов | B30: Мес. | C30: =C31*(1+C37) -> 2509500
A31: Медиа каналы | B31: Модель CRM/СPC | C31: =SUM(C32:C36) -> 2390000 | D31: Формула расчета
A32: Реклама в VK Видео | B32: 2 000 000 показов | C32: =2000000/1000*200 -> 400000 | D32: 2000000/1000∗200
A33: Плашки внутри VK (баннеры) | B33: 1 500 000 показов | C33: =1500000/1000*100 -> 150000 | D33: 1500000/1000∗100
A34: Яндекс (видео/баннеры) | B34: 1 000 000 показов | C34: =1000000/1000*200 -> 200000 | D34: 1000000/1000∗200
A35: Яндекс (пуш-рассылка) | B35: 77% россиян получают по 10 пушей в день | C35: =136000000*60%/50 -> 1632000
A36: Яндекс (поиск, клики) | B36: 8 000 кликов | C36: =8000 -> 8000 | D36: 8000/100∗100
A37: Непредвиденные расходы | C37: 0.05
K42: —

Sheet Cash Flow
A1: Оптимистичный сценарий
B2: 46023 | C2: 46054 | D2: 46082 | E2: 46113 | F2: 46143 | G2: 46174 | H2: 46204 | I2: 46235 | J2: 46266 | K2: 46296 | L2: 46327 | M2: 46357 | N2: 46388 | O2: 46419 | P2: 46447 | Q2: 46478 | R2: 46508 | S2: 46539 | T2: 46569 | U2: 46600 | V2: 46631 | W2: 46661 | X2: 46692 | Y2: 46722 | Z2: 46753 | AA2: 46784 | AB2: 46813 | AC2: 46844
A3: Период (мес.) | F3: 1 | G3: 2 | H3: 3 | I3: 4 | J3: 5 | K3: 6 | L3: 7 | M3: 8 | N3: 9 | O3: 10 | P3: 11 | Q3: 12 | R3: 13 | S3: 14 | T3: 15 | U3: 16 | V3: 17 | W3: 18 | X3: 19 | Y3: 20 | Z3: 21 | AA3: 22 | AB3: 23 | AC3: 24
A4: Конверсия | B4: 0 | C4: 0 | D4: 0 | E4: 0 | F4: 0.05 | G4: =F4*(1+Предпосылки!$C$18/10) -> 0.05154875 | H4: =G4*(1+Предпосылки!$C$18/10) -> 0.053145473 | I4: =H4*(1+Предпосылки!$C$18/10) -> 0.054791654 | J4: =I4*(1+Предпосылки!$C$18/10) -> 0.056488825 | K4: =J4*(1+Предпосылки!$C$18/10) -> 0.058238566 | L4: =K4*(1+Предпосылки!$C$18/10) -> 0.060042506 | M4: =L4*(1+Предпосылки!$C$18/10) -> 0.061902323 | N4: =M4*(1+Предпосылки!$C$18/10) -> 0.063819747 | ... AC4: =AB4*(1+Предпосылки!$C$18/10) -> 0.10085028
A5: =A31 -> Брендированные плейлисты/каналы | F5: =Предпосылки!$G$6*F$4 -> 500000 | G5: =Предпосылки!$G$6*G$4 -> 515487.5 | H5: =Предпосылки!$G$6*H$4 -> 531454.73 | I5: =Предпосылки!$G$6*I$4 -> 547916.54 | J5: =Предпосылки!$G$6*J$4 -> 564888.25 | K5: =Предпосылки!$G$6*K$4 -> 582385.66 | L5: =Предпосылки!$G$6*L$4 -> 600425.06 | M5: =Предпосылки!$G$6*M$4 -> 619023.23 | ... AC5: =Предпосылки!$G$6*AC$4 -> 1008502.8
A6: =A32 -> Реклама перед/после видео | F6: =Предпосылки!$G$8*F$4 -> 99675 | G6: =Предпосылки!$G$8*G$4 -> 102762.43 | H6: =Предпосылки!$G$8*H$4 -> 105945.5 | I6: =Предпосылки!$G$8*I$4 -> 109227.16 | J6: =Предпосылки!$G$8*J$4 -> 112610.47 | K6: =Предпосылки!$G$8*K$4 -> 116098.58 | L6: =Предпосылки!$G$8*L$4 -> 119694.74 | M6: =Предпосылки!$G$8*M$4 -> 123402.28 | ... AC6: =Предпосылки!$G$8*AC$4 -> 201045.03
A7: =A33 -> Спонсорские интеграции в шоу | F7: =Предпосылки!$G$7*F$4 -> 2250000 | G7: =Предпосылки!$G$7*G$4 -> 2319693.8 | H7: =Предпосылки!$G$7*H$4 -> 2391546.3 | I7: =Предпосылки!$G$7*I$4 -> 2465624.4 | J7: =Предпосылки!$G$7*J$4 -> 2541997.1 | K7: =Предпосылки!$G$7*K$4 -> 2620735.5 | L7: =Предпосылки!$G$7*L$4 -> 2701912.8 | M7: =Предпосылки!$G$7*M$4 -> 2785604.5 | ... AC7: =Предпосылки!$G$7*AC$4 -> 4538262.4
A8: =A34 -> реклама от авторов | F8: =Предпосылки!$G$9*F$4 -> 5316 | G8: =Предпосылки!$G$9*G$4 -> 5480.6631 | H8: =Предпосылки!$G$9*H$4 -> 5650.4266 | I8: =Предпосылки!$G$9*I$4 -> 5825.4486 | J8: =Предпосылки!$G$9*J$4 -> 6005.8919 | K8: =Предпосылки!$G$9*K$4 -> 6191.9244 | L8: =Предпосылки!$G$9*L$4 -> 6383.7192 | M8: =Предпосылки!$G$9*M$4 -> 6581.4549 | ... AC8: =Предпосылки!$G$9*AC$4 -> 10722.401
A9: =A35 -> Подписка на "без рекламы" | F9: =Предпосылки!$G$11*F4 -> 0 | G9: =Предпосылки!$G$11*G4 -> 0 | H9: =Предпосылки!$G$11*H4 -> 0 | I9: =Предпосылки!$G$11*I4 -> 0 | J9: =Предпосылки!$G$11*J4 -> 0 | K9: =Предпосылки!$G$11*K4 -> 0 | L9: =Предпосылки!$G$11*L4 -> 0 | M9: =Предпосылки!$G$11*M4 -> 0 | ... AC9: =Предпосылки!$G$11*AC4 -> 0
A10: =Предпосылки!B9 -> реклама от авторов | F10: =Предпосылки!$G$10*'Cash Flow'!F$30*Предпосылки!$C$14 -> 12937500 | G10: =Предпосылки!$G$10*'Cash Flow'!G$30*Предпосылки!$C$14 -> 13137870 | H10: =Предпосылки!$G$10*'Cash Flow'!H$30*Предпосылки!$C$14 -> 13341342 | I10: =Предпосылки!$G$10*'Cash Flow'!I$30*Предпосылки!$C$14 -> 13547966 | J10: =Предпосылки!$G$10*'Cash Flow'!J$30*Предпосылки!$C$14 -> 13757790 | K10: =Предпосылки!$G$10*'Cash Flow'!K$30*Предпосылки!$C$14 -> 13970864 | L10: =Предпосылки!$G$10*'Cash Flow'!L$30*Предпосылки!$C$14 -> 14187238 | M10: =Предпосылки!$G$10*'Cash Flow'!M$30*Предпосылки!$C$14 -> 14406963 | ... AC10: =Предпосылки!$G$10*'Cash Flow'!AC$30*Предпосылки!$C$14 -> 18423229
A11: Сумма | B11: =SUM(B6:B6) -> 0 | C11: =SUM(C6:C6) -> 0 | D11: =SUM(D6:D6) -> 0 | E11: =SUM(E6:E6) -> 0 | F11: =SUM(F5:F10) -> 15792491 | G11: =SUM(G5:G10) -> 16081294 | H11: =SUM(H5:H10) -> 16375939 | I11: =SUM(I5:I10) -> 16676560 | J11: =SUM(J5:J10) -> 16983292 | K11: =SUM(K5:K10) -> 17296276 | L11: =SUM(L5:L10) -> 17615654 | M11: =SUM(M5:M10) -> 17941574 | ... AC11: =SUM(AC5:AC10) -> 24181761
A12: =A38 -> Капитальные затраты (CapEx) | B12: =Расходники!C2*1000000 -> 9000000 | R12: =Расходники!C2*1000000 -> 9000000
A13: =A39 -> Операционные расходы (OpEx) | B13: =Расходники!C11 -> 7245000 | C13: =B13 -> 7245000 | D13: =C13 -> 7245000 | E13: =D13 -> 7245000 | F13: =E13 -> 7245000 | G13: =F13 -> 7245000 | H13: =G13 -> 7245000 | I13: =H13 -> 7245000 | J13: =I13 -> 7245000 | ... AC13: =AB13 -> 7245000
A14: =Расходники!A30 -> Статья маркетинговых расходов | E14: =Расходники!$C$30 -> 2509500 | F14: =Расходники!$C$30*(1-Предпосылки!$C$16/12) -> 2446762.5 | G14: =Расходники!$C$30*(1-Предпосылки!$C$16/12) -> 2446762.5 | H14: =Расходники!$C$30*(1-Предпосылки!$C$16/12) -> 2446762.5 | I14: =Расходники!$C$30*(1-Предпосылки!$C$16/12) -> 2446762.5 | J14: =Расходники!$C$30*(1-Предпосылки!$C$16/12) -> 2446762.5 | K14: =Расходники!$C$30*(1-Предпосылки!$C$16/12) -> 2446762.5 | L14: =Расходники!$C$30*(1-Предпосылки!$C$16/12) -> 2446762.5 | M14: =Расходники!$C$30*(1-Предпосылки!$C$16/12) -> 2446762.5 | ... AC14: =Расходники!$C$30*(1-Предпосылки!$C$16/12) -> 2446762.5
A15: Прибыль до налогообложения | B15: =B11-B12-B13 -> -16245000 | C15: =C11-C12-C13 -> -7245000 | D15: =D11-D12-D13 -> -7245000 | E15: =E11-E12-E13 -> -7245000 | F15: =F11-F12-F13-F14 -> 6100728.5 | G15: =G11-G12-G13-G14 -> 6389531.4 | H15: =H11-H12-H13-H14 -> 6684176.7 | I15: =I11-I12-I13-I14 -> 6984797.4 | J15: =J11-J12-J13-J14 -> 7291529.7 | K15: =K11-K12-K13-K14 -> 7604513.4 | L15: =L11-L12-L13-L14 -> 7923891.8 | M15: =M11-M12-M13-M14 -> 8249811.8 | ... AC15: =AC11-AC12-AC13-AC14 -> 14489999
A16: Налог на прибыль | B16: =IF(B15>0,B15*20%,0) -> 0 | C16: =IF(C15>0,C15*20%,0) -> 0 | D16: =IF(D15>0,D15*20%,0) -> 0 | E16: =IF(E15>0,E15*20%,0) -> 0 | F16: =IF(F15>0,F15*20%,0) -> 1220145.7 | G16: =IF(G15>0,G15*20%,0) -> 1277906.3 | H16: =IF(H15>0,H15*20%,0) -> 1336835.3 | I16: =IF(I15>0,I15*20%,0) -> 1396959.5 | ... AC16: =IF(AC15>0,AC15*20%,0) -> 2897999.8
A17: CF | B17: =SUM(B15:B16) -> -16245000 | C17: =SUM(C15:C16) -> -7245000 | D17: =SUM(D15:D16) -> -7245000 | E17: =SUM(E15:E16) -> -7245000 | F17: =SUM(F15:F16) -> 7320874.2 | G17: =SUM(G15:G16) -> 7667437.7 | H17: =SUM(H15:H16) -> 8021012 | I17: =SUM(I15:I16) -> 8381756.9 | ... AC17: =SUM(AC15:AC16) -> 17387999
A18: Дисконтированный CF | B18: =IF(SUM(B15:B16)<0,SUM(B15:B16),0) -> -16245000 | C18: =IF(SUM(C15:C16)<0,SUM(C15:C16),0) -> -7245000 | D18: =IF(SUM(D15:D16)<0,SUM(D15:D16),0) -> -7245000 | E18: =IF(SUM(E15:E16)<0,SUM(E15:E16),0) -> -7245000 | F18: =IF(SUM(F15:F16)<0,SUM(F15:F16),SUM(F15:F16)*1/(1+Предпосылки!$E$22/12)^F3) -> 7228423 | G18: =IF(SUM(G15:G16)<0,SUM(G15:G16),SUM(G15:G16)*1/(1+Предпосылки!$E$22/12)^G3) -> 7475004.9 | H18: =IF(SUM(H15:H16)<0,SUM(H15:H16),SUM(H15:H16)*1/(1+Предпосылки!$E$22/12)^H3) -> 7720954.8 | I18: =IF(SUM(I15:I16)<0,SUM(I15:I16),SUM(I15:I16)*1/(1+Предпосылки!$E$22/12)^I3) -> 7966315.7 | J18: =IF(SUM(J15:J16)<0,SUM(J15:J16),SUM(J15:J16)*1/(1+Предпосылки!$E$22/12)^J3) -> 8211130.6 | K18: =IF(SUM(K15:K16)<0,SUM(K15:K16),SUM(K15:K16)*1/(1+Предпосылки!$E$22/12)^K3) -> 8455442.8 | L18: =IF(SUM(L15:L16)<0,SUM(L15:L16),SUM(L15:L16)*1/(1+Предпосылки!$E$22/12)^L3) -> 8699295.3 | M18: =IF(SUM(M15:M16)<0,SUM(M15:M16),SUM(M15:M16)*1/(1+Предпосылки!$E$22/12)^M3) -> 8942731.5 | ... Q18: =IF(SUM(Q15:Q16)<0,SUM(Q15:Q16),SUM(Q15:Q16)*1/(1+Предпосылки!$E$22/12)^Q3) -> 9913183.2 | R18: =IF(SUM(R15:R16)<0,SUM(R15:R16),SUM(R15:R16)*1/(1+Предпосылки!$E$23/12)^R3) -> 989294.08 | S18: =IF(SUM(S15:S16)<0,SUM(S15:S16),SUM(S15:S16)*1/(1+Предпосылки!$E$23/12)^S3) -> 10278227 | T18: =IF(SUM(T15:T16)<0,SUM(T15:T16),SUM(T15:T16)*1/(1+Предпосылки!$E$23/12)^T3) -> 10508577 | U18: =IF(SUM(U15:U16)<0,SUM(U15:U16),SUM(U15:U16)*1/(1+Предпосылки!$E$23/12)^U3) -> 10738478 | V18: =IF(SUM(V15:V16)<0,SUM(V15:V16),SUM(V15:V16)*1/(1+Предпосылки!$E$23/12)^V3) -> 10967974 | W18: =IF(SUM(W15:W16)<0,SUM(W15:W16),SUM(W15:W16)*1/(1+Предпосылки!$E$23/12)^W3) -> 11197110 | X18: =IF(SUM(X15:X16)<0,SUM(X15:X16),SUM(X15:X16)*1/(1+Предпосылки!$E$23/12)^X3) -> 11425930 | Y18: =IF(SUM(Y15:Y16)<0,SUM(Y15:Y16),SUM(Y15:Y16)*1/(1+Предпосылки!$E$23/12)^Y3) -> 11654480 | Z18: =IF(SUM(Z15:Z16)<0,SUM(Z15:Z16),SUM(Z15:Z16)*1/(1+Предпосылки!$E$24/12)^Z3) -> 11882803 | AA18: =IF(SUM(AA15:AA16)<0,SUM(AA15:AA16),SUM(AA15:AA16)*1/(1+Предпосылки!$E$24/12)^AA3) -> 12110945 | AB18: =IF(SUM(AB15:AB16)<0,SUM(AB15:AB16),SUM(AB15:AB16)*1/(1+Предпосылки!$E$24/12)^AB3) -> 12338952 | AC18: =IF(SUM(AC15:AC16)<0,SUM(AC15:AC16),SUM(AC15:AC16)*1/(1+Предпосылки!$E$24/12)^AC3) -> 12566867
A20: NPV | B20: =SUM(B18:AC18) -> 1.9157742e+08
A21: Срок окупаемости (мес) | B21: 5
A22: OpEX | B22: =SUM(B13:AC13) -> 202860000
A23: ROI | B23: =(SUM(B17:AC17)-SUM(B12:AC13))/SUM(B12:AC13)*100% -> 0.080528804
A24: IRR | B24: =IRR(B17:AC17) -> 0.17165443
A25: Стоимость привлечения одного клиента | B25: =(F4^AC3+G4^AB3+H4^AA3+I4^I3+J4^Y3+K4^X3+L4^W3+M4^V3+N4^U3+O4^T3+P4^S3+Q4^R3+R4^Q3+S4^P3+T4^O3+U4^N3+V4^M3+W4^L3+X4^J3+Y4^I3+Z4^H3+AA4^G3+AB4^F3+AC4^Z3+AC3)*Предпосылки!$E$2/SUM('Cash Flow'!B12:AC13) -> 8.3393404
A27: Базовый сценарий
B28: 46023 | C28: 46054 | D28: 46082 | E28: 46113 | F28: 46143 | G28: 46174 | H28: 46204 | I28: 46235 | J28: 46266 | K28: 46296 | L28: 46327 | M28: 46357 | N28: 46388 | O28: 46419 | P28: 46447 | Q28: 46478 | R28: 46508 | S28: 46539 | T28: 46569 | U28: 46600 | V28: 46631 | W28: 46661 | X28: 46692 | Y28: 46722 | Z28: 46753 | AA28: 46784 | AB28: 46813 | AC28: 46844
A29: Период (мес.) | F29: 1 | G29: 2 | H29: 3 | I29: 4 | J29: 5 | K29: 6 | L29: 7 | M29: 8 | N29: 9 | O29: 10 | P29: 11 | Q29: 12 | R29: 13 | S29: 14 | T29: 15 | U29: 16 | V29: 17 | W29: 18 | X29: 19 | Y29: 20 | Z29: 21 | AA29: 22 | AB29: 23 | AC29: 24
A30: Конверсия | B30: 0 | C30: 0 | D30: 0 | E30: 0 | F30: 0.05 | G30: =F30*(1+Предпосылки!$C$18/20) -> 0.050774375 | H30: =G30*(1+Предпосылки!$C$18/20) -> 0.051560743 | I30: =H30*(1+Предпосылки!$C$18/20) -> 0.05235929 | J30: =I30*(1+Предпосылки!$C$18/20) -> 0.053170205 | K30: =J30*(1+Предпосылки!$C$18/20) -> 0.053993678 | L30: =K30*(1+Предпосылки!$C$18/20) -> 0.054829905 | M30: =L30*(1+Предпосылки!$C$18/20) -> 0.055679083 | N30: =M30*(1+Предпосылки!$C$18/20) -> 0.056541413 | ... AC30: =AB30*(1+Предпосылки!$C$18/20) -> 0.071200884 | AE30: =SUM(F30:AC30)*Предпосылки!E2 -> 1.1002393e+08
A31: =Предпосылки!B6 -> Брендированные плейлисты/каналы | F31: =Предпосылки!$G$6*F$30 -> 500000 | G31: =Предпосылки!$G$6*G$30 -> 507743.75 | H31: =Предпосылки!$G$6*H$30 -> 515607.43 | I31: =Предпосылки!$G$6*I$30 -> 523592.9 | J31: =Предпосылки!$G$6*J$30 -> 531702.05 | K31: =Предпосылки!$G$6*N$30 -> 565414.13 | L31: =Предпосылки!$G$6*L$30 -> 548299.05 | M31: =Предпосылки!$G$6*M$30 -> 556790.83 | N31: =Предпосылки!$G$6*N$30 -> 565414.13 | O31: =Предпосылки!$G$6*O$30 -> 574170.98 | P31: =Предпосылки!$G$6*P$30 -> 583063.46 | Q31: =Предпосылки!$G$6*Q$30 -> 592093.65 | R31: =Предпосылки!$G$6*R$30 -> 601263.7 | S31: =Предпосылки!$G$6*S$30 -> 610575.77 | ... AC31: =Предпосылки!$G$6*AC$30 -> 712008.84
A32: =Предпосылки!B8 -> Реклама перед/после видео | F32: =Предпосылки!$G$8*F$30 -> 99675 | G32: =Предпосылки!$G$8*G$30 -> 101218.72 | H32: =Предпосылки!$G$8*H$30 -> 102786.34 | I32: =Предпосылки!$G$8*I$30 -> 104378.24 | J32: =Предпосылки!$G$8*J$30 -> 105994.8 | K32: =Предпосылки!$G$8*N$30 -> 112715.31 | L32: =Предпосылки!$G$8*L$30 -> 109303.42 | M32: =Предпосылки!$G$8*M$30 -> 110996.25 | N32: =Предпосылки!$G$8*N$30 -> 112715.31 | O32: =Предпосылки!$G$8*O$30 -> 114460.99 | P32: =Предпосылки!$G$8*P$30 -> 116233.7 | Q32: =Предпосылки!$G$8*Q$30 -> 118033.87 | R32: =Предпосылки!$G$8*R$30 -> 119861.92 | S32: =Предпосылки!$G$8*S$30 -> 121718.28 | ... AC32: =Предпосылки!$G$8*AC$30 -> 141938.96
A33: =Предпосылки!B7 -> Спонсорские интеграции в шоу | F33: =Предпосылки!$G$7*F$30 -> 2250000 | G33: =Предпосылки!$G$7*G$30 -> 2284846.9 | H33: =Предпосылки!$G$7*H$30 -> 2320233.4 | I33: =Предпосылки!$G$7*I$30 -> 2356168.1 | J33: =Предпосылки!$G$7*J$30 -> 2392659.2 | K33: =Предпосылки!$G$7*N$30 -> 2544363.6 | L33: =Предпосылки!$G$7*L$30 -> 2467345.7 | M33: =Предпосылки!$G$7*M$30 -> 2505558.8 | N33: =Предпосылки!$G$7*N$30 -> 2544363.6 | O33: =Предпосылки!$G$7*O$30 -> 2583769.4 | P33: =Предпосылки!$G$7*P$30 -> 2623785.6 | Q33: =Предпосылки!$G$7*Q$30 -> 2664421.4 | R33: =Предпосылки!$G$7*R$30 -> 2705686.7 | S33: =Предпосылки!$G$7*S$30 -> 2747591 | ... AC33: =Предпосылки!$G$7*AC$30 -> 3204039.8
A34: =Предпосылки!B9 -> реклама от авторов | F34: =Предпосылки!$G$9*F$30 -> 5316 | G34: =Предпосылки!$G$9*G$30 -> 5398.3315 | H34: =Предпосылки!$G$9*H$30 -> 5481.9382 | I34: =Предпосылки!$G$9*I$30 -> 5566.8397 | J34: =Предпосылки!$G$9*J$30 -> 5653.0562 | K34: =Предпосылки!$G$9*N$30 -> 6011.4831 | L34: =Предпосылки!$G$9*L$30 -> 5829.5155 | M34: =Предпосылки!$G$9*M$30 -> 5919.8002 | N34: =Предпосылки!$G$9*N$30 -> 6011.4831 | O34: =Предпосылки!$G$9*O$30 -> 6104.5859 | P34: =Предпосылки!$G$9*P$30 -> 6199.1307 | Q34: =Предпосылки!$G$9*Q$30 -> 6295.1397 | R34: =Предпосылки!$G$9*R$30 -> 6392.6357 | S34: =Предпосылки!$G$9*S$30 -> 6491.6416 | ... AC34: =Предпосылки!$G$9*AC$30 -> 7570.078
A35: =Предпосылки!B11 -> Подписка на "без рекламы" | F35: =Предпосылки!$G$11*F30 -> 0 | G35: =Предпосылки!$G$11*G30 -> 0 | H35: =Предпосылки!$G$11*H30 -> 0 | I35: =Предпосылки!$G$11*I30 -> 0 | J35: =Предпосылки!$G$11*J30 -> 0 | K35: =Предпосылки!$G$11*N30 -> 0 | L35: =Предпосылки!$G$11*L30 -> 0 | M35: =Предпосылки!$G$11*M30 -> 0 | N35: =Предпосылки!$G$11*N$30 -> 0 | O35: =Предпосылки!$G$11*O30 -> 0 | P35: =Предпосылки!$G$11*P30 -> 0 | Q35: =Предпосылки!$G$11*Q30 -> 0 | R35: =Предпосылки!$G$11*R30 -> 0 | S35: =Предпосылки!$G$11*S30 -> 0 | T35: =Предпосылки!$G$11*T30 -> 0 | U35: =Предпосылки!$G$11*U30 -> 0 | V35: =Предпосылки!$G$11*V30 -> 0 | ... AC35: =Предпосылки!$G$11*AC30 -> 0
A36: =Предпосылки!B10 -> Просмотры контента от онлайн школ | F36: =Предпосылки!$G$10*'Cash Flow'!F$30*Предпосылки!$C$14 -> 12937500 | G36: =Предпосылки!$G$10*'Cash Flow'!G$30*Предпосылки!$C$14 -> 13137870 | H36: =Предпосылки!$G$10*'Cash Flow'!H$30*Предпосылки!$C$14 -> 13341342 | I36: =Предпосылки!$G$10*'Cash Flow'!I$30*Предпосылки!$C$14 -> 13547966 | J36: =Предпосылки!$G$10*'Cash Flow'!J$30*Предпосылки!$C$14 -> 13757790 | K36: =Предпосылки!$G$10*'Cash Flow'!K$30*Предпосылки!$C$14 -> 13970864 | L36: =Предпосылки!$G$10*'Cash Flow'!L$30*Предпосылки!$C$14 -> 14187238 | M36: =Предпосылки!$G$10*'Cash Flow'!M$30*Предпосылки!$C$14 -> 14406963 | ... AC36: =Предпосылки!$G$10*'Cash Flow'!AC$30*Предпосылки!$C$14 -> 18423229
A37: Сумма | B37: =SUM(B32:B32) -> 0 | C37: =SUM(C32:C32) -> 0 | D37: =SUM(D32:D32) -> 0 | E37: =SUM(E32:E32) -> 0 | F37: =SUM(F31:F36) -> 15792491 | G37: =SUM(G31:G36) -> 16037077 | H37: =SUM(H31:H36) -> 16285451 | I37: =SUM(I31:I36) -> 16537672 | J37: =SUM(J31:J36) -> 16793800 | K37: =SUM(K31:K36) -> 17199369 | L37: =SUM(L31:L36) -> 17318016 | M37: =SUM(M31:M36) -> 17586228 | ... AC37: =SUM(AC31:AC36) -> 22488787
A38: =Расходники!A2 -> Капитальные затраты (CapEx) | B38: =Расходники!C2*1000000 -> 9000000 | R38: =Расходники!C2*1000000 -> 9000000
A39: =Расходники!A11 -> Операционные расходы (OpEx) | B39: =Расходники!C11 -> 7245000 | C39: =B39 -> 7245000 | D39: =C39 -> 7245000 | E39: =D39 -> 7245000 | F39: =E39 -> 7245000 | G39: =F39 -> 7245000 | H39: =G39 -> 7245000 | I39: =H39 -> 7245000 | J39: =I39 -> 7245000 | ... AC39: =AB39 -> 7245000
A40: Статья маркетинговых расходов | E40: =Расходники!$C$30 -> 2509500 | F40: =Расходники!$C$30 -> 2509500 | G40: =Расходники!$C$30 -> 2509500 | H40: =Расходники!$C$30 -> 2509500 | I40: =Расходники!$C$30 -> 2509500 | J40: =Расходники!$C$30 -> 2509500 | K40: =Расходники!$C$30 -> 2509500 | L40: =Расходники!$C$30 -> 2509500 | ... AC40: =Расходники!$C$30 -> 2509500
A41: Прибыль до налогообложения | B41: =B37-B38-B39 -> -16245000 | C41: =C37-C38-C39 -> -7245000 | D41: =D37-D38-D39 -> -7245000 | E41: =E37-E38-E39-E40 -> -9754500 | F41: =F11-F38-F39-F40 -> 6037991 | G41: =G37-G38-G39-G40 -> 6282577.2 | H41: =H37-H38-H39-H40 -> 6530951.4 | I41: =I37-I38-I39-I40 -> 6783172.4 | J41: =J37-J38-J39-J40 -> 7039299.6 | K41: =K37-K38-K39-K40 -> 7444868.8 | L41: =L37-L38-L39-L40 -> 7563515.7 | M41: =M37-M38-M39-M40 -> 7831728.5 | N41: =N37-N38-N39-N40 -> 8104095.2 | ... AC41: =AC37-AC38-AC39-AC40 -> 12734287
A42: Налог на прибыль | B42: =IF(B41>0,B41*20%,0) -> 0 | C42: =IF(C41>0,C41*20%,0) -> 0 | D42: =IF(D41>0,D41*20%,0) -> 0 | E42: =IF(E41>0,E41*20%,0) -> 0 | F42: =IF(F41>0,F41*20%,0) -> 1207598.2 | G42: =IF(G41>0,G41*20%,0) -> 1256515.4 | H42: =IF(H41>0,H41*20%,0) -> 1306190.3 | I42: =IF(I41>0,I41*20%,0) -> 1356634.5 | ... AC42: =IF(AC41>0,AC41*20%,0) -> 2546857.3
A43: CF | B43: =SUM(B41:B42) -> -16245000 | C43: =SUM(C41:C42) -> -7245000 | D43: =SUM(D41:D42) -> -7245000 | E43: =SUM(E41:E42) -> -9754500 | F43: =SUM(F41:F42) -> 7245589.2 | G43: =SUM(G41:G42) -> 7539092.6 | H43: =SUM(H41:H42) -> 7837141.7 | I43: =SUM(I41:I42) -> 8139806.8 | ... AC43: =SUM(AC41:AC42) -> 15281144
A44: Дисконтированный CF | B44: =IF(SUM(B41:B42)<0,SUM(B41:B42),0) -> -16245000 | C44: =IF(SUM(C41:C42)<0,SUM(C41:C42),0) -> -7245000 | D44: =IF(SUM(D41:D42)<0,SUM(D41:D42),0) -> -7245000 | E44: =IF(SUM(E41:E42)<0,SUM(E41:E42),0) -> -9754500 | F44: =IF(SUM(F41:F42)<0,SUM(F41:F42),SUM(F41:F42)*1/(1+Предпосылки!$E$22/12)^F29) -> 7154088.7 | G44: =IF(SUM(G41:G42)<0,SUM(G41:G42),SUM(G41:G42)*1/(1+Предпосылки!$E$22/12)^G29) -> 7349881 | H44: =IF(SUM(H41:H42)<0,SUM(H41:H42),SUM(H41:H42)*1/(1+Предпосылки!$E$22/12)^H29) -> 7543962.8 | I44: =IF(SUM(I41:I42)<0,SUM(I41:I42),SUM(I41:I42)*1/(1+Предпосылки!$E$22/12)^I29) -> 7736357.9 | J44: =IF(SUM(J41:J42)<0,SUM(J41:J42),SUM(J41:J42)*1/(1+Предпосылки!$E$22/12)^J29) -> 7927089.5 | K44: =IF(SUM(K41:K42)<0,SUM(K41:K42),SUM(K41:K42)*1/(1+Предпосылки!$E$22/12)^K29) -> 8277934.2 | L44: =IF(SUM(L41:L42)<0,SUM(L41:L42),SUM(L41:L42)*1/(1+Предпосылки!$E$22/12)^L29) -> 8303654.1 | M44: =IF(SUM(M41:M42)<0,SUM(M41:M42),SUM(M41:M42)*1/(1+Предпосылки!$E$22/12)^M29) -> 8489532.5 | ... Q44: =IF(SUM(Q41:Q42)<0,SUM(Q41:Q42),SUM(Q41:Q42)*1/(1+Предпосылки!$E$22/12)^Q29) -> 9217534 | R44: =IF(SUM(R41:R42)<0,SUM(R41:R42),SUM(R41:R42)*1/(1+Предпосылки!$E$23/12)^R29) -> 237929.02 | S44: =IF(SUM(S41:S42)<0,SUM(S41:S42),SUM(S41:S42)*1/(1+Предпосылки!$E$23/12)^S29) -> 9463132.1 | T44: =IF(SUM(T41:T42)<0,SUM(T41:T42),SUM(T41:T42)*1/(1+Предпосылки!$E$23/12)^T29) -> 9628538.9 | U44: =IF(SUM(U41:U42)<0,SUM(U41:U42),SUM(U41:U42)*1/(1+Предпосылки!$E$23/12)^U29) -> 9792261.4 | V44: =IF(SUM(V41:V42)<0,SUM(V41:V42),SUM(V41:V42)*1/(1+Предпосылки!$E$23/12)^V29) -> 9954323.2 | W44: =IF(SUM(W41:W42)<0,SUM(W41:W42),SUM(W41:W42)*1/(1+Предпосылки!$E$23/12)^W29) -> 10114748 | X44: =IF(SUM(X41:X42)<0,SUM(X41:X42),SUM(X41:X42)*1/(1+Предпосылки!$E$23/12)^X29) -> 10273558 | Y44: =IF(SUM(Y41:Y42)<0,SUM(Y41:Y42),SUM(Y41:Y42)*1/(1+Предпосылки!$E$23/12)^Y29) -> 10430776 | Z44: =IF(SUM(Z41:Z42)<0,SUM(Z41:Z42),SUM(Z41:Z42)*1/(1+Предпосылки!$E$24/12)^Z29) -> 10586425 | AA44: =IF(SUM(AA41:AA42)<0,SUM(AA41:AA42),SUM(AA41:AA42)*1/(1+Предпосылки!$E$24/12)^AA29) -> 10740527 | AB44: =IF(SUM(AB41:AB42)<0,SUM(AB41:AB42),SUM(AB41:AB42)*1/(1+Предпосылки!$E$24/12)^AB29) -> 10893103 | AC44: =IF(SUM(AC41:AC42)<0,SUM(AC41:AC42),SUM(AC41:AC42)*1/(1+Предпосылки!$E$24/12)^AC29) -> 11044175
A46: NPV | B46: =SUM(B44:AC44) -> 1.7123828e+08
A47: Срок окупаемости (мес) | B47: 6
A48: OpEX | B48: =SUM(B39:AC39) -> 202860000
A49: ROI | B49: =(SUM(B43:AC43)-SUM(B38:AC39))/SUM(B38:AC39)*100% -> -0.03204151
A50: IRR | B50: =IRR(B43:AC43) -> 0.15979542
A51: Стоимость привлечения одного клиента | B51: =(F30^AC29+G30^AB29+H30^AA29+I30^I29+J30^Y29+K30^X29+L30^W29+M30^V29+N30^U29+O30^T29+P30^S29+Q30^R29+R30^Q29+S30^P29+T30^O29+U30^N29+V30^M29+W30^L29+X30^J29+Y30^I29+Z30^H29+AA30^G29+AB30^F29+AC30^Z29+AC29)*Предпосылки!$E$2/SUM('Cash Flow'!B38:AC40) -> 6.4857667
A53: Пессимистичный сценарий
B54: 46023 | C54: 46054 | D54: 46082 | E54: 46113 | F54: 46143 | G54: 46174 | H54: 46204 | I54: 46235 | J54: 46266 | K54: 46296 | L54: 46327 | M54: 46357 | N54: 46388 | O54: 46419 | P54: 46447 | Q54: 46478 | R54: 46508 | S54: 46539 | T54: 46569 | U54: 46600 | V54: 46631 | W54: 46661 | X54: 46692 | Y54: 46722 | Z54: 46753 | AA54: 46784 | AB54: 46813 | AC54: 46844
A55: Период (мес.) | F55: 1 | G55: 2 | H55: 3 | I55: 4 | J55: 5 | K55: 6 | L55: 7 | M55: 8 | N55: 9 | O55: 10 | P55: 11 | Q55: 12 | R55: 13 | S55: 14 | T55: 15 | U55: 16 | V55: 17 | W55: 18 | X55: 19 | Y55: 20 | Z55: 21 | AA55: 22 | AB55: 23 | AC55: 24
A56: Конверсия | B56: 0 | C56: 0 | D56: 0 | E56: 0 | F56: 0.05 | G56: =F56*(1+Предпосылки!$C$18/20) -> 0.050774375 | H56: =G56*(1+Предпосылки!$C$18/20) -> 0.051560743 | I56: =H56*(1+Предпосылки!$C$18/20) -> 0.05235929 | J56: =I56*(1+Предпосылки!$C$18/20) -> 0.053170205 | K56: =J56*(1+Предпосылки!$C$18/20) -> 0.053993678 | L56: =K56*(1+Предпосылки!$C$18/20) -> 0.054829905 | M56: =L56*(1+Предпосылки!$C$18/20) -> 0.055679083 | N56: =M56*(1+Предпосылки!$C$18/20) -> 0.056541413 | ... AC56: =AB56*(1+Предпосылки!$C$18/20) -> 0.071200884
A57: =A31 -> Брендированные плейлисты/каналы | F57: =Предпосылки!$G$6*F$56 -> 500000 | G57: =Предпосылки!$G$6*G$56 -> 507743.75 | H57: =Предпосылки!$G$6*H$56 -> 515607.43 | I57: =Предпосылки!$G$6*I$56 -> 523592.9 | J57: =Предпосылки!$G$6*J$56 -> 531702.05 | K57: =Предпосылки!$G$6*K$56 -> 539936.78 | L57: =Предпосылки!$G$6*L$56 -> 548299.05 | M57: =Предпосылки!$G$6*M$56 -> 556790.83 | ... AC57: =Предпосылки!$G$6*AC$56 -> 712008.84
A58: =A32 -> Реклама перед/после видео | F58: =Предпосылки!$G$8*F$56 -> 99675 | G58: =Предпосылки!$G$8*G$56 -> 101218.72 | H58: =Предпосылки!$G$8*H$56 -> 102786.34 | I58: =Предпосылки!$G$8*I$56 -> 104378.24 | J58: =Предпосылки!$G$8*J$56 -> 105994.8 | K58: =Предпосылки!$G$8*K$56 -> 107636.4 | L58: =Предпосылки!$G$8*L$56 -> 109303.42 | M58: =Предпосылки!$G$8*M$56 -> 110996.25 | ... AC58: =Предпосылки!$G$8*AC$56 -> 141938.96
A59: =A33 -> Спонсорские интеграции в шоу | F59: =Предпосылки!$G$7*F$56 -> 2250000 | G59: =Предпосылки!$G$7*G$56 -> 2284846.9 | H59: =Предпосылки!$G$7*H$56 -> 2320233.4 | I59: =Предпосылки!$G$7*I$56 -> 2356168.1 | J59: =Предпосылки!$G$7*J$56 -> 2392659.2 | K59: =Предпосылки!$G$7*K$56 -> 2429715.5 | L59: =Предпосылки!$G$7*L$56 -> 2467345.7 | M59: =Предпосылки!$G$7*M$56 -> 2505558.8 | ... AC59: =Предпосылки!$G$7*AC$56 -> 3204039.8
A60: =A34 -> реклама от авторов | F60: =Предпосылки!$G$9*F$56 -> 5316 | G60: =Предпосылки!$G$9*G$56 -> 5398.3315 | H60: =Предпосылки!$G$9*H$56 -> 5481.9382 | I60: =Предпосылки!$G$9*I$56 -> 5566.8397 | J60: =Предпосылки!$G$9*J$56 -> 5653.0562 | K60: =Предпосылки!$G$9*K$56 -> 5740.6079 | L60: =Предпосылки!$G$9*L$56 -> 5829.5155 | M60: =Предпосылки!$G$9*M$56 -> 5919.8002 | ... AC60: =Предпосылки!$G$9*AC$56 -> 7570.078
A61: =A35 -> Подписка на "без рекламы" | F61: =Предпосылки!$G$11*F$56 -> 0 | G61: =Предпосылки!$G$11*G$56 -> 0 | H61: =Предпосылки!$G$11*H$56 -> 0 | I61: =Предпосылки!$G$11*I$56 -> 0 | J61: =Предпосылки!$G$11*J$56 -> 0 | K61: =Предпосылки!$G$11*K$56 -> 0 | L61: =Предпосылки!$G$11*L$56 -> 0 | M61: =Предпосылки!$G$11*M$56 -> 0 | ... AC61: =Предпосылки!$G$11*AC$56 -> 0
A62: =Предпосылки!B10 -> Просмотры контента от онлайн школ | F62: =Предпосылки!$G$10*'Cash Flow'!F$56*Предпосылки!$C$14*0.7 -> 9056250 | G62: =Предпосылки!$G$10*'Cash Flow'!G$56*Предпосылки!$C$14*0.7 -> 9196508.7 | H62: =Предпосылки!$G$10*'Cash Flow'!H$56*Предпосылки!$C$14*0.7 -> 9338939.6 | I62: =Предпосылки!$G$10*'Cash Flow'!I$56*Предпосылки!$C$14*0.7 -> 9483576.4 | J62: =Предпосылки!$G$10*'Cash Flow'!J$56*Предпосылки!$C$14*0.7 -> 9630453.3 | K62: =Предпосылки!$G$10*'Cash Flow'!K$56*Предпосылки!$C$14*0.7 -> 9779605 | L62: =Предпосылки!$G$10*'Cash Flow'!L$56*Предпосылки!$C$14*0.7 -> 9931066.6 | M62: =Предпосылки!$G$10*'Cash Flow'!M$56*Предпосылки!$C$14*0.7 -> 10084874 | ... AC62: =Предпосылки!$G$10*'Cash Flow'!AC$56*Предпосылки!$C$14*0.7 -> 12896260
A63: Сумма | B63: =SUM(B58:B58) -> 0 | C63: =SUM(C58:C58) -> 0 | D63: =SUM(D58:D58) -> 0 | E63: =SUM(E58:E58) -> 0 | F63: =SUM(F57:F62) -> 11911241 | G63: =SUM(G57:G62) -> 12095716 | H63: =SUM(H57:H62) -> 12283049 | I63: =SUM(I57:I62) -> 12473282 | J63: =SUM(J57:J62) -> 12666462 | K63: =SUM(K57:K62) -> 12862634 | L63: =SUM(L57:L62) -> 13061844 | M63: =SUM(M57:M62) -> 13264140 | ... AC63: =SUM(AC57:AC62) -> 16961818
A64: =Расходники!A2 -> Капитальные затраты (CapEx) | B64: =Расходники!C2*1000000 -> 9000000 | R64: =Расходники!C2*1000000 -> 9000000
A65: =Расходники!A11 -> Операционные расходы (OpEx) | B65: =Расходники!C11 -> 7245000 | C65: =B65 -> 7245000 | D65: =C65 -> 7245000 | E65: =D65 -> 7245000 | F65: =E65 -> 7245000 | G65: =F65 -> 7245000 | H65: =G65 -> 7245000 | I65: =H65 -> 7245000 | J65: =I65 -> 7245000 | ... AC65: =AB65 -> 7245000
A66: Статья маркетинговых расходов | E66: =Расходники!$C$30 -> 2509500 | F66: =Расходники!$C$30 -> 2509500 | G66: =Расходники!$C$30 -> 2509500 | H66: =Расходники!$C$30 -> 2509500 | I66: =Расходники!$C$30 -> 2509500 | J66: =Расходники!$C$30 -> 2509500 | K66: =Расходники!$C$30 -> 2509500 | L66: =Расходники!$C$30 -> 2509500 | ... AC66: =Расходники!$C$30 -> 2509500
A67: Прибыль до налогообложения | B67: =B63-B64-B65 -> -16245000 | C67: =C63-C64-C65 -> -7245000 | D67: =D63-D64-D65 -> -7245000 | E67: =E63-E64-E65-E66 -> -9754500 | F67: =F63-F64-F65-F66 -> 2156741 | G67: =G63-G64-G65-G66 -> 2341216.3 | H67: =H63-H64-H65-H66 -> 2528548.8 | I67: =I63-I64-I65-I66 -> 2718782.5 | J67: =J63-J64-J65-J66 -> 2911962.4 | K67: =K63-K64-K65-K66 -> 3108134.3 | L67: =L63-L64-L65-L66 -> 3307344.3 | ... AC67: =AC63-AC64-AC65-AC66 -> 7207317.9
A68: Налог на прибыль | B68: =IF(B67>0,B67*20%,0) -> 0 | C68: =IF(C67>0,C67*20%,0) -> 0 | D68: =IF(D67>0,D67*20%,0) -> 0 | E68: =IF(E67>0,E67*20%,0) -> 0 | F68: =IF(F67>0,F67*20%,0) -> 431348.2 | G68: =IF(G67>0,G67*20%,0) -> 468243.27 | H68: =IF(H67>0,H67*20%,0) -> 505709.75 | I68: =IF(I67>0,I67*20%,0) -> 543756.49 | ... AC68: =IF(AC67>0,AC67*20%,0) -> 1441463.6
A69: CF | B69: =SUM(B67:B68) -> -16245000 | C69: =SUM(C67:C68) -> -7245000 | D69: =SUM(D67:D68) -> -7245000 | E69: =SUM(E67:E68) -> -9754500 | F69: =SUM(F67:F68) -> 2588089.2 | G69: =SUM(G67:G68) -> 2809459.6 | H69: =SUM(H67:H68) -> 3034258.5 | I69: =SUM(I67:I68) -> 3262539 | ... AC69: =SUM(AC67:AC68) -> 8648781.4
A70: Дисконтированный CF | B70: =IF(SUM(B67:B68)<0,SUM(B67:B68),0) -> -16245000 | C70: =IF(SUM(C67:C68)<0,SUM(C67:C68),0) -> -7245000 | D70: =IF(SUM(D67:D68)<0,SUM(D67:D68),0) -> -7245000 | E70: =IF(SUM(E67:E68)<0,SUM(E67:E68),0) -> -9754500 | F70: =IF(SUM(F67:F68)<0,SUM(F67:F68),SUM(F67:F68)*1/(1+Предпосылки!$E$22/12)^F55) -> 2555405.7 | G70: =IF(SUM(G67:G68)<0,SUM(G67:G68),SUM(G67:G68)*1/(1+Предпосылки!$E$22/12)^G55) -> 2738949.5 | H70: =IF(SUM(H67:H68)<0,SUM(H67:H68),SUM(H67:H68)*1/(1+Предпосылки!$E$22/12)^H55) -> 2920750.2 | I70: =IF(SUM(I67:I68)<0,SUM(I67:I68),SUM(I67:I68)*1/(1+Предпосылки!$E$22/12)^I55) -> 3100831.4 | J70: =IF(SUM(J67:J68)<0,SUM(J67:J68),SUM(J67:J68)*1/(1+Предпосылки!$E$22/12)^J55) -> 3279216.4 | K70: =IF(SUM(K67:K68)<0,SUM(K67:K68),SUM(K67:K68)*1/(1+Предпосылки!$E$22/12)^K55) -> 3455928.1 | L70: =IF(SUM(L67:L68)<0,SUM(L67:L68),SUM(L67:L68)*1/(1+Предпосылки!$E$22/12)^L55) -> 3630989.1 | M70: =IF(SUM(M67:M68)<0,SUM(M67:M68),SUM(M67:M68)*1/(1+Предпосылки!$E$22/12)^M55) -> 3804421.9 | ... Q70: =IF(SUM(Q67:Q68)<0,SUM(Q67:Q68),SUM(Q67:Q68)*1/(1+Предпосылки!$E$22/12)^Q55) -> 4482309 | R70: =IF(SUM(R67:R68)<0,SUM(R67:R68),SUM(R67:R68)*1/(1+Предпосылки!$E$23/12)^R55) -> -4430906.3 | S70: =IF(SUM(S67:S68)<0,SUM(S67:S68),SUM(S67:S68)*1/(1+Предпосылки!$E$23/12)^S55) -> 4757052.5 | T70: =IF(SUM(T67:T68)<0,SUM(T67:T68),SUM(T67:T68)*1/(1+Предпосылки!$E$23/12)^T55) -> 4913797.2 | U70: =IF(SUM(U67:U68)<0,SUM(U67:U68),SUM(U67:U68)*1/(1+Предпосылки!$E$23/12)^U55) -> 5068841.5 | V70: =IF(SUM(V67:V68)<0,SUM(V67:V68),SUM(V67:V68)*1/(1+Предпосылки!$E$23/12)^V55) -> 5222209.3 | W70: =IF(SUM(W67:W68)<0,SUM(W67:W68),SUM(W67:W68)*1/(1+Предпосылки!$E$23/12)^W55) -> 5373923.6 | X70: =IF(SUM(X67:X68)<0,SUM(X67:X68),SUM(X67:X68)*1/(1+Предпосылки!$E$23/12)^X55) -> 5524007.5 | Y70: =IF(SUM(Y67:Y68)<0,SUM(Y67:Y68),SUM(Y67:Y68)*1/(1+Предпосылки!$E$23/12)^Y55) -> 5672483.6 | Z70: =IF(SUM(Z67:Z68)<0,SUM(Z67:Z68),SUM(Z67:Z68)*1/(1+Предпосылки!$E$24/12)^Z55) -> 5819374.3 | AA70: =IF(SUM(AA67:AA68)<0,SUM(AA67:AA68),SUM(AA67:AA68)*1/(1+Предпосылки!$E$24/12)^AA55) -> 5964701.7 | AB70: =IF(SUM(AB67:AB68)<0,SUM(AB67:AB68),SUM(AB67:AB68)*1/(1+Предпосылки!$E$24/12)^AB55) -> 6108487.6 | AC70: =IF(SUM(AC67:AC68)<0,SUM(AC67:AC68),SUM(AC67:AC68)*1/(1+Предпосылки!$E$24/12)^AC55) -> 6250753.3
A72: NPV | B72: =SUM(B70:AC70) -> 58161937
A73: Срок окупаемости (мес) | B73: 12
A74: OpEX | B74: =SUM(B65:AC65) -> 202860000
A75: ROI | B75: =(SUM(B69:AC69)-SUM(B64:AC65))/SUM(B64:AC65)*100% -> -0.63619826
A76: IRR | B76: =IRR(B69:AC69) -> 0.075745009
A77: Стоимость привлечения одного клиента | B77: =(F56^AC55+G56^AB55+H56^AA55+I56^I55+J56^Y55+K56^X55+L56^W55+M56^V55+N56^U55+O56^T55+P56^S55+Q56^R55+R56^Q55+S56^P55+T56^O55+U56^N55+V56^M55+W56^L55+X56^J55+Y56^I55+Z56^H55+AA56^G55+AB56^F55+AC56^Z55+AC55)*Предпосылки!$E$2/SUM('Cash Flow'!B64:AC66) -> 6.4857667
