Workbook

Sheet Предпосылки
A1: Предпосылки расчетов, описание проекта
A2: Цифровые финансовые активы (ЦФА) - это цифровые права на различные активы, которые оформляются и учитываются с помощью технологии блокчейн или других распределенных реестров. Они являются новым инструментом для привлечения инвестиций компаниями и предоставления физлицам новых возможностей для вложения средств в цифровом формате, что делает их удобнее и быстрее, чем традиционные финансовые инструменты.
A3: Цель работы - разработать концепцию и линейку продуктов на рынке токенизированных активов (ЦФА), которые смогут трансформировать традиционный финансовый рынок и привлечь широкие массы населения
A4: Наш проект предлагает линейку цифровых финансовых активов (ЦФА), предназначенных специально для индустрии видеоигр. Мы выступаем в роли провайдера решений для разработчиков, предлагая им готовые инструменты для токенизации их проектов, и в роли эмитента, обеспечивая юридическую и техническую поддержку выпуска. Это создает новую экономику взаимоотношений между игроками и студиями, открывая финансовые возможности для всех участников. Наш продукт решает задачи: Для игроков: вложение времени и денег в внутриигровые предметы, которые приносят реальную финансовую отдачу. Для разработчиков: привлечения финансирования и долгосрочное удержание и монетизация лояльной аудитории. Уникальность нашего решения заключается в том, что мы фокусируемся на продуктах, а не на платформе: предлагаем готовые решения под конкретные нужды. Разрабатываемые продукты обладают низким порогом входа, чтобы они были понятны и доступны обычным игрокам, а не только профессиональным инвесторам. Данные ЦФА не существуют в вакууме: их ценность и функционал напрямую связаны с геймплеем и развитием конкретной игры
A6: *Ячейки, выделенные зеленым цветом участвуют в расчетах - их значения можно менять*
A8: Анализ рынка ЦФА
A30: Источник: https://xn--80a3bf.xn--p1ai/itogi-rynka-cfa-2024.html
D31: В 2024 году объем рынка цифровых финансовых активов (ЦФА) значительно увеличился. Если в 2023 году он составлял 60 млрд рублей, то в 2024 году достиг 346,5 млрд рублей. В 2024 г. объемы рынка ЦФА существенно выросли благодаря активному выходу на рынок как крупных эмитентов, так и небольших компаний. В течение года объем первичных размещений ЦФА вырос почти в 9 раз и составил 594 млрд рублей. В 2024 г. объемы размещений на рынке ЦФА существенно вырос благодаря активному выходу на рынок как крупных эмитентов, так и небольших компаний. В течение года объем первичных размещений ЦФА вырос почти в 9 раз и составил 594 млрд рублей. Лидером по количеству выпусков стала платформа А-Токен - 247 выпусков. На втором месте Сбербанк- 73 выпуска, а третье место занял Атомайз- 72 выпуска. По объему размещений лидером стала платформа Мастерчейн- 112,2 млрд рублей, на втором месте Сбербанк-82,7 млрд рублей, на третьем А-Токен- 69,2 млрд рублей. Таким образом, рынок ЦФА - это активно развивающаяся отрасль, имеющая большой потенциал. Эксперты отмечают, что рынок токенизированных активов еще не успел сформироваться ни в одной стране. Именно поэтому у него огромные перспективы. При этом на прогресс рынка способна позитивно повлиять не только открытость финсистемы, но и ее устойчивость. Еще более позитивное мнение высказывают другие эксперты: они предполагают, что объем отечественного «цифрового» рынка к следующему десятилетию достигнет суммы, превышающей 25 трлн рублей. На сегодняшний день специалист оценивает его объемы в пределах 20 млрд рублей.
A32: Конкуренты Альфа Банка
E53: Источник: | F53: https://xn--80a3bf.xn--p1ai/cfa-tokenizacia.html
F54: https://www.cbr.ru/Collection/Collection/File/55196/review_2024.pdf
A55: Анализ рынка видеоигр
A57: Объем целевой аудитории
B58: Описание | C58: Доля населения РФ | D58: Кол-во чел. (млн) | E58: Источник
A59: TAM | B59: Аудитория, играющая в видеоигры (на 2022 год) | C59: 0.6 | D59: =87.671956 -> 87.671956 | E59: https://nafi.ru/projects/it-i-telekom/geyming-v-rossii-2022-sotsialnye-i-ekonomicheskie-effekty/
A60: SAM | B60: Аудитория, которая называет себя "геймерами" | C60: 0.17 | D60: 25 | E60: https://www.tadviser.ru/index.php/%D0%A1%D1%82%D0%B0%D1%82%D1%8C%D1%8F:%D0%9A%D0%BE%D0%BC%D0%BF%D1%8C%D1%8E%D1%82%D0%B5%D1%80%D0%BD%D1%8B%D0%B5_%D0%B8_%D0%B2%D0%B8%D0%B4%D0%B5%D0%BE%D0%B8%D0%B3%D1%80%D1%8B_(%D1%80%D0%BE%D1%81%D1%81%D0%B8%D0%B9%D1%81%D0%BA%D0%B8%D0%B9_%D1%80%D1%8B%D0%BD%D0%BE%D0%BA)#:~:text=%D0%9F%D1%83%D1%82%D0%B8%D0%BD%20%D0%BF%D0%BE%D0%B4%D1%87%D0%B5%D1%80%D0%BA%D0%BD%D1%83%D0%BB%20%D0%B2%D0%B0%D0%B6%D0%BD%D0%BE%D1%81%D1%82%D1%8C%20%D1%80%D0%B0%D0%B7%D0%B2%D0%B8%D1%82%D0%B8%D1%8F%20%D0%BE%D1%82%D0%B5%D1%87%D0%B5%D1%81%D1%82%D0%B2%D0%B5%D0%BD%D0%BD%D0%BE%D0%B9,%D1%82%D1%80%D0%B0%D0%B4%D0%B8%D1%86%D0%B8%D0%BE%D0%BD%D0%BD%D1%8B%D1%85%20%D1%86%D0%B5%D0%BD%D0%BD%D0%BE%D1%81%D1%82%D0%B5%D0%B9%20%D1%87%D0%B5%D1%80%D0%B5%D0%B7%20%D1%81%D0%BE%D0%B7%D0%B4%D0%B0%D0%BD%D0%B8%D0%B5%20%D0%BA%D0%BE%D0%BD%D1%82%D0%B5%D0%BD%D1%82%D0%B0.&text=%D0%9F%D1%80%D0%B5%D0%B7%D0%B8%D0%B4%D0%B5%D0%BD%D1%82%20%D0%BE%D1%82%D0%BC%D0%B5%D1%82%D0%B8%D0%BB%2C%20%D1%87%D1%82%D0%BE%20%D1%80%D0%BE%D1%81%D1%81%D0%B8%D0%B9%D1%81%D0%BA%D0%B0%D1%8F%20%D0%B8%D0%BD%D0%B4%D1%83%D1%81%D1%82%D1%80%D0%B8%D1%8F,%D1%80%D0%BE%D0%BB%D1%8C%20%D0%B2%20%D0%B2%D0%BE%D1%81%D0%BF%D0%B8%D1%82%D0%B0%D0%BD%D0%B8%D0%B8%20%D0%BC%D0%BE%D0%BB%D0%BE%D0%B4%D1%8B%D1%85%20%D0%BF%D0%BE%D0%BA%D0%BE%D0%BB%D0%B5%D0%BD%D0%B8%D0%B9.
A61: SOM | B61: Доля SAM, которую хотим захватить за 3 года | C61: 0.05 | D61: 7.3 | E61: https://t-j.ru/kto-ti-gamer/?utm_referrer=https%3A%2F%2Fwww.google.com%2F
C62: *Доля 5% населения - экспертная оценка авторов, основанная на показателях роста рынка ЦФА и индустрии видеоигр, а также на собственном проведенном исследовании среди любителей видеоигр, который показал высокую заинтересованность людей в инвестировании через видеоигры (около 50% от числа опрошенных)
A80: Источник: https://nafi.ru/projects/it-i-telekom/geyming-v-rossii-2022-sotsialnye-i-ekonomicheskie-effekty/
D82: На основании анализа статистических данных за период с 2018 по 2022 год можно констатировать устойчивый рост и значительный потенциал развития рынка видеоигр в Российской Федерации. По состоянию на 2022 год охват аудитории составлял 60% от общего населения страны, что равняется 88 млн человек. Из динамики роста можно заметить, что за четырехлетний период доля геймеров в России увеличилась с 18% до 60%, демонстрируя трехкратный прирост. В структуре аудитории на 2025 год выделяется ядро активных пользователей - 25 миллионов человек (17%), идентифицирующих себя как "геймеры". Также стоит отметить, что увеличилась степень осведомленности людей о киберспорте: доля респондентов, хорошо знакомых с этим понятием, увеличилась с 19% до 73%, а доля тех, кто слышит о киберспорте впервые, сократилась с 73% до 10%. График динамики российского рынка видеоигр демонстрирует устойчивый рост на протяжении всего анализируемого периода. В 2016 году объем рынка составлял 91 млрд рублей, а по итогам 2024 года рынок составлял 173 млрд руб, прогноз на 2025 год - 200 млрд рублей. Таким образом, за 8 лет рынок видеоигр вырос практически в 2 раза, причем наибольший рост на 47% пришелся на период пандемии коронавируса. Таким образом, российский рынок видеоигр демонстрирует значимые темпы роста, что подтверждается как показателями охвата аудитории, так и изменениями в росте рынка видеоигр. Данный рынок видеоигр в России продолжает оставаться одной из наиболее динамично развивающихся отраслей цифровой экономики с устойчивой положительной динамикой, что говорит о заинтересованности населением данной сферой и наличии потенциала к расширению.
A103: Истоник: https://strategy.ru/research/research/analiz-rossiyskogo-i-mirovogo-rynkov-videoigr-77/
A105: Потенциальные компании - патрнеры | B105: Выручка 2024 г. (прирост относительно 2023 г.) | D105: К потенциальным партнерам проекта относится 10 российских компаний-разработчиков видеоигр. Такие компании будут выступать в роли эмитента ЦФА (юр. лицо или ИП, который выпускает цифровые финансовые активы (ЦФА) для привлечения финансирования). Основным условием для возможности компании стать эмитентом - годовая выручка в размере не менее 1 млрд рублей. Для того, чтобы выпустить ЦФА компании необходимо всего лишь получить статус эмитента на платформе А-Токен (Оператор информационной системы), определить параметры размещения ЦФА и подготовить решение о выпуске. Все издержки по выпуску и размещению ЦФА берет на себя оператор. Эмитент несет издержки в размере 1,5-3% от суммы выпуска. Далее будут производиться расчеты относительно компании-эмитента, ее расходов и выручки от публикации ЦФА
A106: 1. «Леста Игры» | B106: 35 млрд рублей (+59,1%)
A107: 2. Astrum Entertainment | B107: 9,1 млрд рублей (-15,7%)
A108: 3. Krista Games | B108: 3,53 млрд рублей (+275,2%)
A109: 4. Innova | B109: 2,85 млрд рублей (+1,6%)
A110: 5. CarX Technologies | B110: 2,21 млрд рублей (-4,7%)
A111: 6. «СофтКлаб» | B111: 1,76 млрд рублей (-7,3%)
A112: 7. FunFlow | B112: 1,45 млрд рублей (+83%)
A113: 8. BlackHub Games | B113: 1,25 млрд рублей (+189%)
A114: 9. «Крейзи Панда Рус» | B114: 992,3 млн рублей (+24%)
A115: 10. AbsolutSoft | B115: 791,4 млн рублей (+24%)
A118: Линейка продуктов
A119: *Ячейки, выделенные зеленым цветом участвуют в расчетах - их значения можно менять*
A121: Продукт | B121: Описание | C121: Тип инвестора | D121: Цена приобретения ЦФА при выпуске* | E121: Softcap** количество | F121: Softcap сумма (руб.) | G121: Hardcap*** количество | H121: Hardcap сумма (руб.) | I121: Срок размещения (мес.) | J121: Условие к погашению | K121: Количество выпусков | L121: % в день даты погашения | N121: Процент к погашению | O121: Дата обращения | P121: Источник
A122: 1. ЦФА на скины | B122: ЦФА, обеспеченные редкими предметами, валютами или ресурсами внутри игры. Представляет право на конкретный внутриигровой актив. | C122: Неквал | D122: 1000 | E122: 1000 | F122: =D122*E122 -> 1000000 | G122: 100000 | H122: =D122*G122 -> 100000000 | I122: 12 | J122: В конце срока | K122: 3 | L122: Ставка по 10-летним ОФЗ**** + спред 1.5% — пересматривается раз в квартал. | M122: 0.146 | N122: =M122+1.5% -> 0.161 | O122: 45927 | P122: https://ru.tradingeconomics.com/russia/government-bond-yield
A123: 2. Fan-токен | B123: Предоставляет держателям право голоса в ключевых решениях по развитию игры и доступ к эксклюзивному контенту | C123: Неквал | D123: =D122 -> 1000 | E123: 1000 | F123: =D123*E123 -> 1000000 | G123: 100000 | H123: =D123*G123 -> 100000000 | I123: 12 | J123: В конце срока | K123: 3 | L123: Ключевая ставка ЦБ**** РФ + 1,5% — обновляется при каждом изменении ключевой ставки. | M123: 0.17 | N123: =M124+2% -> 0.19 | O123: 45927 | P123: https://cbr.ru/hd_base/KeyRate/
A124: 3. ЦФА на доход эмитента | B124: ЦФА, привязанный к годовой доходности компании-эмитента | C124: Квал (условие: сумма на инвест. счете от 12 млн руб.) | D124: =D123 -> 1000 | E124: 1000 | F124: =D124*E124 -> 1000000 | G124: 100000 | H124: =D124*G124 -> 100000000 | I124: 12 | J124: В конце срока | K124: 3 | L124: Доходность = RUONIA + 3% — с ежемесячной капитализацией. | M124: 0.17 | N124: =M124+3% -> 0.2 | O124: 45927 | P124: https://cbr.ru/hd_base/ruonia/dynamics/
A125: Итог | E125: =SUM(E122:E124) -> 3000 | F125: =SUM(F122:F124) -> 3000000 | G125: =SUM(G122:G124) -> 300000 | H125: =SUM(H122:H124) -> 300000000 | J125: Ежегодное размещение | L125: Максимальная сумма | M125: =H122*N122+H123*N123+H124*N124 -> 55100000
A126: *в дату погашения инвестор получает выплату в виде стоимости ЦФА и процент к погашению
A127: **Softcap - минимальное количество выпускаемых ЦФА и (или) предельная минимальная сумма денежных средств, передаваемых в оплату ЦФА, указанные Эмитентом в Решении о Выпуске ЦФА, по достижении которых Выпуск ЦФА признается состоявшимся (завершенным).
A128: ***Hardcap - Максимальное количество выпускаемых ЦФА и (или) предельная сумма денежных средств, передаваемых в оплату ЦФА, указанные Эмитентом в условиях Решения о Выпуске ЦФА, по достижении которых Выпуск ЦФА признается завершенным.
A130: ****на 30.09.205 для квалифицированных инвесторов возможно приобретение ЦФА только по фиксированным процентам, поэтому на день погашения будет выплачивать процент, установленный в день приобретения ЦФА (аналогично вкладу). Но если оглашенные меры 25.09.2025 главой ЦБ Эльвирой Набиулиной вступят в силу, то ставки примут плавающий характер.
A131: Возможность выплат по ставкам на перспективу: Глава ЦБ Эльвира Набиуллина в своем выступлении на форуме Ассоциации банков России представила планы ЦБ по развитию рынка ЦФА: "Первая мера заключается в расширении линейки цифровых финансовых активов для неквалифицированных инвесторов. В ближайшее время мы планируем направить в Министерство юстиции указание, согласно которому с 1 января следующего года неквалифицированные инвесторы получат возможность приобретать цифровые финансовые активы. Доходность таких активов будет зависеть от базовой ставки Банка России и других индикаторов денежного рынка, включая так называемые плавающие ставки."
A138: Источник: https://www.finam.ru/publications/item/tsb-sovmestno-s-uchastnikami-rynka-tsfa-opredelil-shagi-po-ego-razvitiyu-20250925-1643/
A140: Предпосылки для расчёта Cash-flow
B141: Характер активности аудитории | C141: Обоснование | E141: 1 год | G141: 2 год | I141: Источник
A142: Сценарий 1 (Оптимистичный) | B142: Органический, устойчивый спрос. Покупка ЦФА происходит в спокойном темпе без активного стимулирования со стороны эмитента. | C142: Глобальный тренд: мировой рост токенизации активов. Российский рынок: во II квартале 2025 г. объем ЦФА в обращении вырос на 86,1% по сравнению с началом года, что свидетельствует о высокой динамике рынка. | E142: Ранние последователи: аудитория, совмещающая паттерны поведения: активное времяпровождение в играх и совершение сделок на финансовом рынке (24%) - исследование команды. | G142: Естественный рост: укрепление позиций "специфических" ЦФА (Fan-токены, ЦФА на игровые предметы) и общий рост популярности класса активов. | I142: https://ict.moscow/analytics/mezhdunarodnyi-opyt-tokenizatsii-aktivov/ https://bosfera.ru/press-release/rossiyskiy-rynok-cfa-rezko-vyros-v-2025-godu
A143: Сценарий 2 | B143: Умеренный рост после начального этапа адаптации. | C143: Сочетание органического спроса и точечных маркетинговых усилий. | E143: Поведение аудитории аналогично пессимистичному сценарию, но компания несет минимальные издержки на пиар компании.
A144: Сценарий 3 (Пессимистичный) | B144: Вялый, инертный спрос. Требуется постоянное "подогревание" интереса через PR-кампании и доказательство инвестиционной привлекательности ЦФА в игровой индустрии. | C144: Высокие барьеры: скептицизм аудитории, низкая осведомленность. Необходимость инвестиций в просвещение: требуются значительные ресурсы для формирования спроса. | E144: Низкая конверсия, ядро — квалифицированные инвесторы. Преимущественно покупки со стороны профессиональных инвесторов, понимающих продукт. Выплата по ЦФА на скины не предполагается, в пессимистичном варианте инвестор получает физический продукт. | G144: Постепенное подключение игровой аудитории. Рост возможен только после продолжительных разъяснительных и маркетинговых кампаний. Делигирование задач по аналитике и маркетингу основным отделам компании через полгода.
A146: Конверсия рынка ЦФА
A147: Тип | B147: Процент | C147: Описание
A148: Конверсия приобретения ЦФА в месяц (Оптимистичный сценарий) | B148: 0.14 | C148: Предполагаем, что спрос на скины и участие в закрытом сообществе разработчика одинаковы. А ЦФА на доход эмитента для квальных инвесторов выше на 2%.
A149: Конверсия приобретения ЦФА в месяц (Пессимистичный сценарий) | B149: 0.07
A150: Конверсия приобретения ЦФА в месяц после PR компаний | B150: =(B149+B148)/2+4% -> 0.145 | C150: Применяются затраты из списка (одна статья расходов или все): Контент и образование 1 Контент и образование 2 PR и репутационные активности 1
A151: Конверсия приобретения ЦФА в месяц после масштабных мероприятий (конференции, фесты) | B151: =B150+6% -> 0.205 | C151: Применяются затраты из списка (От 3х статей): Контент и образование 1 Контент и образование 2 PR и репутационные активности 1 Контент и образование 3 PR и репутационные активности 2
A152: Ежегодный рост рынка | B152: 0.06 | C152: https://strategy.ru/research/research/analiz-rossiyskogo-i-mirovogo-rynkov-videoigr-77/
A153: Доля выбора внутриигрового актива после даты погашения ЦФА на скины | B153: 0.5
A155: Учет сезонных колебаний рынка
A156: Сезон | B156: Сезонный коэффициент | C156: Обоснование | G156: Действия
A157: Осень | B157: 0.1 | C157: Возвращение к активной жизни: окончание летних каникул способствует возвращению аудитории к хобби. «Осенний игровой сезон»: период ключевых релизов крупных игровых проектов, что резко повышает вовлеченность в индустрию. Экономический подъем: деловая активность после летнего затишья. | G157: Активно анонсировать новые продукты, выстраивая параллель с главными игровыми релизами (ЦФА на скины в оборот).
A158: Зима | B158: 0.15 | C158: Новогодние праздники и каникулы: увеличение свободного времени, традиционный период для игр. Зимние распродажи: пик активности в цифровых магазинах и в игровых кабинетах. Психология трат: праздничное настроение повышает склонность аудитории к покупкам и инвестициям. | G158: Запуск специальных новогодних предложений и интеграций с крупными распродажами (ЦФА на скины в оборот).
A159: Весна | B159: 0 | C159: После зимнего пика происходит постепенная стабилизация активности. Аудитория сохраняет высокую вовлеченность, но траты становятся более рациональными. Начинается подготовка к летнему сезону, что создает спрос на мобильные и кроссплатформенные игровые решения | G159: Акцент на проекты, доступные с разных устройств, особенно мобильные. Разработка и тестирование специальных летних активностей и ивентов.
A160: Лето | B160: -0.1 | C160: Сезон отпусков и путешествий: снижение времени, проводимого за компьютером. Смещение фокуса: активный отдых на свежем воздухе конкурирует с цифровыми развлечениями. Общее замедление деловой активности. | G160: Сфокусироваться на стратегическом планировании, аналитике и удержании лояльной аудитории.
A163: Предполагаемые выгоды, эффекты и дальнейшие действия
A164: Ценность для одной аудитории: Оба продукта ориентированы на одну целевую группу — геймеров и фанатов проекта. Для них ценность представляет как внутриигровая атрибутика (скины), так и эксклюзивный статус и близость к разработчику. Обоснование более высокого спроса на ЦФА с доходом для квалов: Разная мотивация: Квалифицированные инвесторы руководствуются финансовой логикой, а не эмоциями. Этот продукт для них — дополнительный инструмент диверсификации с расчетной доходностью, что автоматически формирует более высокий и предсказуемый спрос по сравнению с высокорисковыми "игровыми" активами.
A165: Предполагает стандартную маркетинговую активность (соцсети, email-рассылки) без крупных событий. Основана на типичных показателях конверсии для сложных финансовых продуктов среди узкой, но заинтересованной аудитории.
A166: PR-кампании в игровых СМИ и блогах повышают узнаваемость и доверие к эмитенту, что может мотивировать дополнительных 2% колеблющихся пользователей совершить сделку.
A167: Участие в крупных конференциях (например, IgroMir) или фестивалях позволяет напрямую взаимодействовать с ядром аудитории, проводить презентации и отвечать на вопросы. Это резко повышает доверие и мотивацию к инвестированию, удваивая базовую конверсию.
A170: Другие данные для расчетов
B171: Инфляция | C171: Премия за риск | D171: Ставка дисконтирования | E171: Обоснование | H171: Источники
A172: На 2025 | B172: 0.086 | C172: 0.03 | D172: =SUM(B172:C172) -> 0.116 | E172: Используется дисконтирование суммы выплаты для эмитента, так как стоимость, за которую бриобретают люди ЦФА сегодня будет отличаться от стоимости выплаты эмитентом в будущем | H172: https://cbr.ru/Content/Document/File/179982/forecast_250725.pdf
A173: На 2026 | B173: 0.049 | C173: 0.03 | D173: =SUM(B173:C173) -> 0.079
A174: На 2027 | B174: 0.04 | C174: 0.03 | D174: =SUM(B174:C174) -> 0.07

Sheet Расходы
A1: Перечень расходов эмитента, необходимых для выпуска ЦФА
A2: Статья расходов эмитента | B2: Описание | C2: Сумма (мин) р./мес. | D2: Сумма (макс) р./мес. | E2: Комментарий | F2: Ссылка
A3: Ежемесячные | C3: =SUM(C4:C6) -> 0 | D3: =SUM(D4:D6) -> -400000
A4: Аналитика | B4: Настройка сквозной аналитики (от клика до покупки ЦФА) A/B-тестирование описаний, CTA-кнопок, исследование аудитории (NPS, опросы) | C4: 0 | D4: -100000 | E4: Минимальная сумма назначена в виде делегирования проекта на аналитиков компании разработчика. Максимальная - в случае, если необходима более глубокая аналитика, в частности дополнительное отвественное лицо. | F4: https://ppc.world/articles/skolko-zarabatyvayut-digital-specialisty-v-2025-godu/ | G4: В рядовых расходах компании работает как доп проект
A5: Интернет-маркетинг | B5: Разработка рекламы, работа с таргетингом (бывшим инвесторам), одобрение рекламных материалов compliance-службой | C5: 0 | D5: -150000 | E5: Минимальная сумма назначена в виде делегирования проекта на отдел маркетинга. Максимальная - в случае, если необходимо дополнительное отвественное лицо. | F5: https://ppc.world/articles/skolko-zarabatyvayut-digital-specialisty-v-2025-godu/
A6: Юридическая и экономическая подготовка | B6: Расчет эффектов выпуска ЦФА, расчёт потенциальных угроз, подготовка документов и материалов | C6: 0 | D6: -150000 | E6: Минимальная сумма назначена в виде делегирования задач на юридические и финансовые отделы. Максимальная - в случае, если необходимо обращение к компетенм лицам для решения юридических споров в отрасли. | F6: https://abp.legal/gaming
A7: Ежеквартальные | C7: =SUM(C8:C10) -> 0 | D7: =SUM(D8:D10) -> -1100000
A8: Контент и образование 1 | B8: Статьи в гейм-блогах и в финансовых журналах | C8: 0 | D8: -500000 | E8: Бесплатную публикация разработчиком на VC, TJ, в отраслевых журналах и гейм-медиа И платную публикацию на гейм-медиа (например, Igromania, StopGame), онлайн издания (Ведомости, РБК, Forbes) и в отраслевых журналах с подпиской | F8: https://9writer.ru/ceny https://itiriy.ru/uslugi/publikacii-v-smi-i-media/
A9: Контент и образование 2 | B9: Вебинары с аналитиками и разработчиками | C9: 0 | D9: -500000 | E9: Минимальная сумма - затраты входят в рядовые расходы компании (подготовка материалов, аудитории, фона, договоеренности с инфлюенсирами и журналистами). Максимальная сумма - в случае покупкиинтервью в именитых блогах, каналах
A10: PR и репутационные активности 1 | B10: Пресс-релизы о запуске/объёмах | C10: 0 | D10: -100000 | E10: Затраты входят в рядовые расходы компании. Пресс-релизы возможны как в онлайн-изданиях, так и в личных блогах разработчиков.
A11: Ежегодные | C11: =SUM(C12:C13) -> -250000 | D11: =SUM(D12:D13) -> -2500000
A12: Контент и образование 3 | B12: Демонстрация интеграции ЦФА в игровой продукт на гейм-фестах | C12: -50000 | D12: -1500000 | E12: Затраты входят в рядовые расходы компании. Если разработчику необходимо продемонстрировать работу ЦФА и его интегрированность в игру, то требуются расходы на создание материала (стенды, видеоролики, мерч и игровая продукция). | F12: https://docs.360.yandex.ru/docs/view?url=ya-disk-public%3A%2F%2FDePEsIzVLGgGKUrhXOG0MIYoNuifNgNT4NIGTIouGwfl61UvWkQJD7XFn%2BMs5Cw3DqZvSgIch5AN9ddz7ydViQ%3D%3D&name=Пакеты%20Игропром%20без%20нум.pdf https://russianventureforum.ru/expo
A13: PR и репутационные активности 2 | B13: Выступления на конференциях (РИФ, ФинУТР и др.) | C13: -200000 | D13: -1000000 | E13: Дополнительные компании по расширению понимания интеграции ЦФА в внутриигровые процессы. Предлагается стоимость от выступления на конференции до статуса ген.партнёра и использования доп. услуг по привлечению аудитории | F13: https://static.cnews.ru/img/cnews/2024/12/24/conf2025.pdf
A14: Разовые
A15: Интеграция Alfa ID в платформу покупки внутриигровых продуктов | B15: Интеграция игрового клиента с внешней системой Alfa ID через API | C15: -500000
A16: Комиссии ИС
A17: Внесение в Систему записи о цифровых финансовых активах, выпущенных (размещенных) Эмитентом | B17: От суммы сделки | C17: 0.02 | E17: В дату выпуска (размещения) ЦФА НДС не облагается | F17: Тарифы оператора информационной системы АО «АЛЬФА-БАНК» по операциям, связанным с выпуском, учетом и обращением цифровых финансовых активов (редакция от 15 июля 2025)
A18: Внесение записи в Систему о досрочном прекращении (погашении) Эмитентом обязательств, удостоверенных цифровыми финансовыми активами | C18: Комиссия не установлена | E18: Лежит внутри услуг от Оператора
A19: Доступ Эмитента к Системе | C19: Комиссия не установлена
A20: Формирование выписок, справок, реестров, уведомлений | C20: Комиссия не установлена
A21: Экстраординарные затраты | C21: 0.05
A22: Налог на прибыль | C22: 0.05 | F22: Налоговый кодекс Российской Федерации (часть вторая)" от 05.08.2000 N 117-ФЗ (ред. от 31.07.2025) (с изм. и доп., вступ. в силу с 01.09.2025)
A24: Возможные меры поддержки, в случае 3 сценария
A25: ИРИ гранты | B25: Реализация год | C25: Вертикальный срез - до 7,5 млн. руб. Демо версия – до 15 млн. руб. | F25: https://ири.рф/contests/otbor-prototipov-igr/
A26: Акредитация в Минцифры | C26: Снижение страховых взносов | F26: https://digital.gov.ru/activity/gos-uslugi/akkreditacziya-it-kompanij

Sheet Cash-Flow 1
A1: Расчет Cash-Flow для Сценария 1 (оптимистичный)
A2: Период (мес.) | B2: 1 | C2: 2 | D2: 3 | E2: 4 | F2: 5 | G2: 6 | H2: 7 | I2: 8 | J2: 9 | K2: 10 | L2: 11 | M2: 12 | N2: 13 | O2: 14 | P2: 15 | Q2: 16 | R2: 17 | S2: 18 | T2: 19 | U2: 20 | V2: 21 | W2: 22 | X2: 23 | Y2: 24 | Z2: 25 | AA2: 26 | AB2: 27 | AC2: 28 | AD2: 29 | AE2: 30 | AF2: 31 | AG2: 32 | AH2: 33 | AI2: 34 | AJ2: 35 | AK2: 36 | AL2: 37
A3: Сезонность | B3: =IF(OR(B2=1,B2=2,B2=12,B2=13,B2=14,B2=24,B2=25,B2=26,B2=36),1+Предпосылки!$B$158,IF(OR(B2=9,B2=10,B2=11,B2=21,B2=22,B2=23,B2=33,B2=34,B2=35),1+Предпосылки!$B$157,IF(OR(B2=6,B2=7,B2=8),1+Предпосылки!$B$160,IF(OR(B2=3,B2=4,B2=5,B2=15,B2=16,B2=17,B2=27,B2=28,B2=29),Предпосылки!$B$159+1,1)))) -> 1.15 | C3: =IF(OR(C2=1,C2=2,C2=12,C2=13,C2=14,C2=24,C2=25,C2=26,C2=36),1+Предпосылки!$B$158,IF(OR(C2=9,C2=10,C2=11,C2=21,C2=22,C2=23,C2=33,C2=34,C2=35),1+Предпосылки!$B$157,IF(OR(C2=6,C2=7,C2=8),1+Предпосылки!$B$160,IF(OR(C2=3,C2=4,C2=5,C2=15,C2=16,C2=17,C2=27,C2=28,C2=29),Предпосылки!$B$159+1,1)))) -> 1.15 | D3: =IF(OR(D2=1,D2=2,D2=12,D2=13,D2=14,D2=24,D2=25,D2=26,D2=36),1+Предпосылки!$B$158,IF(OR(D2=9,D2=10,D2=11,D2=21,D2=22,D2=23,D2=33,D2=34,D2=35),1+Предпосылки!$B$157,IF(OR(D2=6,D2=7,D2=8),1+Предпосылки!$B$160,IF(OR(D2=3,D2=4,D2=5,D2=15,D2=16,D2=17,D2=27,D2=28,D2=29),Предпосылки!$B$159+1,1)))) -> 1 | E3: =IF(OR(E2=1,E2=2,E2=12,E2=13,E2=14,E2=24,E2=25,E2=26,E2=36),1+Предпосылки!$B$158,IF(OR(E2=9,E2=10,E2=11,E2=21,E2=22,E2=23,E2=33,E2=34,E2=35),1+Предпосылки!$B$157,IF(OR(E2=6,E2=7,E2=8),1+Предпосылки!$B$160,IF(OR(E2=3,E2=4,E2=5,E2=15,E2=16,E2=17,E2=27,E2=28,E2=29),Предпосылки!$B$159+1,1)))) -> 1 | F3: =IF(OR(F2=1,F2=2,F2=12,F2=13,F2=14,F2=24,F2=25,F2=26,F2=36),1+Предпосылки!$B$158,IF(OR(F2=9,F2=10,F2=11,F2=21,F2=22,F2=23,F2=33,F2=34,F2=35),1+Предпосылки!$B$157,IF(OR(F2=6,F2=7,F2=8),1+Предпосылки!$B$160,IF(OR(F2=3,F2=4,F2=5,F2=15,F2=16,F2=17,F2=27,F2=28,F2=29),Предпосылки!$B$159+1,1)))) -> 1 | G3: =IF(OR(G2=1,G2=2,G2=12,G2=13,G2=14,G2=24,G2=25,G2=26,G2=36),1+Предпосылки!$B$158,IF(OR(G2=9,G2=10,G2=11,G2=21,G2=22,G2=23,G2=33,G2=34,G2=35),1+Предпосылки!$B$157,IF(OR(G2=6,G2=7,G2=8),1+Предпосылки!$B$160,IF(OR(G2=3,G2=4,G2=5,G2=15,G2=16,G2=17,G2=27,G2=28,G2=29),Предпосылки!$B$159+1,1)))) -> 0.9 | H3: =IF(OR(H2=1,H2=2,H2=12,H2=13,H2=14,H2=24,H2=25,H2=26,H2=36),1+Предпосылки!$B$158,IF(OR(H2=9,H2=10,H2=11,H2=21,H2=22,H2=23,H2=33,H2=34,H2=35),1+Предпосылки!$B$157,IF(OR(H2=6,H2=7,H2=8),1+Предпосылки!$B$160,IF(OR(H2=3,H2=4,H2=5,H2=15,H2=16,H2=17,H2=27,H2=28,H2=29),Предпосылки!$B$159+1,1)))) -> 0.9 | I3: =IF(OR(I2=1,I2=2,I2=12,I2=13,I2=14,I2=24,I2=25,I2=26,I2=36),1+Предпосылки!$B$158,IF(OR(I2=9,I2=10,I2=11,I2=21,I2=22,I2=23,I2=33,I2=34,I2=35),1+Предпосылки!$B$157,IF(OR(I2=6,I2=7,I2=8),1+Предпосылки!$B$160,IF(OR(I2=3,I2=4,I2=5,I2=15,I2=16,I2=17,I2=27,I2=28,I2=29),Предпосылки!$B$159+1,1)))) -> 0.9 | ... U3: =IF(OR(U2=1,U2=2,U2=12,U2=13,U2=14,U2=24,U2=25,U2=26,U2=36),1+Предпосылки!$B$158,IF(OR(U2=9,U2=10,U2=11,U2=21,U2=22,U2=23,U2=33,U2=34,U2=35),1+Предпосылки!$B$157,IF(OR(U2=6,U2=7,U2=8),1+Предпосылки!$B$160,IF(OR(U2=3,U2=4,U2=5,U2=15,U2=16,U2=17,U2=27,U2=28,U2=29),Предпосылки!$B$159+1,1)))) -> 1 | V3: =IF(OR(V2=1,V2=2,V2=12,V2=13,V2=14,V2=24,V2=25,V2=26,V2=36),1+Предпосылки!$B$158,IF(OR(V2=9,V2=10,V2=11,V2=21,V2=22,V2=23,V2=33,V2=34,V2=35),1+Предпосылки!$B$157,IF(OR(V2=6,V2=7,V2=8),1+Предпосылки!$B$160,IF(OR(V2=6,V2=7,V2=8),1+Предпосылки!$B$160,IF(OR(V2=3,V2=4,V2=5,V2=15,V2=16,V2=17,V2=27,V2=28,V2=29),Предпосылки!$B$159+1,1))))) -> 1.1 | W3: =IF(OR(W2=1,W2=2,W2=12,W2=13,W2=14,W2=24,W2=25,W2=26,W2=36),1+Предпосылки!$B$158,IF(OR(W2=9,W2=10,W2=11,W2=21,W2=22,W2=23,W2=33,W2=34,W2=35),1+Предпосылки!$B$157,IF(OR(W2=6,W2=7,W2=8),1+Предпосылки!$B$160,IF(OR(W2=6,W2=7,W2=8),1+Предпосылки!$B$160,IF(OR(W2=3,W2=4,W2=5,W2=15,W2=16,W2=17,W2=27,W2=28,W2=29),Предпосылки!$B$159+1,1))))) -> 1.1 | X3: =IF(OR(X2=1,X2=2,X2=12,X2=13,X2=14,X2=24,X2=25,X2=26,X2=36),1+Предпосылки!$B$158,IF(OR(X2=9,X2=10,X2=11,X2=21,X2=22,X2=23,X2=33,X2=34,X2=35),1+Предпосылки!$B$157,IF(OR(X2=6,X2=7,X2=8),1+Предпосылки!$B$160,IF(OR(X2=6,X2=7,X2=8),1+Предпосылки!$B$160,IF(OR(X2=3,X2=4,X2=5,X2=15,X2=16,X2=17,X2=27,X2=28,X2=29),Предпосылки!$B$159+1,1))))) -> 1.1 | Y3: =IF(OR(Y2=1,Y2=2,Y2=12,Y2=13,Y2=14,Y2=24,Y2=25,Y2=26,Y2=36),1+Предпосылки!$B$158,IF(OR(Y2=9,Y2=10,Y2=11,Y2=21,Y2=22,Y2=23,Y2=33,Y2=34,Y2=35),1+Предпосылки!$B$157,IF(OR(Y2=6,Y2=7,Y2=8),1+Предпосылки!$B$160,IF(OR(Y2=6,Y2=7,Y2=8),1+Предпосылки!$B$160,IF(OR(Y2=3,Y2=4,Y2=5,Y2=15,Y2=16,Y2=17,Y2=27,Y2=28,Y2=29),Предпосылки!$B$159+1,1))))) -> 1.15 | Z3: =IF(OR(Z2=1,Z2=2,Z2=12,Z2=13,Z2=14,Z2=24,Z2=25,Z2=26,Z2=36),1+Предпосылки!$B$158,IF(OR(Z2=9,Z2=10,Z2=11,Z2=21,Z2=22,Z2=23,Z2=33,Z2=34,Z2=35),1+Предпосылки!$B$157,IF(OR(Z2=6,Z2=7,Z2=8),1+Предпосылки!$B$160,IF(OR(Z2=6,Z2=7,Z2=8),1+Предпосылки!$B$160,IF(OR(Z2=3,Z2=4,Z2=5,Z2=15,Z2=16,Z2=17,Z2=27,Z2=28,Z2=29),Предпосылки!$B$159+1,1))))) -> 1.15 | AA3: =IF(OR(AA2=1,AA2=2,AA2=12,AA2=13,AA2=14,AA2=24,AA2=25,AA2=26,AA2=36),1+Предпосылки!$B$158,IF(OR(AA2=9,AA2=10,AA2=11,AA2=21,AA2=22,AA2=23,AA2=33,AA2=34,AA2=35),1+Предпосылки!$B$157,IF(OR(AA2=6,AA2=7,AA2=8),1+Предпосылки!$B$160,IF(OR(AA2=6,AA2=7,AA2=8),1+Предпосылки!$B$160,IF(OR(AA2=3,AA2=4,AA2=5,AA2=15,AA2=16,AA2=17,AA2=27,AA2=28,AA2=29),Предпосылки!$B$159+1,1))))) -> 1.15 | AB3: =IF(OR(AB2=1,AB2=2,AB2=12,AB2=13,AB2=14,AB2=24,AB2=25,AB2=26,AB2=36),1+Предпосылки!$B$158,IF(OR(AB2=9,AB2=10,AB2=11,AB2=21,AB2=22,AB2=23,AB2=33,AB2=34,AB2=35),1+Предпосылки!$B$157,IF(OR(AB2=6,AB2=7,AB2=8),1+Предпосылки!$B$160,IF(OR(AB2=6,AB2=7,AB2=8),1+Предпосылки!$B$160,IF(OR(AB2=3,AB2=4,AB2=5,AB2=15,AB2=16,AB2=17,AB2=27,AB2=28,AB2=29),Предпосылки!$B$159+1,1))))) -> 1 | AC3: =IF(OR(AC2=1,AC2=2,AC2=12,AC2=13,AC2=14,AC2=24,AC2=25,AC2=26,AC2=36),1+Предпосылки!$B$158,IF(OR(AC2=9,AC2=10,AC2=11,AC2=21,AC2=22,AC2=23,AC2=33,AC2=34,AC2=35),1+Предпосылки!$B$157,IF(OR(AC2=6,AC2=7,AC2=8),1+Предпосылки!$B$160,IF(OR(AC2=6,AC2=7,AC2=8),1+Предпосылки!$B$160,IF(OR(AC2=3,AC2=4,AC2=5,AC2=15,AC2=16,AC2=17,AC2=27,AC2=28,AC2=29),Предпосылки!$B$159+1,1))))) -> 1 | ... AK3: =IF(OR(AK2=1,AK2=2,AK2=12,AK2=13,AK2=14,AK2=24,AK2=25,AK2=26,AK2=36),1+Предпосылки!$B$158,IF(OR(AK2=9,AK2=10,AK2=11,AK2=21,AK2=22,AK2=23,AK2=33,AK2=34,AK2=35),1+Предпосылки!$B$157,IF(OR(AK2=6,AK2=7,AK2=8),1+Предпосылки!$B$160,IF(OR(AK2=6,AK2=7,AK2=8),1+Предпосылки!$B$160,IF(OR(AK2=3,AK2=4,AK2=5,AK2=15,AK2=16,AK2=17,AK2=27,AK2=28,AK2=29),Предпосылки!$B$159+1,1))))) -> 1.15
A4: Лимит суммы выпуска ЦФА | B4: =Предпосылки!$H$125 -> 300000000 | C4: =B$4-B$13 -> 299483000 | D4: =C$4-C$13 -> 298977000 | E4: =D$4-D$13 -> 298542000 | F4: =E$4-E$13 -> 298102000 | G4: =F$4-F$13 -> 297662000 | H4: =G$4-G$13 -> 297272000 | I4: =H$4-H$13 -> 296876000 | J4: =I$4-I$13 -> 296480000 | ... U4: =T$4-T$13 -> 291142000 | V4: =U4-U13 -> 290707000 | W4: =V4-V13 -> 289955000 | X4: =W4-W13 -> 289448000 | Y4: =X4-X13 -> 288924000 | Z4: =Y4-Y13 -> 288396000 | AA4: =Z4-Z13 -> 287868000 | AB4: =AA4-AA13 -> 287289000 | AC4: =AB4-AB13 -> 286803000 | ... AL4: =AK4-AK13 -> 281687000
A5: Накопленная сумма к выплате | C5: =B$13+B5 -> 517000 | D5: =C$13+C5 -> 1023000 | E5: =D$13+D5 -> 1458000 | F5: =E$13+E5 -> 1898000 | G5: =F$13+F5 -> 2338000 | H5: =G$13+G5 -> 2728000 | I5: =H$13+H5 -> 3124000 | J5: =I$13+I5 -> 3520000 | ... U5: =T$13+T5 -> 8858000 | V5: =V13+U5 -> 9610000 | W5: =V13+V5 -> 10362000 | X5: =W13+W5 -> 10869000 | Y5: =X13+X5 -> 11393000 | Z5: =Y13+Y5 -> 11921000 | AA5: =Z13+Z5 -> 12449000 | AB5: =AA13+AA5 -> 13028000 | AC5: =AB13+AB5 -> 13514000 | AD5: =AC13+AC5 -> 14000000 | ... AK5: =AJ13+AJ5 -> 18069000
A6: Сумма к выплате по ЦФА на скины | B6: 0 | C6: =(B6+B10*Предпосылки!$D$122)/(1+Предпосылки!$D$172/12)^(C$2-1) -> 159458.57 | D6: =(C6+C10*Предпосылки!$D$122)/(1+Предпосылки!$D$172/12)^(D$2-1) -> 314351.73 | E6: =(D6+D10*Предпосылки!$D$122)/(1+Предпосылки!$D$172/12)^(E$2-1) -> 446283.98 | F6: =(E6+E10*Предпосылки!$D$122)/(1+Предпосылки!$D$172/12)^(F$2-1) -> 564151.77 | G6: =(F6+F10*Предпосылки!$D$122)/(1+Предпосылки!$D$172/12)^(G$2-1) -> 671082.91 | H6: =(G6+G10*Предпосылки!$D$122)/(1+Предпосылки!$D$172/12)^(H$2-1) -> 756152.44 | I6: =(H6+H10*Предпосылки!$D$122)/(1+Предпосылки!$D$172/12)^(I$2-1) -> 824702.87 | J6: =(I6+I10*Предпосылки!$D$122)/(1+Предпосылки!$D$172/12)^(J$2-1) -> 880279.64 | ... N6: =(M6+M10*Предпосылки!$D$122)/(1+Предпосылки!$D$172/12)^(N$2-1) -> 1124532.3 | O6: =(N10*Предпосылки!$D$122)/(1+Предпосылки!$D$92/12)^(O$2-1) -> 166000 | P6: =(O10*Предпосылки!$D$122)/(1+Предпосылки!$D$92/12)^(P$2-1) -> 166000 | Q6: =(P10*Предпосылки!$D$122)/(1+Предпосылки!$D$92/12)^(Q$2-1) -> 140000 | R6: =(Q10*Предпосылки!$D$122)/(1+Предпосылки!$D$92/12)^(R$2-1) -> 145000 | S6: =(R10*Предпосылки!$D$122)/(1+Предпосылки!$D$92/12)^(S$2-1) -> 145000 | T6: =(S10*Предпосылки!$D$122)/(1+Предпосылки!$D$92/12)^(T$2-1) -> 140000 | U6: =(T10*Предпосылки!$D$122)/(1+Предпосылки!$D$92/12)^(U$2-1) -> 145000 | V6: =(U6+U10*Предпосылки!$D$122)/(1+Предпосылки!$D$173/12)^(U$2-1) -> 256007.7 | W6: =(V6+V10*Предпосылки!$D$122)/(1+Предпосылки!$D$173/12)^(C$2-1) -> 491770.21 | X6: =(W6+W10*Предпосылки!$D$122)/(1+Предпосылки!$D$173/12)^(D$2-1) -> 652155.24 | Y6: =(X6+X10*Предпосылки!$D$122)/(1+Предпосылки!$D$173/12)^(E$2-1) -> 799265.59 | Z6: =(Y6+Y10*Предпосылки!$D$122)/(1+Предпосылки!$D$173/12)^(F$2-1) -> 950000.78 | AA6: =(Z10*Предпосылки!$D$122)/(1+Предпосылки!$D$174/12)^(G$2-1) -> 170955.29 | AB6: =(AA6+AA10*Предпосылки!$D$122)/(1+Предпосылки!$D$174/12)^(H$2-1) -> 338918.79 | AC6: =(AB6+AB10*Предпосылки!$D$122)/(1+Предпосылки!$D$174/12)^(I$2-1) -> 480933.64 | AD6: =(AC6+AC10*Предпосылки!$D$122)/(1+Предпосылки!$D$174/12)^(J$2-1) -> 613702.59 | AE6: =(AD6+AD10*Предпосылки!$D$122)/(1+Предпосылки!$D$174/12)^(K$2-1) -> 800672.97 | AF6: =(AE6+AE10*Предпосылки!$D$122)/(1+Предпосылки!$D$174/12)^(L$2-1) -> 972435.14 | AG6: =(AF6+AF10*Предпосылки!$D$122)/(1+Предпосылки!$D$174/12)^(M$2-1) -> 1064126.9 | AH6: =(AG6+AG10*Предпосылки!$D$122)/(1+Предпосылки!$D$174/12)^(N$2-1) -> 1138802.7 | AI6: =(AH6+AH10*Предпосылки!$D$122)/(1+Предпосылки!$D$174/12)^(O$2-1) -> 1221833.7 | ... AL6: =(AK6+AK10*Предпосылки!$D$122)/(1+Предпосылки!$D$174/12)^(R$2-1) -> 1393080
A7: Сумма к выплате по Fan-токенам | B7: 0 | C7: =(B7+B11*Предпосылки!$D$122)/(1+Предпосылки!$D$172/12)^(C$2-1) -> 159458.57 | D7: =(C7+C11*Предпосылки!$D$122)/(1+Предпосылки!$D$172/12)^(D$2-1) -> 314351.73 | E7: =(D7+D11*Предпосылки!$D$122)/(1+Предпосылки!$D$172/12)^(E$2-1) -> 446283.98 | F7: =(E7+E11*Предпосылки!$D$122)/(1+Предпосылки!$D$172/12)^(F$2-1) -> 564151.77 | G7: =(F7+F11*Предпосылки!$D$122)/(1+Предпосылки!$D$172/12)^(G$2-1) -> 671082.91 | H7: =(G7+G11*Предпосылки!$D$122)/(1+Предпосылки!$D$172/12)^(H$2-1) -> 756152.44 | I7: =(H7+H11*Предпосылки!$D$122)/(1+Предпосылки!$D$172/12)^(I$2-1) -> 824702.87 | J7: =(I7+I11*Предпосылки!$D$122)/(1+Предпосылки!$D$172/12)^(J$2-1) -> 880279.64 | ... N7: =(M7+M11*Предпосылки!$D$122)/(1+Предпосылки!$D$172/12)^(N$2-1) -> 1124532.3 | O7: =(N11*Предпосылки!$D$122)/(1+Предпосылки!$D$173/12)^(O$2-1) -> 152426.87 | P7: =(O11*Предпосылки!$D$122)/(1+Предпосылки!$D$173/12)^(P$2-1) -> 151429.96 | Q7: =(P11*Предпосылки!$D$122)/(1+Предпосылки!$D$173/12)^(Q$2-1) -> 126876.74 | R7: =(Q11*Предпосылки!$D$122)/(1+Предпосылки!$D$173/12)^(R$2-1) -> 130548.61 | S7: =(R11*Предпосылки!$D$122)/(1+Предпосылки!$D$173/12)^(S$2-1) -> 129694.78 | T7: =(S11*Предпосылки!$D$122)/(1+Предпосылки!$D$173/12)^(T$2-1) -> 124403.56 | U7: =(T11*Предпосылки!$D$122)/(1+Предпосылки!$D$173/12)^(U$2-1) -> 128003.85 | V7: =(U7+U11*Предпосылки!$D$122)/(1+Предпосылки!$D$173/12)^(U$2-1) -> 241003.75 | W7: =(V7+V11*Предпосылки!$D$122)/(1+Предпосылки!$D$173/12)^(C$2-1) -> 476864.39 | X7: =(W7+W11*Предпосылки!$D$122)/(1+Предпосылки!$D$173/12)^(D$2-1) -> 637443.76 | Y7: =(X7+X11*Предпосылки!$D$122)/(1+Предпосылки!$D$173/12)^(E$2-1) -> 784840.88 | Z7: =(Y7+Y11*Предпосылки!$D$122)/(1+Предпосылки!$D$173/12)^(F$2-1) -> 935949.75 | AA7: =(Z11*Предпосылки!$D$122)/(1+Предпосылки!$D$174/12)^(G$2-1) -> 170955.29 | AB7: =AA7+(AA11*Предпосылки!$D$122)/(1+Предпосылки!$D$174/12)^(H$2-1) -> 344781.94 | AC7: =AB7+(AB11*Предпосылки!$D$122)/(1+Предпосылки!$D$174/12)^(I$2-1) -> 500318.63 | AD7: =AC7+(AC11*Предпосылки!$D$122)/(1+Предпосылки!$D$174/12)^(J$2-1) -> 654953.28 | AE7: =AD7+(AD11*Предпосылки!$D$122)/(1+Предпосылки!$D$174/12)^(K$2-1) -> 873223.07 | AF7: =AE7+(AE11*Предпосылки!$D$122)/(1+Предпосылки!$D$174/12)^(L$2-1) -> 1090227 | AG7: =AF7+(AF11*Предпосылки!$D$122)/(1+Предпосылки!$D$174/12)^(M$2-1) -> 1242186.8 | AH7: =AG7+(AG11*Предпосылки!$D$122)/(1+Предпосылки!$D$174/12)^(N$2-1) -> 1388602.4 | AI7: =AH7+(AH11*Предпосылки!$D$122)/(1+Предпосылки!$D$174/12)^(O$2-1) -> 1554566.7 | ... AL7: =AK7+(AK11*Предпосылки!$D$122)/(1+Предпосылки!$D$174/12)^(R$2-1) -> 2048497.3
A8: Сумма к выплате по классическим ЦФА | B8: 0 | C8: =(B8+B12*Предпосылки!$D$122)/(1+Предпосылки!$D$172/12)^(C$2-1) -> 193133.05 | D8: =(C8+C12*Предпосылки!$D$122)/(1+Предпосылки!$D$172/12)^(D$2-1) -> 369946.18 | E8: =(D8+D12*Предпосылки!$D$122)/(1+Предпосылки!$D$172/12)^(E$2-1) -> 500296.87 | F8: =(E8+E12*Предпосылки!$D$122)/(1+Предпосылки!$D$172/12)^(F$2-1) -> 635370.68 | G8: =(F8+F12*Предпосылки!$D$122)/(1+Предпосылки!$D$172/12)^(G$2-1) -> 758017.94 | H8: =(G8+G12*Предпосылки!$D$122)/(1+Предпосылки!$D$172/12)^(H$2-1) -> 838211.52 | I8: =(H8+H12*Предпосылки!$D$122)/(1+Предпосылки!$D$172/12)^(I$2-1) -> 918245.68 | J8: =(I8+I12*Предпосылки!$D$122)/(1+Предпосылки!$D$172/12)^(J$2-1) -> 983559.92 | ... N8: =(M8+M12*Предпосылки!$D$122)/(1+Предпосылки!$D$172/12)^(N$2-1) -> 1228663.1 | O8: =(N12*Предпосылки!$D$122)/(1+Предпосылки!$D$173/12)^(O$2-1) -> 152426.87 | P8: =(O12*Предпосылки!$D$122)/(1+Предпосылки!$D$173/12)^(P$2-1) -> 151429.96 | Q8: =(P12*Предпосылки!$D$122)/(1+Предпосылки!$D$173/12)^(Q$2-1) -> 145001.99 | R8: =(Q12*Предпосылки!$D$122)/(1+Предпосылки!$D$173/12)^(R$2-1) -> 130548.61 | S8: =(R12*Предпосылки!$D$122)/(1+Предпосылки!$D$173/12)^(S$2-1) -> 129694.78 | T8: =(S12*Предпосылки!$D$122)/(1+Предпосылки!$D$173/12)^(T$2-1) -> 142175.49 | U8: =(T12*Предпосылки!$D$122)/(1+Предпосылки!$D$173/12)^(U$2-1) -> 128003.85 | V8: =(U8+U12*Предпосылки!$D$122)/(1+Предпосылки!$D$173/12)^(U$2-1) -> 241003.75 | W8: =(V8+V12*Предпосылки!$D$122)/(1+Предпосылки!$D$173/12)^(C$2-1) -> 511635.48 | X8: =(W8+W12*Предпосылки!$D$122)/(1+Предпосылки!$D$173/12)^(D$2-1) -> 671761.51 | Y8: =(X8+X12*Предпосылки!$D$122)/(1+Предпосылки!$D$173/12)^(E$2-1) -> 852807.44 | Z8: =(Y8+Y12*Предпосылки!$D$122)/(1+Предпосылки!$D$173/12)^(F$2-1) -> 1002155.6 | AA8: =(Z12*Предпосылки!$D$122)/(1+Предпосылки!$D$174/12)^(G$2-1) -> 170955.29 | AB8: =AA8+(AA12*Предпосылки!$D$122)/(1+Предпосылки!$D$174/12)^(H$2-1) -> 382444.38 | AC8: =AB8+(AB12*Предпосылки!$D$122)/(1+Предпосылки!$D$174/12)^(I$2-1) -> 537981.07 | AD8: =AC8+(AC12*Предпосылки!$D$122)/(1+Предпосылки!$D$174/12)^(J$2-1) -> 692615.72 | AE8: =AD8+(AD12*Предпосылки!$D$122)/(1+Предпосылки!$D$174/12)^(K$2-1) -> 943151.48 | AF8: =AE8+(AE12*Предпосылки!$D$122)/(1+Предпосылки!$D$174/12)^(L$2-1) -> 1192234.2 | AG8: =AF8+(AF12*Предпосылки!$D$122)/(1+Предпосылки!$D$174/12)^(M$2-1) -> 1344194.1 | AH8: =AG8+(AG12*Предпосылки!$D$122)/(1+Предпосылки!$D$174/12)^(N$2-1) -> 1522317.5 | AI8: =AH8+(AH12*Предпосылки!$D$122)/(1+Предпосылки!$D$174/12)^(O$2-1) -> 1688281.8 | ... AL8: =AK8+(AK12*Предпосылки!$D$122)/(1+Предпосылки!$D$174/12)^(R$2-1) -> 2216121.1
A9: Количество купленных ЦФА | B9: =SUM(B10:B12) -> 517 | C9: =SUM(C10:C12) -> 506 | D9: =SUM(D10:D12) -> 435 | E9: =SUM(E10:E12) -> 440 | F9: =SUM(F10:F12) -> 440 | G9: =SUM(G10:G12) -> 390 | H9: =SUM(H10:H12) -> 396 | I9: =SUM(I10:I12) -> 396 | ... AK9: =SUM(AK10:AK12) -> 561
A10: Количество купленных ЦФА на скины | B10: =ROUNDDOWN(B3*IF(COUNT(B22:B26)>0,Предпосылки!$B$150,IF(COUNT(B22:B26)>3,Предпосылки!$B$151,Предпосылки!$B$148))*Предпосылки!$E$122,0) -> 161 | C10: =ROUNDDOWN(C3*IF(COUNT(C22:C26)>0,Предпосылки!$B$150,IF(COUNT(C22:C26)>3,Предпосылки!$B$151,Предпосылки!$B$148))*Предпосылки!$E$122,0) -> 161 | D10: =ROUNDDOWN(D3*IF(COUNT(D22:D26)>0,Предпосылки!$B$150,IF(COUNT(D22:D26)>3,Предпосылки!$B$151,Предпосылки!$B$148))*Предпосылки!$E$122,0) -> 145 | E10: =ROUNDDOWN(E3*IF(COUNT(E22:E26)>0,Предпосылки!$B$150,IF(COUNT(E22:E26)>3,Предпосылки!$B$151,Предпосылки!$B$148))*Предпосылки!$E$122,0) -> 140 | F10: =ROUNDDOWN(F3*IF(COUNT(F22:F26)>0,Предпосылки!$B$150,IF(COUNT(F22:F26)>3,Предпосылки!$B$151,Предпосылки!$B$148))*Предпосылки!$E$122,0) -> 140 | G10: =ROUNDDOWN(G3*IF(COUNT(G22:G26)>0,Предпосылки!$B$150,IF(COUNT(G22:G26)>3,Предпосылки!$B$151,Предпосылки!$B$148))*Предпосылки!$E$122,0) -> 130 | H10: =ROUNDDOWN(H3*IF(COUNT(H22:H26)>0,Предпосылки!$B$150,IF(COUNT(H22:H26)>3,Предпосылки!$B$151,Предпосылки!$B$148))*Предпосылки!$E$122,0) -> 126 | I10: =ROUNDDOWN(I3*IF(COUNT(I22:I26)>0,Предпосылки!$B$150,IF(COUNT(I22:I26)>3,Предпосылки!$B$151,Предпосылки!$B$148))*Предпосылки!$E$122,0) -> 126 | J10: =ROUNDDOWN(J3*IF(COUNT(J22:J26)<3,Предпосылки!$B$150,IF(COUNT(J22:J26)>3,Предпосылки!$B$151,Предпосылки!$B$148))*Предпосылки!$E$122,0) -> 225 | K10: =ROUNDDOWN(K3*IF(COUNT(K22:K26)<3,Предпосылки!$B$150,IF(COUNT(K22:K26)>3,Предпосылки!$B$151,Предпосылки!$B$148))*Предпосылки!$E$122,0) -> 159 | L10: =ROUNDDOWN(L3*IF(COUNT(L22:L26)<3,Предпосылки!$B$150,IF(COUNT(L22:L26)>3,Предпосылки!$B$151,Предпосылки!$B$148))*Предпосылки!$E$122,0) -> 159 | M10: =ROUNDDOWN(M3*IF(COUNT(M22:M26)<3,Предпосылки!$B$150,IF(COUNT(M22:M26)>3,Предпосылки!$B$151,Предпосылки!$B$148))*Предпосылки!$E$122,0) -> 161 | N10: =ROUNDDOWN(N3*IF(COUNT(N22:N26)<3,Предпосылки!$B$150,IF(COUNT(N22:N26)>3,Предпосылки!$B$151,Предпосылки!$B$148))*Предпосылки!$E$122,0) -> 166 | O10: =ROUNDDOWN(O3*IF(COUNT(O22:O26)<3,Предпосылки!$B$150,IF(COUNT(O22:O26)>3,Предпосылки!$B$151,Предпосылки!$B$148))*Предпосылки!$E$122,0) -> 166 | P10: =ROUNDDOWN(P3*IF(COUNT(P22:P26)<3,Предпосылки!$B$150,IF(COUNT(P22:P26)>3,Предпосылки!$B$151,Предпосылки!$B$148))*Предпосылки!$E$122,0) -> 140 | Q10: =ROUNDDOWN(Q3*IF(COUNT(Q22:Q26)<3,Предпосылки!$B$150,IF(COUNT(Q22:Q26)>3,Предпосылки!$B$151,Предпосылки!$B$148))*Предпосылки!$E$122,0) -> 145 | ... U10: =ROUNDDOWN(U3*IF(COUNT(U22:U26)<3,Предпосылки!$B$150,IF(COUNT(U22:U26)>3,Предпосылки!$B$151,Предпосылки!$B$148))*Предпосылки!$E$122,0) -> 145 | V10: =ROUNDDOWN(V3*IF(COUNT(V22:V26)<3,Предпосылки!$B$150,IF(COUNT(V22:V26)>3,Предпосылки!$B$151,Предпосылки!$B$148))*Предпосылки!$E$122*(1+Предпосылки!$B$152),0) -> 239 | W10: =ROUNDDOWN(W3*IF(COUNT(W22:W26)<3,Предпосылки!$B$150,IF(COUNT(W22:W26)>3,Предпосылки!$B$151,Предпосылки!$B$148))*Предпосылки!$E$122*(1+Предпосылки!$B$152),0) -> 169 | X10: =ROUNDDOWN(X3*IF(COUNT(X22:X26)<3,Предпосылки!$B$150,IF(COUNT(X22:X26)>3,Предпосылки!$B$151,Предпосылки!$B$148))*Предпосылки!$E$122*(1+Предпосылки!$B$152),0) -> 163 | Y10: =ROUNDDOWN(Y3*IF(COUNT(Y22:Y26)<3,Предпосылки!$B$150,IF(COUNT(Y22:Y26)>3,Предпосылки!$B$151,Предпосылки!$B$148))*Предпосылки!$E$122*(1+Предпосылки!$B$152),0) -> 176 | Z10: =ROUNDDOWN(Z3*IF(COUNT(Z22:Z26)<3,Предпосылки!$B$150,IF(COUNT(Z22:Z26)>3,Предпосылки!$B$151,Предпосылки!$B$148))*Предпосылки!$E$122*(1+Предпосылки!$B$152),0) -> 176 | AA10: =ROUNDDOWN(AA3*IF(COUNT(AA22:AA26)<3,Предпосылки!$B$150,IF(COUNT(AA22:AA26)>3,Предпосылки!$B$151,Предпосылки!$B$148))*Предпосылки!$E$122*(1+Предпосылки!$B$152)^2,0) -> 180 | AB10: =ROUNDDOWN(AB3*IF(COUNT(AB22:AB26)<3,Предпосылки!$B$150,IF(COUNT(AB22:AB26)>3,Предпосылки!$B$151,Предпосылки!$B$148))*Предпосылки!$E$122*(1+Предпосылки!$B$152)^2,0) -> 162 | AC10: =ROUNDDOWN(AC3*IF(COUNT(AC22:AC26)<3,Предпосылки!$B$150,IF(COUNT(AC22:AC26)>3,Предпосылки!$B$151,Предпосылки!$B$148))*Предпосылки!$E$122*(1+Предпосылки!$B$152)^2,0) -> 162 | AD10: =ROUNDDOWN(AD3*IF(COUNT(AD22:AD26)<3,Предпосылки!$B$150,IF(COUNT(AD22:AD26)>3,Предпосылки!$B$151,Предпосылки!$B$148))*Предпосылки!$E$122*(1+Предпосылки!$B$152)^2,0) -> 230 | AE10: =ROUNDDOWN(AE3*IF(COUNT(AE22:AE26)<3,Предпосылки!$B$150,IF(COUNT(AE22:AE26)>3,Предпосылки!$B$151,Предпосылки!$B$148))*Предпосылки!$E$122*(1+Предпосылки!$B$152)^2,0) -> 230 | AF10: =ROUNDDOWN(AF3*IF(COUNT(AF22:AF26)<3,Предпосылки!$B$150,IF(COUNT(AF22:AF26)>3,Предпосылки!$B$151,Предпосылки!$B$148))*Предпосылки!$E$122*(1+Предпосылки!$B$152)^2,0) -> 162 | AG10: =ROUNDDOWN(AG3*IF(COUNT(AG22:AG26)<3,Предпосылки!$B$150,IF(COUNT(AG22:AG26)>3,Предпосылки!$B$151,Предпосылки!$B$148))*Предпосылки!$E$122*(1+Предпосылки!$B$152)^2,0) -> 157 | AH10: =ROUNDDOWN(AH3*IF(COUNT(AH22:AH26)<3,Предпосылки!$B$150,IF(COUNT(AH22:AH26)>3,Предпосылки!$B$151,Предпосылки!$B$148))*Предпосылки!$E$122*(1+Предпосылки!$B$152)^2,0) -> 179 | ... AK10: =ROUNDDOWN(AK3*IF(COUNT(AK22:AK26)<3,Предпосылки!$B$150,IF(COUNT(AK22:AK26)>3,Предпосылки!$B$151,Предпосылки!$B$148))*Предпосылки!$E$122*(1+Предпосылки!$B$152)^2,0) -> 187
A11: Количество купленных Fan-токенов | B11: =ROUNDDOWN(B3*IF(COUNT(B22:B26)>0,Предпосылки!$B$150,IF(COUNT(B22:B26)>3,Предпосылки!$B$151,Предпосылки!$B$148))*Предпосылки!$E$123,0) -> 161 | C11: =ROUNDDOWN(C3*IF(COUNT(C22:C26)>0,Предпосылки!$B$150,IF(COUNT(C22:C26)>3,Предпосылки!$B$151,Предпосылки!$B$148))*Предпосылки!$E$123,0) -> 161 | D11: =ROUNDDOWN(D3*IF(COUNT(D22:D26)>0,Предпосылки!$B$150,IF(COUNT(D22:D26)>3,Предпосылки!$B$151,Предпосылки!$B$148))*Предпосылки!$E$123,0) -> 145 | E11: =ROUNDDOWN(E3*IF(COUNT(E22:E26)>0,Предпосылки!$B$150,IF(COUNT(E22:E26)>3,Предпосылки!$B$151,Предпосылки!$B$148))*Предпосылки!$E$123,0) -> 140 | F11: =ROUNDDOWN(F3*IF(COUNT(F22:F26)>0,Предпосылки!$B$150,IF(COUNT(F22:F26)>3,Предпосылки!$B$151,Предпосылки!$B$148))*Предпосылки!$E$123,0) -> 140 | G11: =ROUNDDOWN(G3*IF(COUNT(G22:G26)>0,Предпосылки!$B$150,IF(COUNT(G22:G26)>3,Предпосылки!$B$151,Предпосылки!$B$148))*Предпосылки!$E$123,0) -> 130 | H11: =ROUNDDOWN(H3*IF(COUNT(H22:H26)>0,Предпосылки!$B$150,IF(COUNT(H22:H26)>3,Предпосылки!$B$151,Предпосылки!$B$148))*Предпосылки!$E$123,0) -> 126 | I11: =ROUNDDOWN(I3*IF(COUNT(I22:I26)>0,Предпосылки!$B$150,IF(COUNT(I22:I26)>3,Предпосылки!$B$151,Предпосылки!$B$148))*Предпосылки!$E$123,0) -> 126 | J11: =ROUNDDOWN(J3*IF(COUNT(J22:J26)<3,Предпосылки!$B$150,IF(COUNT(J22:J26)>3,Предпосылки!$B$151,Предпосылки!$B$148))*Предпосылки!$E$123,0) -> 225 | K11: =ROUNDDOWN(K3*IF(COUNT(K22:K26)<3,Предпосылки!$B$150,IF(COUNT(K22:K26)>3,Предпосылки!$B$151,Предпосылки!$B$148))*Предпосылки!$E$123,0) -> 159 | L11: =ROUNDDOWN(L3*IF(COUNT(L22:L26)<3,Предпосылки!$B$150,IF(COUNT(L22:L26)>3,Предпосылки!$B$151,Предпосылки!$B$148))*Предпосылки!$E$123,0) -> 159 | M11: =ROUNDDOWN(M3*IF(COUNT(M22:M26)<3,Предпосылки!$B$150,IF(COUNT(M22:M26)>3,Предпосылки!$B$151,Предпосылки!$B$148))*Предпосылки!$E$123,0) -> 161 | N11: =ROUNDDOWN(N3*IF(COUNT(N22:N26)<3,Предпосылки!$B$150,IF(COUNT(N22:N26)>3,Предпосылки!$B$151,Предпосылки!$B$148))*Предпосылки!$E$123,0) -> 166 | O11: =ROUNDDOWN(O3*IF(COUNT(O22:O26)<3,Предпосылки!$B$150,IF(COUNT(O22:O26)>3,Предпосылки!$B$151,Предпосылки!$B$148))*Предпосылки!$E$123,0) -> 166 | P11: =ROUNDDOWN(P3*IF(COUNT(P22:P26)<3,Предпосылки!$B$150,IF(COUNT(P22:P26)>3,Предпосылки!$B$151,Предпосылки!$B$148))*Предпосылки!$E$123,0) -> 140 | Q11: =ROUNDDOWN(Q3*IF(COUNT(Q22:Q26)<3,Предпосылки!$B$150,IF(COUNT(Q22:Q26)>3,Предпосылки!$B$151,Предпосылки!$B$148))*Предпосылки!$E$123,0) -> 145 | ... U11: =ROUNDDOWN(U3*IF(COUNT(U22:U26)<3,Предпосылки!$B$150,IF(COUNT(U22:U26)>3,Предпосылки!$B$151,Предпосылки!$B$148))*Предпосылки!$E$123,0) -> 145 | V11: =ROUNDDOWN(V3*IF(COUNT(V22:V26)<3,Предпосылки!$B$150,IF(COUNT(V22:V26)>3,Предпосылки!$B$151,Предпосылки!$B$148))*Предпосылки!$E$123*(1+Предпосылки!$B$152),0) -> 239 | W11: =ROUNDDOWN(W3*IF(COUNT(W22:W26)<3,Предпосылки!$B$150,IF(COUNT(W22:W26)>3,Предпосылки!$B$151,Предпосылки!$B$148))*Предпосылки!$E$123*(1+Предпосылки!$B$152),0) -> 169 | X11: =ROUNDDOWN(X3*IF(COUNT(X22:X26)<3,Предпосылки!$B$150,IF(COUNT(X22:X26)>3,Предпосылки!$B$151,Предпосылки!$B$148))*Предпосылки!$E$123*(1+Предпосылки!$B$152),0) -> 163 | Y11: =ROUNDDOWN(Y3*IF(COUNT(Y22:Y26)<3,Предпосылки!$B$150,IF(COUNT(Y22:Y26)>3,Предпосылки!$B$151,Предпосылки!$B$148))*Предпосылки!$E$123*(1+Предпосылки!$B$152),0) -> 176 | Z11: =ROUNDDOWN(Z3*IF(COUNT(Z22:Z26)<3,Предпосылки!$B$150,IF(COUNT(Z22:Z26)>3,Предпосылки!$B$151,Предпосылки!$B$148))*Предпосылки!$E$123*(1+Предпосылки!$B$152),0) -> 176 | AA11: =ROUNDDOWN(AA3*IF(COUNT(AA22:AA26)<3,Предпосылки!$B$150,IF(COUNT(AA22:AA26)>3,Предпосылки!$B$151,Предпосылки!$B$148))*Предпосылки!$E$123*(1+Предпосылки!$B$152)^2,0) -> 180 | AB11: =ROUNDDOWN(AB3*IF(COUNT(AB22:AB26)<3,Предпосылки!$B$150,IF(COUNT(AB22:AB26)>3,Предпосылки!$B$151,Предпосылки!$B$148))*Предпосылки!$E$123*(1+Предпосылки!$B$152)^2,0) -> 162 | AC11: =ROUNDDOWN(AC3*IF(COUNT(AC22:AC26)<3,Предпосылки!$B$150,IF(COUNT(AC22:AC26)>3,Предпосылки!$B$151,Предпосылки!$B$148))*Предпосылки!$E$123*(1+Предпосылки!$B$152)^2,0) -> 162 | AD11: =ROUNDDOWN(AD3*IF(COUNT(AD22:AD26)<3,Предпосылки!$B$150,IF(COUNT(AD22:AD26)>3,Предпосылки!$B$151,Предпосылки!$B$148))*Предпосылки!$E$123*(1+Предпосылки!$B$152)^2,0) -> 230 | AE11: =ROUNDDOWN(AE3*IF(COUNT(AE22:AE26)<3,Предпосылки!$B$150,IF(COUNT(AE22:AE26)>3,Предпосылки!$B$151,Предпосылки!$B$148))*Предпосылки!$E$123*(1+Предпосылки!$B$152)^2,0) -> 230 | AF11: =ROUNDDOWN(AF3*IF(COUNT(AF22:AF26)<3,Предпосылки!$B$150,IF(COUNT(AF22:AF26)>3,Предпосылки!$B$151,Предпосылки!$B$148))*Предпосылки!$E$123*(1+Предпосылки!$B$152)^2,0) -> 162 | AG11: =ROUNDDOWN(AG3*IF(COUNT(AG22:AG26)<3,Предпосылки!$B$150,IF(COUNT(AG22:AG26)>3,Предпосылки!$B$151,Предпосылки!$B$148))*Предпосылки!$E$123*(1+Предпосылки!$B$152)^2,0) -> 157 | AH11: =ROUNDDOWN(AH3*IF(COUNT(AH22:AH26)<3,Предпосылки!$B$150,IF(COUNT(AH22:AH26)>3,Предпосылки!$B$151,Предпосылки!$B$148))*Предпосылки!$E$123*(1+Предпосылки!$B$152)^2,0) -> 179 | ... AK11: =ROUNDDOWN(AK3*IF(COUNT(AK22:AK26)<3,Предпосылки!$B$150,IF(COUNT(AK22:AK26)>3,Предпосылки!$B$151,Предпосылки!$B$148))*Предпосылки!$E$123*(1+Предпосылки!$B$152)^2,0) -> 187
A12: Количество купленных классических ЦФА | B12: =ROUNDDOWN(B3*IF(COUNT(B22:B26)>0,Предпосылки!$B$150,(IF(COUNT(B22:B26)>3,Предпосылки!$B$151,Предпосылки!$B$148))+3%)*Предпосылки!$E$124,0) -> 195 | C12: =ROUNDDOWN(C3*IF(COUNT(C22:C26)>0,Предпосылки!$B$150,(IF(COUNT(C22:C26)>3,Предпосылки!$B$151,Предпосылки!$B$148))+2%)*Предпосылки!$E$124,0) -> 184 | D12: =ROUNDDOWN(D3*IF(COUNT(D22:D26)>0,Предпосылки!$B$150,(IF(COUNT(D22:D26)>3,Предпосылки!$B$151,Предпосылки!$B$148))+2%)*Предпосылки!$E$124,0) -> 145 | E12: =ROUNDDOWN(E3*IF(COUNT(E22:E26)>0,Предпосылки!$B$150,(IF(COUNT(E22:E26)>3,Предпосылки!$B$151,Предпосылки!$B$148))+2%)*Предпосылки!$E$124,0) -> 160 | F12: =ROUNDDOWN(F3*IF(COUNT(F22:F26)>0,Предпосылки!$B$150,(IF(COUNT(F22:F26)>3,Предпосылки!$B$151,Предпосылки!$B$148))+2%)*Предпосылки!$E$124,0) -> 160 | G12: =ROUNDDOWN(G3*IF(COUNT(G22:G26)>0,Предпосылки!$B$150,(IF(COUNT(G22:G26)>3,Предпосылки!$B$151,Предпосылки!$B$148))+2%)*Предпосылки!$E$124,0) -> 130 | H12: =ROUNDDOWN(H3*IF(COUNT(H22:H26)>0,Предпосылки!$B$150,(IF(COUNT(H22:H26)>3,Предпосылки!$B$151,Предпосылки!$B$148))+2%)*Предпосылки!$E$124,0) -> 144 | I12: =ROUNDDOWN(I3*IF(COUNT(I22:I26)>0,Предпосылки!$B$150,(IF(COUNT(I22:I26)>3,Предпосылки!$B$151,Предпосылки!$B$148))+2%)*Предпосылки!$E$124,0) -> 144 | J12: =ROUNDDOWN(J3*IF(COUNT(J22:J26)<3,Предпосылки!$B$150,(IF(COUNT(J22:J26)>3,Предпосылки!$B$151,Предпосылки!$B$148))+2%)*Предпосылки!$E$124,0) -> 247 | K12: =ROUNDDOWN(K3*IF(COUNT(K22:K26)<3,Предпосылки!$B$150,(IF(COUNT(K22:K26)>3,Предпосылки!$B$151,Предпосылки!$B$148))+2%)*Предпосылки!$E$124,0) -> 159 | L12: =ROUNDDOWN(L3*IF(COUNT(L22:L26)<3,Предпосылки!$B$150,(IF(COUNT(L22:L26)>3,Предпосылки!$B$151,Предпосылки!$B$148))+2%)*Предпосылки!$E$124,0) -> 159 | M12: =ROUNDDOWN(M3*IF(COUNT(M22:M26)<3,Предпосылки!$B$150,(IF(COUNT(M22:M26)>3,Предпосылки!$B$151,Предпосылки!$B$148))+2%)*Предпосылки!$E$124,0) -> 184 | N12: =ROUNDDOWN(N3*IF(COUNT(N22:N26)<3,Предпосылки!$B$150,(IF(COUNT(N22:N26)>3,Предпосылки!$B$151,Предпосылки!$B$148))+2%)*Предпосылки!$E$124,0) -> 166 | O12: =ROUNDDOWN(O3*IF(COUNT(O22:O26)<3,Предпосылки!$B$150,(IF(COUNT(O22:O26)>3,Предпосылки!$B$151,Предпосылки!$B$148))+2%)*Предпосылки!$E$124,0) -> 166 | P12: =ROUNDDOWN(P3*IF(COUNT(P22:P26)<3,Предпосылки!$B$150,(IF(COUNT(P22:P26)>3,Предпосылки!$B$151,Предпосылки!$B$148))+2%)*Предпосылки!$E$124,0) -> 160 | Q12: =ROUNDDOWN(Q3*IF(COUNT(Q22:Q26)<3,Предпосылки!$B$150,(IF(COUNT(Q22:Q26)>3,Предпосылки!$B$151,Предпосылки!$B$148))+2%)*Предпосылки!$E$124,0) -> 145 | ... U12: =ROUNDDOWN(U3*IF(COUNT(U22:U26)<3,Предпосылки!$B$150,(IF(COUNT(U22:U26)>3,Предпосылки!$B$151,Предпосылки!$B$148))+2%)*Предпосылки!$E$124,0) -> 145 | V12: =ROUNDDOWN(V3*IF(COUNT(V22:V26)<3,Предпосылки!$B$150,(IF(COUNT(V22:V26)>3,Предпосылки!$B$151,Предпосылки!$B$148))+3%)*Предпосылки!$E$124*(1+Предпосылки!$B$152),0) -> 274 | W12: =ROUNDDOWN(W3*IF(COUNT(W22:W26)<3,Предпосылки!$B$150,(IF(COUNT(W22:W26)>3,Предпосылки!$B$151,Предпосылки!$B$148))+3%)*Предпосылки!$E$124*(1+Предпосылки!$B$152),0) -> 169 | X12: =ROUNDDOWN(X3*IF(COUNT(X22:X26)<3,Предпосылки!$B$150,(IF(COUNT(X22:X26)>3,Предпосылки!$B$151,Предпосылки!$B$148))+3%)*Предпосылки!$E$124*(1+Предпосылки!$B$152),0) -> 198 | Y12: =ROUNDDOWN(Y3*IF(COUNT(Y22:Y26)<3,Предпосылки!$B$150,(IF(COUNT(Y22:Y26)>3,Предпосылки!$B$151,Предпосылки!$B$148))+3%)*Предпосылки!$E$124*(1+Предпосылки!$B$152),0) -> 176 | Z12: =ROUNDDOWN(Z3*IF(COUNT(Z22:Z26)<3,Предпосылки!$B$150,(IF(COUNT(Z22:Z26)>3,Предпосылки!$B$151,Предпосылки!$B$148))+3%)*Предпосылки!$E$124*(1+Предпосылки!$B$152),0) -> 176 | AA12: =ROUNDDOWN(AA3*IF(COUNT(AA22:AA26)<3,Предпосылки!$B$150,(IF(COUNT(AA22:AA26)>3,Предпосылки!$B$151,Предпосылки!$B$148))+3%)*Предпосылки!$E$124*(1+Предпосылки!$B$152)^2,0) -> 219 | AB12: =ROUNDDOWN(AB3*IF(COUNT(AB22:AB26)<3,Предпосылки!$B$150,(IF(COUNT(AB22:AB26)>3,Предпосылки!$B$151,Предпосылки!$B$148))+3%)*Предпосылки!$E$124*(1+Предпосылки!$B$152)^2,0) -> 162 | AC12: =ROUNDDOWN(AC3*IF(COUNT(AC22:AC26)<3,Предпосылки!$B$150,(IF(COUNT(AC22:AC26)>3,Предпосылки!$B$151,Предпосылки!$B$148))+3%)*Предпосылки!$E$124*(1+Предпосылки!$B$152)^2,0) -> 162 | AD12: =ROUNDDOWN(AD3*IF(COUNT(AD22:AD26)<3,Предпосылки!$B$150,(IF(COUNT(AD22:AD26)>3,Предпосылки!$B$151,Предпосылки!$B$148))+3%)*Предпосылки!$E$124*(1+Предпосылки!$B$152)^2,0) -> 264 | AE12: =ROUNDDOWN(AE3*IF(COUNT(AE22:AE26)<3,Предпосылки!$B$150,(IF(COUNT(AE22:AE26)>3,Предпосылки!$B$151,Предпосылки!$B$148))+3%)*Предпосылки!$E$124*(1+Предпосылки!$B$152)^2,0) -> 264 | AF12: =ROUNDDOWN(AF3*IF(COUNT(AF22:AF26)<3,Предпосылки!$B$150,(IF(COUNT(AF22:AF26)>3,Предпосылки!$B$151,Предпосылки!$B$148))+3%)*Предпосылки!$E$124*(1+Предпосылки!$B$152)^2,0) -> 162 | AG12: =ROUNDDOWN(AG3*IF(COUNT(AG22:AG26)<3,Предпосылки!$B$150,(IF(COUNT(AG22:AG26)>3,Предпосылки!$B$151,Предпосылки!$B$148))+3%)*Предпосылки!$E$124*(1+Предпосылки!$B$152)^2,0) -> 191 | AH12: =ROUNDDOWN(AH3*IF(COUNT(AH22:AH26)<3,Предпосылки!$B$150,(IF(COUNT(AH22:AH26)>3,Предпосылки!$B$151,Предпосылки!$B$148))+3%)*Предпосылки!$E$124*(1+Предпосылки!$B$152)^2,0) -> 179 | ... AK12: =ROUNDDOWN(AK3*IF(COUNT(AK22:AK26)<3,Предпосылки!$B$150,(IF(COUNT(AK22:AK26)>3,Предпосылки!$B$151,Предпосылки!$B$148))+3%)*Предпосылки!$E$124*(1+Предпосылки!$B$152)^2,0) -> 187
A13: Сумма приобретенных ЦФА | B13: =B$9*Предпосылки!$D$122 -> 517000 | C13: =C$9*Предпосылки!$D$122 -> 506000 | D13: =D$9*Предпосылки!$D$122 -> 435000 | E13: =E$9*Предпосылки!$D$122 -> 440000 | F13: =F$9*Предпосылки!$D$122 -> 440000 | G13: =G$9*Предпосылки!$D$122 -> 390000 | H13: =H$9*Предпосылки!$D$122 -> 396000 | I13: =I$9*Предпосылки!$D$122 -> 396000 | ... N13: =N$9*Предпосылки!$D$122 -> 498000 | O13: =O$9*1000 -> 498000 | P13: =P$9*1000 -> 440000 | Q13: =Q$9*1000 -> 435000 | R13: =R$9*1000 -> 435000 | S13: =S$9*1000 -> 440000 | T13: =T$9*1000 -> 435000 | U13: =U$9*1000 -> 435000 | V13: =V9*Предпосылки!$D$122 -> 752000 | W13: =W9*Предпосылки!$D$122 -> 507000 | X13: =X9*Предпосылки!$D$122 -> 524000 | Y13: =Y9*Предпосылки!$D$122 -> 528000 | Z13: =Z9*Предпосылки!$D$122 -> 528000 | AA13: =AA9*Предпосылки!$D$122 -> 579000 | AB13: =AB9*Предпосылки!$D$122 -> 486000 | AC13: =AC9*Предпосылки!$D$122 -> 486000 | ... AL13: =AL9*Предпосылки!$D$122 -> 0
A14: Сумма к выплате по ЦФА на скины | N14: =N6*(1+Предпосылки!$N$122)*Предпосылки!$B$153 -> 652791 | Z14: =Z6*(1+Предпосылки!$N$122)*Предпосылки!$B$153 -> 551475.45 | AL14: =AL6*(1+Предпосылки!$N$122)*Предпосылки!$B$153 -> 808682.92
A15: Сумма к выплате по Fan-токенам | N15: =N7*(1+Предпосылки!$N$123) -> 1338193.4 | Z15: =Z7*(1+Предпосылки!$N$123) -> 1113780.2 | AL15: =AL7*(1+Предпосылки!$N$123) -> 2437711.8
A16: Сумма к выплате по классическим ЦФА | N16: =N8*(1+Предпосылки!$N$124) -> 1474395.7 | Z16: =Z8*(1+Предпосылки!$N$124) -> 1202586.7 | AL16: =AL8*(1+Предпосылки!$N$124) -> 2659345.3
A17: Интеграция Alfa ID в платформу покупки внутриигровых продуктов | B17: =Расходы!$C$15 -> -500000
A18: Выплата ЦФА | N18: =-(SUM(N14:N16)) -> -3465380.1 | Z18: =-SUM(Z14:Z16) -> -2867842.4 | AH18: =-(SUM(AH14:AH16)) -> 0 | AL18: =-SUM(AL14:AL16) -> -5905740
A19: Аналитика | B19: =Расходы!C4 -> 0 | C19: =B19 -> 0 | D19: =C19 -> 0 | E19: =D19 -> 0 | F19: =E19 -> 0 | G19: =F19 -> 0 | H19: =G19 -> 0 | I19: =H19 -> 0 | J19: =I19 -> 0 | ... U19: =T19 -> 0 | V19: 0 | W19: =V19 -> 0 | X19: =W19 -> 0 | Y19: =X19 -> 0 | Z19: =Y19 -> 0 | AA19: =Z19 -> 0 | AB19: =AA19 -> 0 | AC19: =AB19 -> 0 | AD19: =AC19 -> 0 | ... AK19: =AJ19 -> 0 | AL19: 0
A20: Интернет-маркетинг | B20: =Расходы!C5 -> 0 | C20: =B20 -> 0 | D20: =C20 -> 0 | E20: =D20 -> 0 | F20: =E20 -> 0 | G20: =F20 -> 0 | H20: =G20 -> 0 | I20: =H20 -> 0 | J20: =I20 -> 0 | ... U20: =T20 -> 0 | V20: 0 | W20: =V20 -> 0 | X20: =W20 -> 0 | Y20: =X20 -> 0 | Z20: =Y20 -> 0 | AA20: =Z20 -> 0 | AB20: =AA20 -> 0 | AC20: =AB20 -> 0 | AD20: =AC20 -> 0 | ... AK20: =AJ20 -> 0 | AL20: 0
A21: Юридическая и экономическая подготовка | B21: =Расходы!C6 -> 0 | C21: =B21 -> 0 | D21: =C21 -> 0 | E21: =D21 -> 0 | F21: =E21 -> 0 | G21: =F21 -> 0 | H21: =G21 -> 0 | I21: =H21 -> 0 | J21: =I21 -> 0 | ... U21: =T21 -> 0 | V21: 0 | W21: =V21 -> 0 | X21: =W21 -> 0 | Y21: =X21 -> 0 | Z21: =Y21 -> 0 | AA21: =Z21 -> 0 | AB21: =AA21 -> 0 | AC21: =AB21 -> 0 | AD21: =AC21 -> 0 | ... AK21: =AJ21 -> 0 | AL21: 0
A22: Контент и образование 1 | D22: =Расходы!C8 -> 0 | G22: =D22 -> 0 | J22: =G22 -> 0 | M22: =J22 -> 0 | P22: =M22 -> 0 | S22: =P22 -> 0 | V22: 0 | X22: =Расходы!C42 -> 0 | Y22: 0 | AA22: =X22 -> 0 | AB22: 0 | AD22: =AA22 -> 0 | AE22: 0 | AG22: =AD22 -> 0 | AJ22: =AG22 -> 0
A23: Контент и образование 2 | D23: =Расходы!C9 -> 0 | G23: =D23 -> 0 | J23: =G23 -> 0 | M23: =J23 -> 0 | P23: =M23 -> 0 | S23: =P23 -> 0 | V23: 0 | X23: =Расходы!C43 -> 0 | Y23: 0 | AA23: =X23 -> 0 | AB23: 0 | AD23: =AA23 -> 0 | AE23: 0 | AG23: =AD23 -> 0 | AJ23: =AG23 -> 0
A24: PR и репутационные активности 1 | D24: =Расходы!C10 -> 0 | G24: =D24 -> 0 | J24: =G24 -> 0 | M24: =J24 -> 0 | P24: =M24 -> 0 | S24: =P24 -> 0 | V24: 0 | X24: =Расходы!C44 -> 0 | AA24: =X24 -> 0 | AD24: =AA24 -> 0 | AE24: 0 | AG24: =AD24 -> 0 | AJ24: =AG24 -> 0
A25: Контент и образование 3 | J25: =Расходы!C12 -> -50000 | V25: =Расходы!C12 -> -50000 | AD25: =Расходы!C46 -> 0 | AE25: =V25 -> -50000
A26: PR и репутационные активности 2 | J26: =Расходы!C13 -> -200000 | V26: =Расходы!C13 -> -200000 | AD26: =Расходы!C47 -> 0 | AE26: =V26 -> -200000
A27: Комиссия Оператора | B27: =-B$13*Расходы!$C$17 -> -10340 | C27: =-C$13*Расходы!$C$17 -> -10120 | D27: =-D$13*Расходы!$C$17 -> -8700 | E27: =-E$13*Расходы!$C$17 -> -8800 | F27: =-F$13*Расходы!$C$17 -> -8800 | G27: =-G$13*Расходы!$C$17 -> -7800 | H27: =-H$13*Расходы!$C$17 -> -7920 | I27: =-I$13*Расходы!$C$17 -> -7920 | ... U27: =-U$13*Расходы!$C$17 -> -8700 | V27: =-V13*Расходы!$C$17 -> -15040 | W27: =-W13*Расходы!$C$17 -> -10140 | X27: =-X13*Расходы!$C$17 -> -10480 | Y27: =-Y13*Расходы!$C$17 -> -10560 | Z27: =-Z13*Расходы!$C$17 -> -10560 | AA27: =-AA13*Расходы!$C$17 -> -11580 | AB27: =-AB13*Расходы!$C$17 -> -9720 | AC27: =-AC13*Расходы!$C$17 -> -9720 | ... AL27: =-AL13*Расходы!$C$17 -> 0
A28: Экстраординарные затраты | B28: =-Расходы!$C$21*B$13 -> -25850 | C28: =-Расходы!$C$21*C$13 -> -25300 | D28: =-Расходы!$C$21*D$13 -> -21750 | E28: =-Расходы!$C$21*E$13 -> -22000 | F28: =-Расходы!$C$21*F$13 -> -22000 | G28: =-Расходы!$C$21*G$13 -> -19500 | H28: =-Расходы!$C$21*H$13 -> -19800 | I28: =-Расходы!$C$21*I$13 -> -19800 | ... U28: =-Расходы!$C$21*U$13 -> -21750 | V28: =-Расходы!$C$21*V13 -> -37600 | W28: =-Расходы!$C$21*W13 -> -25350 | X28: =-Расходы!$C$21*X13 -> -26200 | Y28: =-Расходы!$C$21*Y13 -> -26400 | Z28: =-Расходы!$C$21*Z13 -> -26400 | AA28: =-Расходы!$C$21*AA13 -> -28950 | AB28: =-Расходы!$C$21*AB13 -> -24300 | AC28: =-Расходы!$C$21*AC13 -> -24300 | ... AL28: =-Расходы!$C$21*AL13 -> 0
A29: Сумма издержек | B29: =SUM(B17:B28) -> -536190 | C29: =SUM(C17:C28) -> -35420 | D29: =SUM(D17:D28) -> -30450 | E29: =SUM(E17:E28) -> -30800 | F29: =SUM(F17:F28) -> -30800 | G29: =SUM(G17:G28) -> -27300 | H29: =SUM(H17:H28) -> -27720 | I29: =SUM(I17:I28) -> -27720 | ... N29: =SUM(N17:N28) -> -3500240.1 | O29: =SUM(O19:O28) -> -34860 | P29: =SUM(P19:P28) -> -30800 | Q29: =SUM(Q19:Q28) -> -30450 | R29: =SUM(R19:R28) -> -30450 | S29: =SUM(S19:S28) -> -30800 | T29: =SUM(T19:T28) -> -30450 | U29: =SUM(U19:U28) -> -30450 | V29: =SUM(V17:V28) -> -302640 | W29: =SUM(W17:W28) -> -35490 | X29: =SUM(X17:X28) -> -36680 | Y29: =SUM(Y17:Y28) -> -36960 | Z29: =SUM(Z17:Z28) -> -2904802.4 | AA29: =SUM(AA17:AA28) -> -40530 | AB29: =SUM(AB17:AB28) -> -34020 | AC29: =SUM(AC17:AC28) -> -34020 | ... AL29: =SUM(AL17:AL28) -> -5905740
A30: Прибыль до налогооблажения | B30: =B13+B29 -> -19190 | C30: =C13+C29 -> 470580 | D30: =D13+D29 -> 404550 | E30: =E13+E29 -> 409200 | F30: =F13+F29 -> 409200 | G30: =G13+G29 -> 362700 | H30: =H13+H29 -> 368280 | I30: =I13+I29 -> 368280 | ... M30: =M13+M29 -> 470580 | N30: =N17+N13+N29 -> -3002240.1 | O30: =O17+O13+O29 -> 463140 | P30: =P17+P13+P29 -> 409200 | Q30: =Q17+Q13+Q29 -> 404550 | R30: =R17+R13+R29 -> 404550 | S30: =S17+S13+S29 -> 409200 | T30: =T17+T13+T29 -> 404550 | U30: =U17+U13+U29 -> 404550 | V30: =V13+V29 -> 449360 | W30: =W13+W29 -> 471510 | X30: =X13+X29 -> 487320 | Y30: =Y13+Y29 -> 491040 | Z30: =Z13+Z29 -> -2376802.4 | AA30: =AA13+AA29 -> 538470 | AB30: =AB13+AB29 -> 451980 | AC30: =AC13+AC29 -> 451980 | ... AL30: =AL13+AL29 -> -5905740
A31: Налог на прибыль | B31: =IF(B$30>0,B$30*Расходы!$C$22,0) -> 0 | C31: =IF(C$30>0,C$30*Расходы!$C$22,0) -> 23529 | D31: =IF(D$30>0,D$30*Расходы!$C$22,0) -> 20227.5 | E31: =IF(E$30>0,E$30*Расходы!$C$22,0) -> 20460 | F31: =IF(F$30>0,F$30*Расходы!$C$22,0) -> 20460 | G31: =IF(G$30>0,G$30*Расходы!$C$22,0) -> 18135 | H31: =IF(H$30>0,H$30*Расходы!$C$22,0) -> 18414 | I31: =IF(I$30>0,I$30*Расходы!$C$22,0) -> 18414 | ... U31: =IF(U$30>0,U$30*Расходы!$C$22,0) -> 20227.5 | V31: =IF(V30>0,V30*Расходы!$C$22,0) -> 22468 | W31: =IF(W30>0,W30*Расходы!$C$22,0) -> 23575.5 | X31: =IF(X30>0,X30*Расходы!$C$22,0) -> 24366 | Y31: =IF(Y30>0,Y30*Расходы!$C$22,0) -> 24552 | Z31: =IF(Z30>0,Z30*Расходы!$C$22,0) -> 0 | AA31: =IF(AA30>0,AA30*Расходы!$C$22,0) -> 26923.5 | AB31: =IF(AB30>0,AB30*Расходы!$C$22,0) -> 22599 | AC31: =IF(AC30>0,AC30*Расходы!$C$22,0) -> 22599 | ... AL31: =IF(AL30>0,AL30*Расходы!$C$22,0) -> 0
A32: Чистая прибыль | B32: =B30-B31 -> -19190 | C32: =C30-C31 -> 447051 | D32: =D30-D31 -> 384322.5 | E32: =E30-E31 -> 388740 | F32: =F30-F31 -> 388740 | G32: =G30-G31 -> 344565 | H32: =H30-H31 -> 349866 | I32: =I30-I31 -> 349866 | ... AL32: =AL30-AL31 -> -5905740
A34: Прибыль за 3 года | B34: =SUM(B32:U32,V32:AL32) -> 2799822.5
A36: Основные выводы | B36: В рамках оптимистичного сценария проект показывает наилучшие результаты. Он предполагает наличие устойчивого спроса на ЦФА, который не требует значительных маркетинговых затрат на пиар и "подогрев" аудитории. Выплаты по трем типам инструментов (ЦФА на скины, Fan-токены, классические ЦФА) распределены неравномерно (из-за условий), но суммарно соответствуют лимиту выпуска. Высокая месячная конверсия (0,14%) и уверенный рост рынка, подкрепленный глобальным трендом на токенизацию, позволяют достичь максимальной прибыли. Наибольшие выплаты приходятся на классические ЦФА, доминирование этого типа инструмента в портфеле объясняется спросом со стороны квалифицированных инвесторов на данный вид актива и рост привлекательности инвестиций в специфический рынок (видеоигровая индустрия). Этот сценарий характеризуется низкими рисками и высокой рентабельностью, так как основные издержки приходятся не на привлечение клиентов, а на операционную деятельность. Проект оказывается финансово состоятельным и крайне привлекательным для реализации.

Sheet Cash-Flow 2
A1: Расчет Cash-Flow для Сценария 2 (нейтральный)
A2: Период (мес.) | B2: 1 | C2: 2 | D2: 3 | E2: 4 | F2: 5 | G2: 6 | H2: 7 | I2: 8 | J2: 9 | K2: 10 | L2: 11 | M2: 12 | N2: 13 | O2: 14 | P2: 15 | Q2: 16 | R2: 17 | S2: 18 | T2: 19 | U2: 20 | V2: 21 | W2: 22 | X2: 23 | Y2: 24 | Z2: 25 | AA2: 26 | AB2: 27 | AC2: 28 | AD2: 29 | AE2: 30 | AF2: 31 | AG2: 32 | AH2: 33 | AI2: 34 | AJ2: 35 | AK2: 36 | AL2: 37
A3: Сезонность | B3: =IF(OR(B2=1,B2=2,B2=12,B2=13,B2=14,B2=24,B2=25,B2=26,B2=36),1+Предпосылки!$B$158,IF(OR(B2=9,B2=10,B2=11,B2=21,B2=22,B2=23,B2=33,B2=34,B2=35),1+Предпосылки!$B$157,IF(OR(B2=6,B2=7,B2=8),1+Предпосылки!$B$160,IF(OR(B2=3,B2=4,B2=5,B2=15,B2=16,B2=17,B2=27,B2=28,B2=29),Предпосылки!$B$159+1,1)))) -> 1.15 | C3: =IF(OR(C2=1,C2=2,C2=12,C2=13,C2=14,C2=24,C2=25,C2=26,C2=36),1+Предпосылки!$B$158,IF(OR(C2=9,C2=10,C2=11,C2=21,C2=22,C2=23,C2=33,C2=34,C2=35),1+Предпосылки!$B$157,IF(OR(C2=6,C2=7,C2=8),1+Предпосылки!$B$160,IF(OR(C2=3,C2=4,C2=5,C2=15,C2=16,C2=17,C2=27,C2=28,C2=29),Предпосылки!$B$159+1,1)))) -> 1.15 | D3: =IF(OR(D2=1,D2=2,D2=12,D2=13,D2=14,D2=24,D2=25,D2=26,D2=36),1+Предпосылки!$B$158,IF(OR(D2=9,D2=10,D2=11,D2=21,D2=22,D2=23,D2=33,D2=34,D2=35),1+Предпосылки!$B$157,IF(OR(D2=6,D2=7,D2=8),1+Предпосылки!$B$160,IF(OR(D2=3,D2=4,D2=5,D2=15,D2=16,D2=17,D2=27,D2=28,D2=29),Предпосылки!$B$159+1,1)))) -> 1 | E3: =IF(OR(E2=1,E2=2,E2=12,E2=13,E2=14,E2=24,E2=25,E2=26,E2=36),1+Предпосылки!$B$158,IF(OR(E2=9,E2=10,E2=11,E2=21,E2=22,E2=23,E2=33,E2=34,E2=35),1+Предпосылки!$B$157,IF(OR(E2=6,E2=7,E2=8),1+Предпосылки!$B$160,IF(OR(E2=3,E2=4,E2=5,E2=15,E2=16,E2=17,E2=27,E2=28,E2=29),Предпосылки!$B$159+1,1)))) -> 1 | F3: =IF(OR(F2=1,F2=2,F2=12,F2=13,F2=14,F2=24,F2=25,F2=26,F2=36),1+Предпосылки!$B$158,IF(OR(F2=9,F2=10,F2=11,F2=21,F2=22,F2=23,F2=33,F2=34,F2=35),1+Предпосылки!$B$157,IF(OR(F2=6,F2=7,F2=8),1+Предпосылки!$B$160,IF(OR(F2=3,F2=4,F2=5,F2=15,F2=16,F2=17,F2=27,F2=28,F2=29),Предпосылки!$B$159+1,1)))) -> 1 | G3: =IF(OR(G2=1,G2=2,G2=12,G2=13,G2=14,G2=24,G2=25,G2=26,G2=36),1+Предпосылки!$B$158,IF(OR(G2=9,G2=10,G2=11,G2=21,G2=22,G2=23,G2=33,G2=34,G2=35),1+Предпосылки!$B$157,IF(OR(G2=6,G2=7,G2=8),1+Предпосылки!$B$160,IF(OR(G2=3,G2=4,G2=5,G2=15,G2=16,G2=17,G2=27,G2=28,G2=29),Предпосылки!$B$159+1,1)))) -> 0.9 | H3: =IF(OR(H2=1,H2=2,H2=12,H2=13,H2=14,H2=24,H2=25,H2=26,H2=36),1+Предпосылки!$B$158,IF(OR(H2=9,H2=10,H2=11,H2=21,H2=22,H2=23,H2=33,H2=34,H2=35),1+Предпосылки!$B$157,IF(OR(H2=6,H2=7,H2=8),1+Предпосылки!$B$160,IF(OR(H2=3,H2=4,H2=5,H2=15,H2=16,H2=17,H2=27,H2=28,H2=29),Предпосылки!$B$159+1,1)))) -> 0.9 | I3: =IF(OR(I2=1,I2=2,I2=12,I2=13,I2=14,I2=24,I2=25,I2=26,I2=36),1+Предпосылки!$B$158,IF(OR(I2=9,I2=10,I2=11,I2=21,I2=22,I2=23,I2=33,I2=34,I2=35),1+Предпосылки!$B$157,IF(OR(I2=6,I2=7,I2=8),1+Предпосылки!$B$160,IF(OR(I2=3,I2=4,I2=5,I2=15,I2=16,I2=17,I2=27,I2=28,I2=29),Предпосылки!$B$159+1,1)))) -> 0.9 | ... U3: =IF(OR(U2=1,U2=2,U2=12,U2=13,U2=14,U2=24,U2=25,U2=26,U2=36),1+Предпосылки!$B$158,IF(OR(U2=9,U2=10,U2=11,U2=21,U2=22,U2=23,U2=33,U2=34,U2=35),1+Предпосылки!$B$157,IF(OR(U2=6,U2=7,U2=8),1+Предпосылки!$B$160,IF(OR(U2=3,U2=4,U2=5,U2=15,U2=16,U2=17,U2=27,U2=28,U2=29),Предпосылки!$B$159+1,1)))) -> 1 | V3: =IF(OR(V2=1,V2=2,V2=12,V2=13,V2=14,V2=24,V2=25,V2=26,V2=36),1+Предпосылки!$B$158,IF(OR(V2=9,V2=10,V2=11,V2=21,V2=22,V2=23,V2=33,V2=34,V2=35),1+Предпосылки!$B$157,IF(OR(V2=6,V2=7,V2=8),1+Предпосылки!$B$160,IF(OR(V2=6,V2=7,V2=8),1+Предпосылки!$B$160,IF(OR(V2=3,V2=4,V2=5,V2=15,V2=16,V2=17,V2=27,V2=28,V2=29),Предпосылки!$B$159+1,1))))) -> 1.1 | W3: =IF(OR(W2=1,W2=2,W2=12,W2=13,W2=14,W2=24,W2=25,W2=26,W2=36),1+Предпосылки!$B$158,IF(OR(W2=9,W2=10,W2=11,W2=21,W2=22,W2=23,W2=33,W2=34,W2=35),1+Предпосылки!$B$157,IF(OR(W2=6,W2=7,W2=8),1+Предпосылки!$B$160,IF(OR(W2=6,W2=7,W2=8),1+Предпосылки!$B$160,IF(OR(W2=3,W2=4,W2=5,W2=15,W2=16,W2=17,W2=27,W2=28,W2=29),Предпосылки!$B$159+1,1))))) -> 1.1 | X3: =IF(OR(X2=1,X2=2,X2=12,X2=13,X2=14,X2=24,X2=25,X2=26,X2=36),1+Предпосылки!$B$158,IF(OR(X2=9,X2=10,X2=11,X2=21,X2=22,X2=23,X2=33,X2=34,X2=35),1+Предпосылки!$B$157,IF(OR(X2=6,X2=7,X2=8),1+Предпосылки!$B$160,IF(OR(X2=6,X2=7,X2=8),1+Предпосылки!$B$160,IF(OR(X2=3,X2=4,X2=5,X2=15,X2=16,X2=17,X2=27,X2=28,X2=29),Предпосылки!$B$159+1,1))))) -> 1.1 | Y3: =IF(OR(Y2=1,Y2=2,Y2=12,Y2=13,Y2=14,Y2=24,Y2=25,Y2=26,Y2=36),1+Предпосылки!$B$158,IF(OR(Y2=9,Y2=10,Y2=11,Y2=21,Y2=22,Y2=23,Y2=33,Y2=34,Y2=35),1+Предпосылки!$B$157,IF(OR(Y2=6,Y2=7,Y2=8),1+Предпосылки!$B$160,IF(OR(Y2=6,Y2=7,Y2=8),1+Предпосылки!$B$160,IF(OR(Y2=3,Y2=4,Y2=5,Y2=15,Y2=16,Y2=17,Y2=27,Y2=28,Y2=29),Предпосылки!$B$159+1,1))))) -> 1.15 | Z3: =IF(OR(Z2=1,Z2=2,Z2=12,Z2=13,Z2=14,Z2=24,Z2=25,Z2=26,Z2=36),1+Предпосылки!$B$158,IF(OR(Z2=9,Z2=10,Z2=11,Z2=21,Z2=22,Z2=23,Z2=33,Z2=34,Z2=35),1+Предпосылки!$B$157,IF(OR(Z2=6,Z2=7,Z2=8),1+Предпосылки!$B$160,IF(OR(Z2=6,Z2=7,Z2=8),1+Предпосылки!$B$160,IF(OR(Z2=3,Z2=4,Z2=5,Z2=15,Z2=16,Z2=17,Z2=27,Z2=28,Z2=29),Предпосылки!$B$159+1,1))))) -> 1.15 | AA3: =IF(OR(AA2=1,AA2=2,AA2=12,AA2=13,AA2=14,AA2=24,AA2=25,AA2=26,AA2=36),1+Предпосылки!$B$158,IF(OR(AA2=9,AA2=10,AA2=11,AA2=21,AA2=22,AA2=23,AA2=33,AA2=34,AA2=35),1+Предпосылки!$B$157,IF(OR(AA2=6,AA2=7,AA2=8),1+Предпосылки!$B$160,IF(OR(AA2=6,AA2=7,AA2=8),1+Предпосылки!$B$160,IF(OR(AA2=3,AA2=4,AA2=5,AA2=15,AA2=16,AA2=17,AA2=27,AA2=28,AA2=29),Предпосылки!$B$159+1,1))))) -> 1.15 | AB3: =IF(OR(AB2=1,AB2=2,AB2=12,AB2=13,AB2=14,AB2=24,AB2=25,AB2=26,AB2=36),1+Предпосылки!$B$158,IF(OR(AB2=9,AB2=10,AB2=11,AB2=21,AB2=22,AB2=23,AB2=33,AB2=34,AB2=35),1+Предпосылки!$B$157,IF(OR(AB2=6,AB2=7,AB2=8),1+Предпосылки!$B$160,IF(OR(AB2=6,AB2=7,AB2=8),1+Предпосылки!$B$160,IF(OR(AB2=3,AB2=4,AB2=5,AB2=15,AB2=16,AB2=17,AB2=27,AB2=28,AB2=29),Предпосылки!$B$159+1,1))))) -> 1 | AC3: =IF(OR(AC2=1,AC2=2,AC2=12,AC2=13,AC2=14,AC2=24,AC2=25,AC2=26,AC2=36),1+Предпосылки!$B$158,IF(OR(AC2=9,AC2=10,AC2=11,AC2=21,AC2=22,AC2=23,AC2=33,AC2=34,AC2=35),1+Предпосылки!$B$157,IF(OR(AC2=6,AC2=7,AC2=8),1+Предпосылки!$B$160,IF(OR(AC2=6,AC2=7,AC2=8),1+Предпосылки!$B$160,IF(OR(AC2=3,AC2=4,AC2=5,AC2=15,AC2=16,AC2=17,AC2=27,AC2=28,AC2=29),Предпосылки!$B$159+1,1))))) -> 1 | ... AK3: =IF(OR(AK2=1,AK2=2,AK2=12,AK2=13,AK2=14,AK2=24,AK2=25,AK2=26,AK2=36),1+Предпосылки!$B$158,IF(OR(AK2=9,AK2=10,AK2=11,AK2=21,AK2=22,AK2=23,AK2=33,AK2=34,AK2=35),1+Предпосылки!$B$157,IF(OR(AK2=6,AK2=7,AK2=8),1+Предпосылки!$B$160,IF(OR(AK2=6,AK2=7,AK2=8),1+Предпосылки!$B$160,IF(OR(AK2=3,AK2=4,AK2=5,AK2=15,AK2=16,AK2=17,AK2=27,AK2=28,AK2=29),Предпосылки!$B$159+1,1))))) -> 1.15
A4: Лимит суммы выпуска ЦФА | B4: =Предпосылки!$H$125 -> 300000000 | C4: =B$4-B$13 -> 299725000 | D4: =C$4-C$13 -> 299450000 | E4: =D$4-D$13 -> 299015000 | F4: =E$4-E$13 -> 298775000 | G4: =F$4-F$13 -> 298535000 | H4: =G$4-G$13 -> 298145000 | I4: =H$4-H$13 -> 297929000 | J4: =I$4-I$13 -> 297713000 | ... U4: =T$4-T$13 -> 293672000 | V4: =U4-U13 -> 293237000 | W4: =V4-V13 -> 292485000 | X4: =W4-W13 -> 291978000 | Y4: =X4-X13 -> 291700000 | Z4: =Y4-Y13 -> 291172000 | AA4: =Z4-Z13 -> 290644000 | AB4: =AA4-AA13 -> 290335000 | AC4: =AB4-AB13 -> 289849000 | ... AL4: =AK4-AK13 -> 285231000
A5: Накопленная сумма к выплате | C5: =B$13+B5 -> 275000 | D5: =C$13+C5 -> 550000 | E5: =D$13+D5 -> 985000 | F5: =E$13+E5 -> 1225000 | G5: =F$13+F5 -> 1465000 | H5: =G$13+G5 -> 1855000 | I5: =H$13+H5 -> 2071000 | J5: =I$13+I5 -> 2287000 | ... U5: =T$13+T5 -> 6328000 | V5: =V13+U5 -> 7080000 | W5: =V13+V5 -> 7832000 | X5: =W13+W5 -> 8339000 | Y5: =X13+X5 -> 8617000 | Z5: =Y13+Y5 -> 9145000 | AA5: =Z13+Z5 -> 9673000 | AB5: =AA13+AA5 -> 9982000 | AC5: =AB13+AB5 -> 10468000 | AD5: =AC13+AC5 -> 10954000 | ... AK5: =AJ13+AJ5 -> 14525000
A6: Сумма к выплате по ЦФА на скины | B6: 0 | C6: =(B6+B10*Предпосылки!$D$122)/(1+Предпосылки!$D$172/12)^(C$2-1) -> 79234.071 | D6: =(C6+C10*Предпосылки!$D$122)/(1+Предпосылки!$D$172/12)^(D$2-1) -> 156199.62 | E6: =(D6+D10*Предпосылки!$D$122)/(1+Предпосылки!$D$172/12)^(E$2-1) -> 292631.02 | F6: =(E6+E10*Предпосылки!$D$122)/(1+Предпосылки!$D$172/12)^(F$2-1) -> 348941.7 | G6: =(F6+F10*Предпосылки!$D$122)/(1+Предпосылки!$D$172/12)^(G$2-1) -> 399267.08 | H6: =(G6+G10*Предпосылки!$D$122)/(1+Предпосылки!$D$172/12)^(H$2-1) -> 499581.98 | I6: =(H6+H10*Предпосылки!$D$122)/(1+Предпосылки!$D$172/12)^(I$2-1) -> 525944.22 | J6: =(I6+I10*Предпосылки!$D$122)/(1+Предпосылки!$D$172/12)^(J$2-1) -> 545318.23 | ... N6: =(M6+M10*Предпосылки!$D$122)/(1+Предпосылки!$D$172/12)^(N$2-1) -> 735882.58 | O6: =(N10*Предпосылки!$D$122)/(1+Предпосылки!$D$92/12)^(O$2-1) -> 80000 | P6: =(O10*Предпосылки!$D$122)/(1+Предпосылки!$D$92/12)^(P$2-1) -> 166000 | Q6: =(P10*Предпосылки!$D$122)/(1+Предпосылки!$D$92/12)^(Q$2-1) -> 70000 | R6: =(Q10*Предпосылки!$D$122)/(1+Предпосылки!$D$92/12)^(R$2-1) -> 145000 | S6: =(R10*Предпосылки!$D$122)/(1+Предпосылки!$D$92/12)^(S$2-1) -> 145000 | T6: =(S10*Предпосылки!$D$122)/(1+Предпосылки!$D$92/12)^(T$2-1) -> 70000 | U6: =(T10*Предпосылки!$D$122)/(1+Предпосылки!$D$92/12)^(U$2-1) -> 145000 | V6: =(U6+U10*Предпосылки!$D$122)/(1+Предпосылки!$D$173/12)^(U$2-1) -> 256007.7 | W6: =(V6+V10*Предпосылки!$D$122)/(1+Предпосылки!$D$173/12)^(C$2-1) -> 491770.21 | X6: =(W6+W10*Предпосылки!$D$122)/(1+Предпосылки!$D$173/12)^(D$2-1) -> 652155.24 | Y6: =(X6+X10*Предпосылки!$D$122)/(1+Предпосылки!$D$173/12)^(E$2-1) -> 718864 | Z6: =(Y6+Y10*Предпосылки!$D$122)/(1+Предпосылки!$D$173/12)^(F$2-1) -> 871682.04 | AA6: =(Z10*Предпосылки!$D$122)/(1+Предпосылки!$D$174/12)^(G$2-1) -> 170955.29 | AB6: =(AA6+AA10*Предпосылки!$D$122)/(1+Предпосылки!$D$174/12)^(H$2-1) -> 252005.47 | AC6: =(AB6+AB10*Предпосылки!$D$122)/(1+Предпосылки!$D$174/12)^(I$2-1) -> 397487.9 | AD6: =(AC6+AC10*Предпосылки!$D$122)/(1+Предпосылки!$D$174/12)^(J$2-1) -> 534050.72 | AE6: =(AD6+AD10*Предпосылки!$D$122)/(1+Предпосылки!$D$174/12)^(K$2-1) -> 725083.41 | AF6: =(AE6+AE10*Предпосылки!$D$122)/(1+Предпосылки!$D$174/12)^(L$2-1) -> 901116.75 | AG6: =(AF6+AF10*Предпосылки!$D$122)/(1+Предпосылки!$D$174/12)^(M$2-1) -> 997228.53 | AH6: =(AG6+AG10*Предпосылки!$D$122)/(1+Предпосылки!$D$174/12)^(N$2-1) -> 1002740.4 | AI6: =(AH6+AH10*Предпосылки!$D$122)/(1+Предпосылки!$D$174/12)^(O$2-1) -> 1095680 | ... AL6: =(AK6+AK10*Предпосылки!$D$122)/(1+Предпосылки!$D$174/12)^(R$2-1) -> 1223331.7
A7: Сумма к выплате по Fan-токенам | B7: 0 | C7: =(B7+B11*Предпосылки!$D$122)/(1+Предпосылки!$D$172/12)^(C$2-1) -> 79234.071 | D7: =(C7+C11*Предпосылки!$D$122)/(1+Предпосылки!$D$172/12)^(D$2-1) -> 156199.62 | E7: =(D7+D11*Предпосылки!$D$122)/(1+Предпосылки!$D$172/12)^(E$2-1) -> 292631.02 | F7: =(E7+E11*Предпосылки!$D$122)/(1+Предпосылки!$D$172/12)^(F$2-1) -> 348941.7 | G7: =(F7+F11*Предпосылки!$D$122)/(1+Предпосылки!$D$172/12)^(G$2-1) -> 399267.08 | H7: =(G7+G11*Предпосылки!$D$122)/(1+Предпосылки!$D$172/12)^(H$2-1) -> 499581.98 | I7: =(H7+H11*Предпосылки!$D$122)/(1+Предпосылки!$D$172/12)^(I$2-1) -> 525944.22 | J7: =(I7+I11*Предпосылки!$D$122)/(1+Предпосылки!$D$172/12)^(J$2-1) -> 545318.23 | ... N7: =(M7+M11*Предпосылки!$D$122)/(1+Предпосылки!$D$172/12)^(N$2-1) -> 735882.58 | O7: =(N11*Предпосылки!$D$122)/(1+Предпосылки!$D$173/12)^(O$2-1) -> 73458.732 | P7: =(O11*Предпосылки!$D$122)/(1+Предпосылки!$D$173/12)^(P$2-1) -> 151429.96 | Q7: =(P11*Предпосылки!$D$122)/(1+Предпосылки!$D$173/12)^(Q$2-1) -> 63438.369 | R7: =(Q11*Предпосылки!$D$122)/(1+Предпосылки!$D$173/12)^(R$2-1) -> 130548.61 | S7: =(R11*Предпосылки!$D$122)/(1+Предпосылки!$D$173/12)^(S$2-1) -> 129694.78 | T7: =(S11*Предпосылки!$D$122)/(1+Предпосылки!$D$173/12)^(T$2-1) -> 62201.779 | U7: =(T11*Предпосылки!$D$122)/(1+Предпосылки!$D$173/12)^(U$2-1) -> 128003.85 | V7: =(U7+U11*Предпосылки!$D$122)/(1+Предпосылки!$D$173/12)^(U$2-1) -> 241003.75 | W7: =(V7+V11*Предпосылки!$D$122)/(1+Предпосылки!$D$173/12)^(C$2-1) -> 476864.39 | X7: =(W7+W11*Предпосылки!$D$122)/(1+Предпосылки!$D$173/12)^(D$2-1) -> 637443.76 | Y7: =(X7+X11*Предпосылки!$D$122)/(1+Предпосылки!$D$173/12)^(E$2-1) -> 704439.29 | Z7: =(Y7+Y11*Предпосылки!$D$122)/(1+Предпосылки!$D$173/12)^(F$2-1) -> 857631.01 | AA7: =(Z11*Предпосылки!$D$122)/(1+Предпосылки!$D$174/12)^(G$2-1) -> 170955.29 | AB7: =AA7+(AA11*Предпосылки!$D$122)/(1+Предпосылки!$D$174/12)^(H$2-1) -> 257868.62 | AC7: =AB7+(AB11*Предпосылки!$D$122)/(1+Предпосылки!$D$174/12)^(I$2-1) -> 413405.3 | AD7: =AC7+(AC11*Предпосылки!$D$122)/(1+Предпосылки!$D$174/12)^(J$2-1) -> 568039.96 | AE7: =AD7+(AD11*Предпосылки!$D$122)/(1+Предпосылки!$D$174/12)^(K$2-1) -> 786309.74 | AF7: =AE7+(AE11*Предпосылки!$D$122)/(1+Предпосылки!$D$174/12)^(L$2-1) -> 1003313.7 | AG7: =AF7+(AF11*Предпосылки!$D$122)/(1+Предпосылки!$D$174/12)^(M$2-1) -> 1155273.5 | AH7: =AG7+(AG11*Предпосылки!$D$122)/(1+Предпосылки!$D$174/12)^(N$2-1) -> 1228015 | AI7: =AH7+(AH11*Предпосылки!$D$122)/(1+Предпосылки!$D$174/12)^(O$2-1) -> 1393979.3 | ... AL7: =AK7+(AK11*Предпосылки!$D$122)/(1+Предпосылки!$D$174/12)^(R$2-1) -> 1808178.6
A8: Сумма к выплате по классическим ЦФА | B8: 0 | C8: =(B8+B12*Предпосылки!$D$122)/(1+Предпосылки!$D$172/12)^(C$2-1) -> 113898.98 | D8: =(C8+C12*Предпосылки!$D$122)/(1+Предпосылки!$D$172/12)^(D$2-1) -> 224536.95 | E8: =(D8+D12*Предпосылки!$D$122)/(1+Предпосылки!$D$172/12)^(E$2-1) -> 359024.27 | F8: =(E8+E12*Предпосылки!$D$122)/(1+Предпосылки!$D$172/12)^(F$2-1) -> 441696.11 | G8: =(F8+F12*Предпосылки!$D$122)/(1+Предпосылки!$D$172/12)^(G$2-1) -> 516256.61 | H8: =(G8+G12*Предпосылки!$D$122)/(1+Предпосылки!$D$172/12)^(H$2-1) -> 610009.9 | I8: =(H8+H12*Предпосылки!$D$122)/(1+Предпосылки!$D$172/12)^(I$2-1) -> 654422.25 | J8: =(I8+I12*Предпосылки!$D$122)/(1+Предпосылки!$D$172/12)^(J$2-1) -> 689279.23 | ... N8: =(M8+M12*Предпосылки!$D$122)/(1+Предпосылки!$D$172/12)^(N$2-1) -> 882465.77 | O8: =(N12*Предпосылки!$D$122)/(1+Предпосылки!$D$173/12)^(O$2-1) -> 105596.93 | P8: =(O12*Предпосылки!$D$122)/(1+Предпосылки!$D$173/12)^(P$2-1) -> 151429.96 | Q8: =(P12*Предпосылки!$D$122)/(1+Предпосылки!$D$173/12)^(Q$2-1) -> 81563.618 | R8: =(Q12*Предпосылки!$D$122)/(1+Предпосылки!$D$173/12)^(R$2-1) -> 130548.61 | S8: =(R12*Предпосылки!$D$122)/(1+Предпосылки!$D$173/12)^(S$2-1) -> 129694.78 | T8: =(S12*Предпосылки!$D$122)/(1+Предпосылки!$D$173/12)^(T$2-1) -> 79973.716 | U8: =(T12*Предпосылки!$D$122)/(1+Предпосылки!$D$173/12)^(U$2-1) -> 128003.85 | V8: =(U8+U12*Предпосылки!$D$122)/(1+Предпосылки!$D$173/12)^(U$2-1) -> 241003.75 | W8: =(V8+V12*Предпосылки!$D$122)/(1+Предпосылки!$D$173/12)^(C$2-1) -> 511635.48 | X8: =(W8+W12*Предпосылки!$D$122)/(1+Предпосылки!$D$173/12)^(D$2-1) -> 671761.51 | Y8: =(X8+X12*Предпосылки!$D$122)/(1+Предпосылки!$D$173/12)^(E$2-1) -> 772405.85 | Z8: =(Y8+Y12*Предпосылки!$D$122)/(1+Предпосылки!$D$173/12)^(F$2-1) -> 923836.85 | AA8: =(Z12*Предпосылки!$D$122)/(1+Предпосылки!$D$174/12)^(G$2-1) -> 170955.29 | AB8: =AA8+(AA12*Предпосылки!$D$122)/(1+Предпосылки!$D$174/12)^(H$2-1) -> 295531.06 | AC8: =AB8+(AB12*Предпосылки!$D$122)/(1+Предпосылки!$D$174/12)^(I$2-1) -> 451067.75 | AD8: =AC8+(AC12*Предпосылки!$D$122)/(1+Предпосылки!$D$174/12)^(J$2-1) -> 605702.4 | AE8: =AD8+(AD12*Предпосылки!$D$122)/(1+Предпосылки!$D$174/12)^(K$2-1) -> 856238.15 | AF8: =AE8+(AE12*Предпосылки!$D$122)/(1+Предпосылки!$D$174/12)^(L$2-1) -> 1105320.9 | AG8: =AF8+(AF12*Предпосылки!$D$122)/(1+Предпосылки!$D$174/12)^(M$2-1) -> 1257280.7 | AH8: =AG8+(AG12*Предпосылки!$D$122)/(1+Предпосылки!$D$174/12)^(N$2-1) -> 1361730.1 | AI8: =AH8+(AH12*Предпосылки!$D$122)/(1+Предпосылки!$D$174/12)^(O$2-1) -> 1527694.4 | ... AL8: =AK8+(AK12*Предпосылки!$D$122)/(1+Предпосылки!$D$174/12)^(R$2-1) -> 1975802.4
A9: Количество купленных ЦФА | B9: =SUM(B10:B12) -> 275 | C9: =SUM(C10:C12) -> 275 | D9: =SUM(D10:D12) -> 435 | E9: =SUM(E10:E12) -> 240 | F9: =SUM(F10:F12) -> 240 | G9: =SUM(G10:G12) -> 390 | H9: =SUM(H10:H12) -> 216 | I9: =SUM(I10:I12) -> 216 | ... AK9: =SUM(AK10:AK12) -> 561
A10: Количество купленных ЦФА на скины | B10: =ROUNDDOWN(B3*IF(COUNT(B22:B26)>0,Предпосылки!$B$150,IF(COUNT(B22:B26)>3,Предпосылки!$B$151,Предпосылки!$B$149))*Предпосылки!$E$122,0) -> 80 | C10: =ROUNDDOWN(C3*IF(COUNT(C22:C26)>0,Предпосылки!$B$150,IF(COUNT(C22:C26)>3,Предпосылки!$B$151,Предпосылки!$B$149))*Предпосылки!$E$122,0) -> 80 | D10: =ROUNDDOWN(D3*IF(COUNT(D22:D26)>0,Предпосылки!$B$150,IF(COUNT(D22:D26)>3,Предпосылки!$B$151,Предпосылки!$B$149))*Предпосылки!$E$122,0) -> 145 | E10: =ROUNDDOWN(E3*IF(COUNT(E22:E26)>0,Предпосылки!$B$150,IF(COUNT(E22:E26)>3,Предпосылки!$B$151,Предпосылки!$B$149))*Предпосылки!$E$122,0) -> 70 | F10: =ROUNDDOWN(F3*IF(COUNT(F22:F26)>0,Предпосылки!$B$150,IF(COUNT(F22:F26)>3,Предпосылки!$B$151,Предпосылки!$B$149))*Предпосылки!$E$122,0) -> 70 | G10: =ROUNDDOWN(G3*IF(COUNT(G22:G26)>0,Предпосылки!$B$150,IF(COUNT(G22:G26)>3,Предпосылки!$B$151,Предпосылки!$B$149))*Предпосылки!$E$122,0) -> 130 | H10: =ROUNDDOWN(H3*IF(COUNT(H22:H26)>0,Предпосылки!$B$150,IF(COUNT(H22:H26)>3,Предпосылки!$B$151,Предпосылки!$B$149))*Предпосылки!$E$122,0) -> 63 | I10: =ROUNDDOWN(I3*IF(COUNT(I22:I26)>0,Предпосылки!$B$150,IF(COUNT(I22:I26)>3,Предпосылки!$B$151,Предпосылки!$B$149))*Предпосылки!$E$122,0) -> 63 | ... N10: =ROUNDDOWN(N3*IF(COUNT(N22:N26)>0,Предпосылки!$B$150,IF(COUNT(N22:N26)>3,Предпосылки!$B$151,Предпосылки!$B$149))*Предпосылки!$E$122,0) -> 80 | O10: =ROUNDDOWN(O3*IF(COUNT(O22:O26)<3,Предпосылки!$B$150,IF(COUNT(O22:O26)>3,Предпосылки!$B$151,Предпосылки!$B$149))*Предпосылки!$E$122,0) -> 166 | P10: =ROUNDDOWN(P3*IF(COUNT(P22:P26)<3,Предпосылки!$B$150,IF(COUNT(P22:P26)>3,Предпосылки!$B$151,Предпосылки!$B$149))*Предпосылки!$E$122,0) -> 70 | Q10: =ROUNDDOWN(Q3*IF(COUNT(Q22:Q26)<3,Предпосылки!$B$150,IF(COUNT(Q22:Q26)>3,Предпосылки!$B$151,Предпосылки!$B$149))*Предпосылки!$E$122,0) -> 145 | R10: =ROUNDDOWN(R3*IF(COUNT(R22:R26)<3,Предпосылки!$B$150,IF(COUNT(R22:R26)>3,Предпосылки!$B$151,Предпосылки!$B$149))*Предпосылки!$E$122,0) -> 145 | S10: =ROUNDDOWN(S3*IF(COUNT(S22:S26)<3,Предпосылки!$B$150,IF(COUNT(S22:S26)>3,Предпосылки!$B$151,Предпосылки!$B$149))*Предпосылки!$E$122,0) -> 70 | T10: =ROUNDDOWN(T3*IF(COUNT(T22:T26)<3,Предпосылки!$B$150,IF(COUNT(T22:T26)>3,Предпосылки!$B$151,Предпосылки!$B$149))*Предпосылки!$E$122,0) -> 145 | U10: =ROUNDDOWN(U3*IF(COUNT(U22:U26)<3,Предпосылки!$B$150,IF(COUNT(U22:U26)>3,Предпосылки!$B$151,Предпосылки!$B$149))*Предпосылки!$E$122,0) -> 145 | V10: =ROUNDDOWN(V3*IF(COUNT(V22:V26)<3,Предпосылки!$B$150,IF(COUNT(V22:V26)>3,Предпосылки!$B$151,Предпосылки!$B$149))*Предпосылки!$E$122*(1+Предпосылки!$B$152),0) -> 239 | W10: =ROUNDDOWN(W3*IF(COUNT(W22:W26)<3,Предпосылки!$B$150,IF(COUNT(W22:W26)>3,Предпосылки!$B$151,Предпосылки!$B$149))*Предпосылки!$E$122*(1+Предпосылки!$B$152),0) -> 169 | X10: =ROUNDDOWN(X3*IF(COUNT(X22:X26)<3,Предпосылки!$B$150,IF(COUNT(X22:X26)>3,Предпосылки!$B$151,Предпосылки!$B$149))*Предпосылки!$E$122*(1+Предпосылки!$B$152),0) -> 81 | Y10: =ROUNDDOWN(Y3*IF(COUNT(Y22:Y26)<3,Предпосылки!$B$150,IF(COUNT(Y22:Y26)>3,Предпосылки!$B$151,Предпосылки!$B$149))*Предпосылки!$E$122*(1+Предпосылки!$B$152),0) -> 176 | Z10: =ROUNDDOWN(Z3*IF(COUNT(Z22:Z26)<3,Предпосылки!$B$150,IF(COUNT(Z22:Z26)>3,Предпосылки!$B$151,Предпосылки!$B$149))*Предпосылки!$E$122*(1+Предпосылки!$B$152),0) -> 176 | AA10: =ROUNDDOWN(AA3*IF(COUNT(AA22:AA26)<3,Предпосылки!$B$150,IF(COUNT(AA22:AA26)>3,Предпосылки!$B$151,Предпосылки!$B$149))*Предпосылки!$E$122*(1+Предпосылки!$B$152)^2,0) -> 90 | AB10: =ROUNDDOWN(AB3*IF(COUNT(AB22:AB26)<3,Предпосылки!$B$150,IF(COUNT(AB22:AB26)>3,Предпосылки!$B$151,Предпосылки!$B$149))*Предпосылки!$E$122*(1+Предпосылки!$B$152)^2,0) -> 162 | AC10: =ROUNDDOWN(AC3*IF(COUNT(AC22:AC26)<3,Предпосылки!$B$150,IF(COUNT(AC22:AC26)>3,Предпосылки!$B$151,Предпосылки!$B$149))*Предпосылки!$E$122*(1+Предпосылки!$B$152)^2,0) -> 162 | AD10: =ROUNDDOWN(AD3*IF(COUNT(AD22:AD26)<3,Предпосылки!$B$150,IF(COUNT(AD22:AD26)>3,Предпосылки!$B$151,Предпосылки!$B$149))*Предпосылки!$E$122*(1+Предпосылки!$B$152)^2,0) -> 230 | AE10: =ROUNDDOWN(AE3*IF(COUNT(AE22:AE26)<3,Предпосылки!$B$150,IF(COUNT(AE22:AE26)>3,Предпосылки!$B$151,Предпосылки!$B$149))*Предпосылки!$E$122*(1+Предпосылки!$B$152)^2,0) -> 230 | AF10: =ROUNDDOWN(AF3*IF(COUNT(AF22:AF26)<3,Предпосылки!$B$150,IF(COUNT(AF22:AF26)>3,Предпосылки!$B$151,Предпосылки!$B$149))*Предпосылки!$E$122*(1+Предпосылки!$B$152)^2,0) -> 162 | AG10: =ROUNDDOWN(AG3*IF(COUNT(AG22:AG26)<3,Предпосылки!$B$150,IF(COUNT(AG22:AG26)>3,Предпосылки!$B$151,Предпосылки!$B$149))*Предпосылки!$E$122*(1+Предпосылки!$B$152)^2,0) -> 78 | AH10: =ROUNDDOWN(AH3*IF(COUNT(AH22:AH26)<3,Предпосылки!$B$150,IF(COUNT(AH22:AH26)>3,Предпосылки!$B$151,Предпосылки!$B$149))*Предпосылки!$E$122*(1+Предпосылки!$B$152)^2,0) -> 179 | ... AL10: =ROUNDDOWN(AL3*IF(COUNT(AL22:AL26)<3,Предпосылки!$B$150,IF(COUNT(AL22:AL26)>3,Предпосылки!$B$151,Предпосылки!$B$149))*Предпосылки!$E$122*(1+Предпосылки!$B$152)^2,0) -> 0
A11: Количество купленных Fan-токенов | B11: =ROUNDDOWN(B3*IF(COUNT(B22:B26)>0,Предпосылки!$B$150,IF(COUNT(B22:B26)>3,Предпосылки!$B$151,Предпосылки!$B$149))*Предпосылки!$E$123,0) -> 80 | C11: =ROUNDDOWN(C3*IF(COUNT(C22:C26)>0,Предпосылки!$B$150,IF(COUNT(C22:C26)>3,Предпосылки!$B$151,Предпосылки!$B$149))*Предпосылки!$E$123,0) -> 80 | D11: =ROUNDDOWN(D3*IF(COUNT(D22:D26)>0,Предпосылки!$B$150,IF(COUNT(D22:D26)>3,Предпосылки!$B$151,Предпосылки!$B$149))*Предпосылки!$E$123,0) -> 145 | E11: =ROUNDDOWN(E3*IF(COUNT(E22:E26)>0,Предпосылки!$B$150,IF(COUNT(E22:E26)>3,Предпосылки!$B$151,Предпосылки!$B$149))*Предпосылки!$E$123,0) -> 70 | F11: =ROUNDDOWN(F3*IF(COUNT(F22:F26)>0,Предпосылки!$B$150,IF(COUNT(F22:F26)>3,Предпосылки!$B$151,Предпосылки!$B$149))*Предпосылки!$E$123,0) -> 70 | G11: =ROUNDDOWN(G3*IF(COUNT(G22:G26)>0,Предпосылки!$B$150,IF(COUNT(G22:G26)>3,Предпосылки!$B$151,Предпосылки!$B$149))*Предпосылки!$E$123,0) -> 130 | H11: =ROUNDDOWN(H3*IF(COUNT(H22:H26)>0,Предпосылки!$B$150,IF(COUNT(H22:H26)>3,Предпосылки!$B$151,Предпосылки!$B$149))*Предпосылки!$E$123,0) -> 63 | I11: =ROUNDDOWN(I3*IF(COUNT(I22:I26)>0,Предпосылки!$B$150,IF(COUNT(I22:I26)>3,Предпосылки!$B$151,Предпосылки!$B$149))*Предпосылки!$E$123,0) -> 63 | ... N11: =ROUNDDOWN(N3*IF(COUNT(N22:N26)>0,Предпосылки!$B$150,IF(COUNT(N22:N26)>3,Предпосылки!$B$151,Предпосылки!$B$149))*Предпосылки!$E$123,0) -> 80 | O11: =ROUNDDOWN(O3*IF(COUNT(O22:O26)<3,Предпосылки!$B$150,IF(COUNT(O22:O26)>3,Предпосылки!$B$151,Предпосылки!$B$149))*Предпосылки!$E$123,0) -> 166 | P11: =ROUNDDOWN(P3*IF(COUNT(P22:P26)<3,Предпосылки!$B$150,IF(COUNT(P22:P26)>3,Предпосылки!$B$151,Предпосылки!$B$149))*Предпосылки!$E$123,0) -> 70 | Q11: =ROUNDDOWN(Q3*IF(COUNT(Q22:Q26)<3,Предпосылки!$B$150,IF(COUNT(Q22:Q26)>3,Предпосылки!$B$151,Предпосылки!$B$149))*Предпосылки!$E$123,0) -> 145 | R11: =ROUNDDOWN(R3*IF(COUNT(R22:R26)<3,Предпосылки!$B$150,IF(COUNT(R22:R26)>3,Предпосылки!$B$151,Предпосылки!$B$149))*Предпосылки!$E$123,0) -> 145 | S11: =ROUNDDOWN(S3*IF(COUNT(S22:S26)<3,Предпосылки!$B$150,IF(COUNT(S22:S26)>3,Предпосылки!$B$151,Предпосылки!$B$149))*Предпосылки!$E$123,0) -> 70 | T11: =ROUNDDOWN(T3*IF(COUNT(T22:T26)<3,Предпосылки!$B$150,IF(COUNT(T22:T26)>3,Предпосылки!$B$151,Предпосылки!$B$149))*Предпосылки!$E$123,0) -> 145 | U11: =ROUNDDOWN(U3*IF(COUNT(U22:U26)<3,Предпосылки!$B$150,IF(COUNT(U22:U26)>3,Предпосылки!$B$151,Предпосылки!$B$149))*Предпосылки!$E$123,0) -> 145 | V11: =ROUNDDOWN(V3*IF(COUNT(V22:V26)<3,Предпосылки!$B$150,IF(COUNT(V22:V26)>3,Предпосылки!$B$151,Предпосылки!$B$149))*Предпосылки!$E$123*(1+Предпосылки!$B$152),0) -> 239 | W11: =ROUNDDOWN(W3*IF(COUNT(W22:W26)<3,Предпосылки!$B$150,IF(COUNT(W22:W26)>3,Предпосылки!$B$151,Предпосылки!$B$149))*Предпосылки!$E$123*(1+Предпосылки!$B$152),0) -> 169 | X11: =ROUNDDOWN(X3*IF(COUNT(X22:X26)<3,Предпосылки!$B$150,IF(COUNT(X22:X26)>3,Предпосылки!$B$151,Предпосылки!$B$149))*Предпосылки!$E$123*(1+Предпосылки!$B$152),0) -> 81 | Y11: =ROUNDDOWN(Y3*IF(COUNT(Y22:Y26)<3,Предпосылки!$B$150,IF(COUNT(Y22:Y26)>3,Предпосылки!$B$151,Предпосылки!$B$149))*Предпосылки!$E$123*(1+Предпосылки!$B$152),0) -> 176 | Z11: =ROUNDDOWN(Z3*IF(COUNT(Z22:Z26)<3,Предпосылки!$B$150,IF(COUNT(Z22:Z26)>3,Предпосылки!$B$151,Предпосылки!$B$149))*Предпосылки!$E$123*(1+Предпосылки!$B$152),0) -> 176 | AA11: =ROUNDDOWN(AA3*IF(COUNT(AA22:AA26)<3,Предпосылки!$B$150,IF(COUNT(AA22:AA26)>3,Предпосылки!$B$151,Предпосылки!$B$149))*Предпосылки!$E$123*(1+Предпосылки!$B$152)^2,0) -> 90 | AB11: =ROUNDDOWN(AB3*IF(COUNT(AB22:AB26)<3,Предпосылки!$B$150,IF(COUNT(AB22:AB26)>3,Предпосылки!$B$151,Предпосылки!$B$149))*Предпосылки!$E$123*(1+Предпосылки!$B$152)^2,0) -> 162 | AC11: =ROUNDDOWN(AC3*IF(COUNT(AC22:AC26)<3,Предпосылки!$B$150,IF(COUNT(AC22:AC26)>3,Предпосылки!$B$151,Предпосылки!$B$149))*Предпосылки!$E$123*(1+Предпосылки!$B$152)^2,0) -> 162 | AD11: =ROUNDDOWN(AD3*IF(COUNT(AD22:AD26)<3,Предпосылки!$B$150,IF(COUNT(AD22:AD26)>3,Предпосылки!$B$151,Предпосылки!$B$149))*Предпосылки!$E$123*(1+Предпосылки!$B$152)^2,0) -> 230 | AE11: =ROUNDDOWN(AE3*IF(COUNT(AE22:AE26)<3,Предпосылки!$B$150,IF(COUNT(AE22:AE26)>3,Предпосылки!$B$151,Предпосылки!$B$149))*Предпосылки!$E$123*(1+Предпосылки!$B$152)^2,0) -> 230 | AF11: =ROUNDDOWN(AF3*IF(COUNT(AF22:AF26)<3,Предпосылки!$B$150,IF(COUNT(AF22:AF26)>3,Предпосылки!$B$151,Предпосылки!$B$149))*Предпосылки!$E$123*(1+Предпосылки!$B$152)^2,0) -> 162 | AG11: =ROUNDDOWN(AG3*IF(COUNT(AG22:AG26)<3,Предпосылки!$B$150,IF(COUNT(AG22:AG26)>3,Предпосылки!$B$151,Предпосылки!$B$149))*Предпосылки!$E$123*(1+Предпосылки!$B$152)^2,0) -> 78 | AH11: =ROUNDDOWN(AH3*IF(COUNT(AH22:AH26)<3,Предпосылки!$B$150,IF(COUNT(AH22:AH26)>3,Предпосылки!$B$151,Предпосылки!$B$149))*Предпосылки!$E$123*(1+Предпосылки!$B$152)^2,0) -> 179 | ... AL11: =ROUNDDOWN(AL3*IF(COUNT(AL22:AL26)<3,Предпосылки!$B$150,IF(COUNT(AL22:AL26)>3,Предпосылки!$B$151,Предпосылки!$B$149))*Предпосылки!$E$123*(1+Предпосылки!$B$152)^2,0) -> 0
A12: Количество купленных классических ЦФА | B12: =ROUNDDOWN(B3*IF(COUNT(B22:B26)>0,Предпосылки!$B$150,(IF(COUNT(B22:B26)>3,Предпосылки!$B$151,Предпосылки!$B$149))+3%)*Предпосылки!$E$124,0) -> 115 | C12: =ROUNDDOWN(C3*IF(COUNT(C22:C26)>0,Предпосылки!$B$150,(IF(COUNT(C22:C26)>3,Предпосылки!$B$151,Предпосылки!$B$149))+3%)*Предпосылки!$E$124,0) -> 115 | D12: =ROUNDDOWN(D3*IF(COUNT(D22:D26)>0,Предпосылки!$B$150,(IF(COUNT(D22:D26)>3,Предпосылки!$B$151,Предпосылки!$B$149))+3%)*Предпосылки!$E$124,0) -> 145 | E12: =ROUNDDOWN(E3*IF(COUNT(E22:E26)>0,Предпосылки!$B$150,(IF(COUNT(E22:E26)>3,Предпосылки!$B$151,Предпосылки!$B$149))+3%)*Предпосылки!$E$124,0) -> 100 | F12: =ROUNDDOWN(F3*IF(COUNT(F22:F26)>0,Предпосылки!$B$150,(IF(COUNT(F22:F26)>3,Предпосылки!$B$151,Предпосылки!$B$149))+3%)*Предпосылки!$E$124,0) -> 100 | G12: =ROUNDDOWN(G3*IF(COUNT(G22:G26)>0,Предпосылки!$B$150,(IF(COUNT(G22:G26)>3,Предпосылки!$B$151,Предпосылки!$B$149))+3%)*Предпосылки!$E$124,0) -> 130 | H12: =ROUNDDOWN(H3*IF(COUNT(H22:H26)>0,Предпосылки!$B$150,(IF(COUNT(H22:H26)>3,Предпосылки!$B$151,Предпосылки!$B$149))+3%)*Предпосылки!$E$124,0) -> 90 | I12: =ROUNDDOWN(I3*IF(COUNT(I22:I26)>0,Предпосылки!$B$150,(IF(COUNT(I22:I26)>3,Предпосылки!$B$151,Предпосылки!$B$149))+3%)*Предпосылки!$E$124,0) -> 90 | ... N12: =ROUNDDOWN(N3*IF(COUNT(N22:N26)>0,Предпосылки!$B$150,(IF(COUNT(N22:N26)>3,Предпосылки!$B$151,Предпосылки!$B$149))+3%)*Предпосылки!$E$124,0) -> 115 | O12: =ROUNDDOWN(O3*IF(COUNT(O22:O26)<3,Предпосылки!$B$150,(IF(COUNT(O22:O26)>3,Предпосылки!$B$151,Предпосылки!$B$149))+2%)*Предпосылки!$E$124,0) -> 166 | P12: =ROUNDDOWN(P3*IF(COUNT(P22:P26)<3,Предпосылки!$B$150,(IF(COUNT(P22:P26)>3,Предпосылки!$B$151,Предпосылки!$B$149))+2%)*Предпосылки!$E$124,0) -> 90 | Q12: =ROUNDDOWN(Q3*IF(COUNT(Q22:Q26)<3,Предпосылки!$B$150,(IF(COUNT(Q22:Q26)>3,Предпосылки!$B$151,Предпосылки!$B$149))+2%)*Предпосылки!$E$124,0) -> 145 | R12: =ROUNDDOWN(R3*IF(COUNT(R22:R26)<3,Предпосылки!$B$150,(IF(COUNT(R22:R26)>3,Предпосылки!$B$151,Предпосылки!$B$149))+2%)*Предпосылки!$E$124,0) -> 145 | S12: =ROUNDDOWN(S3*IF(COUNT(S22:S26)<3,Предпосылки!$B$150,(IF(COUNT(S22:S26)>3,Предпосылки!$B$151,Предпосылки!$B$149))+2%)*Предпосылки!$E$124,0) -> 90 | T12: =ROUNDDOWN(T3*IF(COUNT(T22:T26)<3,Предпосылки!$B$150,(IF(COUNT(T22:T26)>3,Предпосылки!$B$151,Предпосылки!$B$149))+2%)*Предпосылки!$E$124,0) -> 145 | U12: =ROUNDDOWN(U3*IF(COUNT(U22:U26)<3,Предпосылки!$B$150,(IF(COUNT(U22:U26)>3,Предпосылки!$B$151,Предпосылки!$B$149))+2%)*Предпосылки!$E$124,0) -> 145 | V12: =ROUNDDOWN(V3*IF(COUNT(V22:V26)<3,Предпосылки!$B$150,(IF(COUNT(V22:V26)>3,Предпосылки!$B$151,Предпосылки!$B$149))+3%)*Предпосылки!$E$124*(1+Предпосылки!$B$152),0) -> 274 | W12: =ROUNDDOWN(W3*IF(COUNT(W22:W26)<3,Предпосылки!$B$150,(IF(COUNT(W22:W26)>3,Предпосылки!$B$151,Предпосылки!$B$149))+3%)*Предпосылки!$E$124*(1+Предпосылки!$B$152),0) -> 169 | X12: =ROUNDDOWN(X3*IF(COUNT(X22:X26)<3,Предпосылки!$B$150,(IF(COUNT(X22:X26)>3,Предпосылки!$B$151,Предпосылки!$B$149))+3%)*Предпосылки!$E$124*(1+Предпосылки!$B$152),0) -> 116 | Y12: =ROUNDDOWN(Y3*IF(COUNT(Y22:Y26)<3,Предпосылки!$B$150,(IF(COUNT(Y22:Y26)>3,Предпосылки!$B$151,Предпосылки!$B$149))+3%)*Предпосылки!$E$124*(1+Предпосылки!$B$152),0) -> 176 | Z12: =ROUNDDOWN(Z3*IF(COUNT(Z22:Z26)<3,Предпосылки!$B$150,(IF(COUNT(Z22:Z26)>3,Предпосылки!$B$151,Предпосылки!$B$149))+3%)*Предпосылки!$E$124*(1+Предпосылки!$B$152),0) -> 176 | AA12: =ROUNDDOWN(AA3*IF(COUNT(AA22:AA26)<3,Предпосылки!$B$150,(IF(COUNT(AA22:AA26)>3,Предпосылки!$B$151,Предпосылки!$B$149))+3%)*Предпосылки!$E$124*(1+Предпосылки!$B$152)^2,0) -> 129 | AB12: =ROUNDDOWN(AB3*IF(COUNT(AB22:AB26)<3,Предпосылки!$B$150,(IF(COUNT(AB22:AB26)>3,Предпосылки!$B$151,Предпосылки!$B$149))+3%)*Предпосылки!$E$124*(1+Предпосылки!$B$152)^2,0) -> 162 | AC12: =ROUNDDOWN(AC3*IF(COUNT(AC22:AC26)<3,Предпосылки!$B$150,(IF(COUNT(AC22:AC26)>3,Предпосылки!$B$151,Предпосылки!$B$149))+3%)*Предпосылки!$E$124*(1+Предпосылки!$B$152)^2,0) -> 162 | AD12: =ROUNDDOWN(AD3*IF(COUNT(AD22:AD26)<3,Предпосылки!$B$150,(IF(COUNT(AD22:AD26)>3,Предпосылки!$B$151,Предпосылки!$B$149))+3%)*Предпосылки!$E$124*(1+Предпосылки!$B$152)^2,0) -> 264 | AE12: =ROUNDDOWN(AE3*IF(COUNT(AE22:AE26)<3,Предпосылки!$B$150,(IF(COUNT(AE22:AE26)>3,Предпосылки!$B$151,Предпосылки!$B$149))+3%)*Предпосылки!$E$124*(1+Предпосылки!$B$152)^2,0) -> 264 | AF12: =ROUNDDOWN(AF3*IF(COUNT(AF22:AF26)<3,Предпосылки!$B$150,(IF(COUNT(AF22:AF26)>3,Предпосылки!$B$151,Предпосылки!$B$149))+3%)*Предпосылки!$E$124*(1+Предпосылки!$B$152)^2,0) -> 162 | AG12: =ROUNDDOWN(AG3*IF(COUNT(AG22:AG26)<3,Предпосылки!$B$150,(IF(COUNT(AG22:AG26)>3,Предпосылки!$B$151,Предпосылки!$B$149))+3%)*Предпосылки!$E$124*(1+Предпосылки!$B$152)^2,0) -> 112 | AH12: =ROUNDDOWN(AH3*IF(COUNT(AH22:AH26)<3,Предпосылки!$B$150,(IF(COUNT(AH22:AH26)>3,Предпосылки!$B$151,Предпосылки!$B$149))+3%)*Предпосылки!$E$124*(1+Предпосылки!$B$152)^2,0) -> 179 | ... AL12: =ROUNDDOWN(AL3*IF(COUNT(AL22:AL26)<3,Предпосылки!$B$150,(IF(COUNT(AL22:AL26)>3,Предпосылки!$B$151,Предпосылки!$B$149))+3%)*Предпосылки!$E$124*(1+Предпосылки!$B$152)^2,0) -> 0
A13: Сумма приобретенных ЦФА | B13: =B$9*Предпосылки!$D$122 -> 275000 | C13: =C$9*Предпосылки!$D$122 -> 275000 | D13: =D$9*Предпосылки!$D$122 -> 435000 | E13: =E$9*Предпосылки!$D$122 -> 240000 | F13: =F$9*Предпосылки!$D$122 -> 240000 | G13: =G$9*Предпосылки!$D$122 -> 390000 | H13: =H$9*Предпосылки!$D$122 -> 216000 | I13: =I$9*Предпосылки!$D$122 -> 216000 | ... N13: =N$9*Предпосылки!$D$122 -> 275000 | O13: =O$9*1000 -> 498000 | P13: =P$9*1000 -> 230000 | Q13: =Q$9*1000 -> 435000 | R13: =R$9*1000 -> 435000 | S13: =S$9*1000 -> 230000 | T13: =T$9*1000 -> 435000 | U13: =U$9*1000 -> 435000 | V13: =V9*Предпосылки!$D$122 -> 752000 | W13: =W9*Предпосылки!$D$122 -> 507000 | X13: =X9*Предпосылки!$D$122 -> 278000 | Y13: =Y9*Предпосылки!$D$122 -> 528000 | Z13: =Z9*Предпосылки!$D$122 -> 528000 | AA13: =AA9*Предпосылки!$D$122 -> 309000 | AB13: =AB9*Предпосылки!$D$122 -> 486000 | AC13: =AC9*Предпосылки!$D$122 -> 486000 | ... AL13: =AL9*Предпосылки!$D$122 -> 0
A14: Сумма к выплате по ЦФА на скины | N14: =N6*(1+Предпосылки!$N$122)*Предпосылки!$B$153 -> 427179.84 | Z14: =Z6*(1+Предпосылки!$N$122) -> 1012022.8 | AL14: =AL6*(1+Предпосылки!$N$122) -> 1420288.1
A15: Сумма к выплате по Fan-токенам | N15: =N7*(1+Предпосылки!$N$123) -> 875700.28 | Z15: =Z7*(1+Предпосылки!$N$123) -> 1020580.9 | AL15: =AL7*(1+Предпосылки!$N$123) -> 2151732.5
A16: Сумма к выплате по классическим ЦФА | N16: =N8*(1+Предпосылки!$N$124) -> 1058958.9 | Z16: =Z8*(1+Предпосылки!$N$124) -> 1108604.2 | AL16: =AL8*(1+Предпосылки!$N$124) -> 2370962.8
A17: Интеграция Alfa ID в платформу покупки внутриигровых продуктов | B17: =Расходы!$C$15 -> -500000
A18: Выплата ЦФА | N18: =-(SUM(N14:N16)) -> -2361839 | Z18: =-SUM(Z14:Z16) -> -3141208 | AH18: =-(SUM(AH14:AH16)) -> 0 | AL18: =-SUM(AL14:AL16) -> -5942983.5
A19: Аналитика | B19: =Расходы!C4 -> 0 | C19: =B19 -> 0 | D19: =C19 -> 0 | E19: =D19 -> 0 | F19: =E19 -> 0 | G19: =F19 -> 0 | H19: =G19 -> 0 | I19: =H19 -> 0 | J19: =I19 -> 0 | ... U19: =T19 -> 0 | V19: 0 | W19: =V19 -> 0 | X19: =W19 -> 0 | Y19: =X19 -> 0 | Z19: =Y19 -> 0 | AA19: =Z19 -> 0 | AB19: =AA19 -> 0 | AC19: =AB19 -> 0 | AD19: =AC19 -> 0 | ... AK19: =AJ19 -> 0 | AL19: 0
A20: Интернет-маркетинг | B20: =Расходы!C5 -> 0 | C20: =B20 -> 0 | D20: =C20 -> 0 | E20: =D20 -> 0 | F20: =E20 -> 0 | G20: =F20 -> 0 | H20: =G20 -> 0 | I20: =H20 -> 0 | J20: =I20 -> 0 | ... U20: =T20 -> 0 | V20: 0 | W20: =V20 -> 0 | X20: =W20 -> 0 | Y20: =X20 -> 0 | Z20: =Y20 -> 0 | AA20: =Z20 -> 0 | AB20: =AA20 -> 0 | AC20: =AB20 -> 0 | AD20: =AC20 -> 0 | ... AK20: =AJ20 -> 0 | AL20: 0
A21: Юридическая и экономическая подготовка | B21: =Расходы!C6 -> 0 | C21: =B21 -> 0 | D21: =C21 -> 0 | E21: =D21 -> 0 | F21: =E21 -> 0 | G21: =F21 -> 0 | H21: =G21 -> 0 | I21: =H21 -> 0 | J21: =I21 -> 0 | ... U21: =T21 -> 0 | V21: 0 | W21: =V21 -> 0 | X21: =W21 -> 0 | Y21: =X21 -> 0 | Z21: =Y21 -> 0 | AA21: =Z21 -> 0 | AB21: =AA21 -> 0 | AC21: =AB21 -> 0 | AD21: =AC21 -> 0 | ... AK21: =AJ21 -> 0 | AL21: 0
A22: Контент и образование 1 | D22: =Расходы!C8 -> 0 | G22: =D22 -> 0 | J22: =G22 -> 0 | M22: =J22 -> 0 | P22: =M22 -> 0 | S22: =P22 -> 0 | V22: 0 | X22: =Расходы!C42 -> 0 | Y22: 0 | AA22: =X22 -> 0 | AB22: 0 | AD22: =AA22 -> 0 | AE22: 0 | AG22: =AD22 -> 0 | AJ22: =AG22 -> 0
A23: Контент и образование 2 | D23: =Расходы!C9 -> 0 | G23: =D23 -> 0 | J23: =G23 -> 0 | M23: =J23 -> 0 | P23: =M23 -> 0 | S23: =P23 -> 0 | V23: 0 | X23: =Расходы!C43 -> 0 | Y23: 0 | AA23: =X23 -> 0 | AB23: 0 | AD23: =AA23 -> 0 | AE23: 0 | AG23: =AD23 -> 0 | AJ23: =AG23 -> 0
A24: PR и репутационные активности 1 | D24: =Расходы!C10 -> 0 | G24: =D24 -> 0 | J24: =G24 -> 0 | M24: =J24 -> 0 | P24: =M24 -> 0 | S24: =P24 -> 0 | V24: 0 | X24: =Расходы!C44 -> 0 | AA24: =X24 -> 0 | AD24: =AA24 -> 0 | AE24: 0 | AG24: =AD24 -> 0 | AJ24: =AG24 -> 0
A25: Контент и образование 3 | J25: =Расходы!C12 -> -50000 | V25: =Расходы!C12 -> -50000 | AD25: =Расходы!C46 -> 0 | AE25: =V25 -> -50000
A26: PR и репутационные активности 2 | J26: =Расходы!C13 -> -200000 | V26: =Расходы!C13 -> -200000 | AD26: =Расходы!C47 -> 0 | AE26: =V26 -> -200000
A27: Комиссия Оператора | B27: =-B$13*Расходы!$C$17 -> -5500 | C27: =-C$13*Расходы!$C$17 -> -5500 | D27: =-D$13*Расходы!$C$17 -> -8700 | E27: =-E$13*Расходы!$C$17 -> -4800 | F27: =-F$13*Расходы!$C$17 -> -4800 | G27: =-G$13*Расходы!$C$17 -> -7800 | H27: =-H$13*Расходы!$C$17 -> -4320 | I27: =-I$13*Расходы!$C$17 -> -4320 | ... U27: =-U$13*Расходы!$C$17 -> -8700 | V27: =-V13*Расходы!$C$17 -> -15040 | W27: =-W13*Расходы!$C$17 -> -10140 | X27: =-X13*Расходы!$C$17 -> -5560 | Y27: =-Y13*Расходы!$C$17 -> -10560 | Z27: =-Z13*Расходы!$C$17 -> -10560 | AA27: =-AA13*Расходы!$C$17 -> -6180 | AB27: =-AB13*Расходы!$C$17 -> -9720 | AC27: =-AC13*Расходы!$C$17 -> -9720 | ... AL27: =-AL13*Расходы!$C$17 -> 0
A28: Экстраординарные затраты | B28: =-Расходы!$C$21*B$13 -> -13750 | C28: =-Расходы!$C$21*C$13 -> -13750 | D28: =-Расходы!$C$21*D$13 -> -21750 | E28: =-Расходы!$C$21*E$13 -> -12000 | F28: =-Расходы!$C$21*F$13 -> -12000 | G28: =-Расходы!$C$21*G$13 -> -19500 | H28: =-Расходы!$C$21*H$13 -> -10800 | I28: =-Расходы!$C$21*I$13 -> -10800 | ... U28: =-Расходы!$C$21*U$13 -> -21750 | V28: =-Расходы!$C$21*V13 -> -37600 | W28: =-Расходы!$C$21*W13 -> -25350 | X28: =-Расходы!$C$21*X13 -> -13900 | Y28: =-Расходы!$C$21*Y13 -> -26400 | Z28: =-Расходы!$C$21*Z13 -> -26400 | AA28: =-Расходы!$C$21*AA13 -> -15450 | AB28: =-Расходы!$C$21*AB13 -> -24300 | AC28: =-Расходы!$C$21*AC13 -> -24300 | ... AL28: =-Расходы!$C$21*AL13 -> 0
A29: Сумма издержек | B29: =SUM(B17:B28) -> -519250 | C29: =SUM(C17:C28) -> -19250 | D29: =SUM(D17:D28) -> -30450 | E29: =SUM(E17:E28) -> -16800 | F29: =SUM(F17:F28) -> -16800 | G29: =SUM(G17:G28) -> -27300 | H29: =SUM(H17:H28) -> -15120 | I29: =SUM(I17:I28) -> -15120 | ... N29: =SUM(N17:N28) -> -2381089 | O29: =SUM(O19:O28) -> -34860 | P29: =SUM(P19:P28) -> -16100 | Q29: =SUM(Q19:Q28) -> -30450 | R29: =SUM(R19:R28) -> -30450 | S29: =SUM(S19:S28) -> -16100 | T29: =SUM(T19:T28) -> -30450 | U29: =SUM(U19:U28) -> -30450 | V29: =SUM(V17:V28) -> -302640 | W29: =SUM(W17:W28) -> -35490 | X29: =SUM(X17:X28) -> -19460 | Y29: =SUM(Y17:Y28) -> -36960 | Z29: =SUM(Z17:Z28) -> -3178168 | AA29: =SUM(AA17:AA28) -> -21630 | AB29: =SUM(AB17:AB28) -> -34020 | AC29: =SUM(AC17:AC28) -> -34020 | ... AL29: =SUM(AL17:AL28) -> -5942983.5
A30: Прибыль до налогооблажения | B30: =B13+B29 -> -244250 | C30: =C13+C29 -> 255750 | D30: =D13+D29 -> 404550 | E30: =E13+E29 -> 223200 | F30: =F13+F29 -> 223200 | G30: =G13+G29 -> 362700 | H30: =H13+H29 -> 200880 | I30: =I13+I29 -> 200880 | ... M30: =M13+M29 -> 463140 | N30: =N17+N13+N29 -> -2106089 | O30: =O17+O13+O29 -> 463140 | P30: =P17+P13+P29 -> 213900 | Q30: =Q17+Q13+Q29 -> 404550 | R30: =R17+R13+R29 -> 404550 | S30: =S17+S13+S29 -> 213900 | T30: =T17+T13+T29 -> 404550 | U30: =U17+U13+U29 -> 404550 | V30: =V13+V29 -> 449360 | W30: =W13+W29 -> 471510 | X30: =X13+X29 -> 258540 | Y30: =Y13+Y29 -> 491040 | Z30: =Z13+Z29 -> -2650168 | AA30: =AA13+AA29 -> 287370 | AB30: =AB13+AB29 -> 451980 | AC30: =AC13+AC29 -> 451980 | ... AL30: =AL13+AL29 -> -5942983.5
A31: Налог на прибыль | B31: =IF(B$30>0,B$30*Расходы!$C$22,0) -> 0 | C31: =IF(C$30>0,C$30*Расходы!$C$22,0) -> 12787.5 | D31: =IF(D$30>0,D$30*Расходы!$C$22,0) -> 20227.5 | E31: =IF(E$30>0,E$30*Расходы!$C$22,0) -> 11160 | F31: =IF(F$30>0,F$30*Расходы!$C$22,0) -> 11160 | G31: =IF(G$30>0,G$30*Расходы!$C$22,0) -> 18135 | H31: =IF(H$30>0,H$30*Расходы!$C$22,0) -> 10044 | I31: =IF(I$30>0,I$30*Расходы!$C$22,0) -> 10044 | ... U31: =IF(U$30>0,U$30*Расходы!$C$22,0) -> 20227.5 | V31: =IF(V30>0,V30*Расходы!$C$22,0) -> 22468 | W31: =IF(W30>0,W30*Расходы!$C$22,0) -> 23575.5 | X31: =IF(X30>0,X30*Расходы!$C$22,0) -> 12927 | Y31: =IF(Y30>0,Y30*Расходы!$C$22,0) -> 24552 | Z31: =IF(Z30>0,Z30*Расходы!$C$22,0) -> 0 | AA31: =IF(AA30>0,AA30*Расходы!$C$22,0) -> 14368.5 | AB31: =IF(AB30>0,AB30*Расходы!$C$22,0) -> 22599 | AC31: =IF(AC30>0,AC30*Расходы!$C$22,0) -> 22599 | ... AL31: =IF(AL30>0,AL30*Расходы!$C$22,0) -> 0
A32: Чистая прибыль | B32: =B30-B31 -> -244250 | C32: =C30-C31 -> 242962.5 | D32: =D30-D31 -> 384322.5 | E32: =E30-E31 -> 212040 | F32: =F30-F31 -> 212040 | G32: =G30-G31 -> 344565 | H32: =H30-H31 -> 190836 | I32: =I30-I31 -> 190836 | ... AL32: =AL30-AL31 -> -5942983.5
A34: Прибыль за 3 года | B34: =SUM(B32:AL32) -> 440008.03
A36: Основные выводы | B36: Нейтральный сценарий показывает более сбалансированные и близкие к реалиям результаты. Рост спроса здесь является умеренным и достигается за счет комбинации органики и точечных маркетинговых усилий. Конверсия находится на среднем уровне между оптимистичным и пессимистичным прогнозами. Хотя классические ЦФА по-прежнему лидируют по объему выплат, наблюдается более равномерное распределение интереса между всеми типами активов. Для достижения целевых финансовых показателей в этом сценарии уже требуются системные вложения в PR, контент и образование. Прибыль проекта является устойчивой, но для ее максимизации необходим четкий контроль над издержками и эффективностью маркетинговых кампаний. Этот сценарий можно считать базовым для планирования, так как он учитывает вероятные барьеры на пути быстрого роста, но не предполагает кризисных явлений.

Sheet Cash-Flow 3
A1: Расчет Cash-Flow для Сценария 3 (пессимистичный)
A2: Период (мес.) | B2: 1 | C2: 2 | D2: 3 | E2: 4 | F2: 5 | G2: 6 | H2: 7 | I2: 8 | J2: 9 | K2: 10 | L2: 11 | M2: 12 | N2: 13 | O2: 14 | P2: 15 | Q2: 16 | R2: 17 | S2: 18 | T2: 19 | U2: 20 | V2: 21 | W2: 22 | X2: 23 | Y2: 24 | Z2: 25 | AA2: 26 | AB2: 27 | AC2: 28 | AD2: 29 | AE2: 30 | AF2: 31 | AG2: 32 | AH2: 33 | AI2: 34 | AJ2: 35 | AK2: 36 | AL2: 37
A3: Сезонность | B3: =IF(OR(B2=1,B2=2,B2=12,B2=13,B2=14,B2=24,B2=25,B2=26,B2=36),1+Предпосылки!$B$158,IF(OR(B2=9,B2=10,B2=11,B2=21,B2=22,B2=23,B2=33,B2=34,B2=35),1+Предпосылки!$B$157,IF(OR(B2=6,B2=7,B2=8),1+Предпосылки!$B$160,IF(OR(B2=3,B2=4,B2=5,B2=15,B2=16,B2=17,B2=27,B2=28,B2=29),Предпосылки!$B$159+1,1)))) -> 1.15 | C3: =IF(OR(C2=1,C2=2,C2=12,C2=13,C2=14,C2=24,C2=25,C2=26,C2=36),1+Предпосылки!$B$158,IF(OR(C2=9,C2=10,C2=11,C2=21,C2=22,C2=23,C2=33,C2=34,C2=35),1+Предпосылки!$B$157,IF(OR(C2=6,C2=7,C2=8),1+Предпосылки!$B$160,IF(OR(C2=3,C2=4,C2=5,C2=15,C2=16,C2=17,C2=27,C2=28,C2=29),Предпосылки!$B$159+1,1)))) -> 1.15 | D3: =IF(OR(D2=1,D2=2,D2=12,D2=13,D2=14,D2=24,D2=25,D2=26,D2=36),1+Предпосылки!$B$158,IF(OR(D2=9,D2=10,D2=11,D2=21,D2=22,D2=23,D2=33,D2=34,D2=35),1+Предпосылки!$B$157,IF(OR(D2=6,D2=7,D2=8),1+Предпосылки!$B$160,IF(OR(D2=3,D2=4,D2=5,D2=15,D2=16,D2=17,D2=27,D2=28,D2=29),Предпосылки!$B$159+1,1)))) -> 1 | E3: =IF(OR(E2=1,E2=2,E2=12,E2=13,E2=14,E2=24,E2=25,E2=26,E2=36),1+Предпосылки!$B$158,IF(OR(E2=9,E2=10,E2=11,E2=21,E2=22,E2=23,E2=33,E2=34,E2=35),1+Предпосылки!$B$157,IF(OR(E2=6,E2=7,E2=8),1+Предпосылки!$B$160,IF(OR(E2=3,E2=4,E2=5,E2=15,E2=16,E2=17,E2=27,E2=28,E2=29),Предпосылки!$B$159+1,1)))) -> 1 | F3: =IF(OR(F2=1,F2=2,F2=12,F2=13,F2=14,F2=24,F2=25,F2=26,F2=36),1+Предпосылки!$B$158,IF(OR(F2=9,F2=10,F2=11,F2=21,F2=22,F2=23,F2=33,F2=34,F2=35),1+Предпосылки!$B$157,IF(OR(F2=6,F2=7,F2=8),1+Предпосылки!$B$160,IF(OR(F2=3,F2=4,F2=5,F2=15,F2=16,F2=17,F2=27,F2=28,F2=29),Предпосылки!$B$159+1,1)))) -> 1 | G3: =IF(OR(G2=1,G2=2,G2=12,G2=13,G2=14,G2=24,G2=25,G2=26,G2=36),1+Предпосылки!$B$158,IF(OR(G2=9,G2=10,G2=11,G2=21,G2=22,G2=23,G2=33,G2=34,G2=35),1+Предпосылки!$B$157,IF(OR(G2=6,G2=7,G2=8),1+Предпосылки!$B$160,IF(OR(G2=3,G2=4,G2=5,G2=15,G2=16,G2=17,G2=27,G2=28,G2=29),Предпосылки!$B$159+1,1)))) -> 0.9 | H3: =IF(OR(H2=1,H2=2,H2=12,H2=13,H2=14,H2=24,H2=25,H2=26,H2=36),1+Предпосылки!$B$158,IF(OR(H2=9,H2=10,H2=11,H2=21,H2=22,H2=23,H2=33,H2=34,H2=35),1+Предпосылки!$B$157,IF(OR(H2=6,H2=7,H2=8),1+Предпосылки!$B$160,IF(OR(H2=3,H2=4,H2=5,H2=15,H2=16,H2=17,H2=27,H2=28,H2=29),Предпосылки!$B$159+1,1)))) -> 0.9 | I3: =IF(OR(I2=1,I2=2,I2=12,I2=13,I2=14,I2=24,I2=25,I2=26,I2=36),1+Предпосылки!$B$158,IF(OR(I2=9,I2=10,I2=11,I2=21,I2=22,I2=23,I2=33,I2=34,I2=35),1+Предпосылки!$B$157,IF(OR(I2=6,I2=7,I2=8),1+Предпосылки!$B$160,IF(OR(I2=3,I2=4,I2=5,I2=15,I2=16,I2=17,I2=27,I2=28,I2=29),Предпосылки!$B$159+1,1)))) -> 0.9 | ... AK3: =IF(OR(AK2=1,AK2=2,AK2=12,AK2=13,AK2=14,AK2=24,AK2=25,AK2=26,AK2=36),1+Предпосылки!$B$158,IF(OR(AK2=9,AK2=10,AK2=11,AK2=21,AK2=22,AK2=23,AK2=33,AK2=34,AK2=35),1+Предпосылки!$B$157,IF(OR(AK2=6,AK2=7,AK2=8),1+Предпосылки!$B$160,IF(OR(AK2=3,AK2=4,AK2=5,AK2=15,AK2=16,AK2=17,AK2=27,AK2=28,AK2=29),Предпосылки!$B$159+1,1)))) -> 1.15
A4: Лимит суммы выпуска ЦФА | B4: =Предпосылки!$H$125 -> 300000000 | C4: =B$4-B$14 -> 299725000 | D4: =C$4-C$14 -> 299450000 | E4: =D$4-D$14 -> 299015000 | F4: =E$4-E$14 -> 298775000 | G4: =F$4-F$14 -> 298535000 | H4: =G$4-G$14 -> 298145000 | I4: =H$4-H$14 -> 297929000 | J4: =I$4-I$14 -> 297713000 | ... U4: =T$4-T$14 -> 293544000 | V4: =U4-U14 -> 293085000 | W4: =V4-V14 -> 292333000 | X4: =W4-W14 -> 291826000 | Y4: =X4-X14 -> 291548000 | Z4: =Y4-Y14 -> 291020000 | AA4: =Z4-Z14 -> 290492000 | AB4: =AA4-AA14 -> 290183000 | AC4: =AB4-AB14 -> 289697000 | ... AL4: =AK4-AK14 -> 285079000
A5: Сумма к выплате | B5: 0 | C5: =SUM(C7:C9) -> 272367.12 | D5: =SUM(D7:D9) -> 536936.18 | E5: =SUM(E7:E9) -> 944286.31 | F5: =SUM(F7:F9) -> 1139579.5 | G5: =SUM(G7:G9) -> 1314790.8 | H5: =SUM(H7:H9) -> 1609173.9 | I5: =SUM(I7:I9) -> 1706310.7 | J5: =SUM(J7:J9) -> 1779915.7 | ... AK5: =SUM(AK7:AK9) -> 4598859
A6: Накопленная сумма к выплате | C6: =B$14+B6 -> 275000 | D6: =C$14+C6 -> 550000 | E6: =D$14+D6 -> 985000 | F6: =E$14+E6 -> 1225000 | G6: =F$14+F6 -> 1465000 | H6: =G$14+G6 -> 1855000 | I6: =H$14+H6 -> 2071000 | J6: =I$14+I6 -> 2287000 | ... U6: =T$14+T6 -> 6456000 | V6: =V14+U6 -> 7208000 | W6: =V14+V6 -> 7960000 | X6: =W14+W6 -> 8467000 | Y6: =X14+X6 -> 8745000 | Z6: =Y14+Y6 -> 9273000 | AA6: =Z14+Z6 -> 9801000 | AB6: =AA14+AA6 -> 10110000 | AC6: =AB14+AB6 -> 10596000 | AD6: =AC14+AC6 -> 11082000 | ... AK6: =AJ14+AJ6 -> 14653000
A7: Сумма к выплате по ЦФА на скины | B7: 0 | C7: =(B7+B11*Предпосылки!$D$122)/(1+Предпосылки!$D$172/12)^(C$2-1) -> 79234.071 | D7: =(C7+C11*Предпосылки!$D$122)/(1+Предпосылки!$D$172/12)^(D$2-1) -> 156199.62 | E7: =(D7+D11*Предпосылки!$D$122)/(1+Предпосылки!$D$172/12)^(E$2-1) -> 292631.02 | F7: =(E7+E11*Предпосылки!$D$122)/(1+Предпосылки!$D$172/12)^(F$2-1) -> 348941.7 | G7: =(F7+F11*Предпосылки!$D$122)/(1+Предпосылки!$D$172/12)^(G$2-1) -> 399267.08 | H7: =(G7+G11*Предпосылки!$D$122)/(1+Предпосылки!$D$172/12)^(H$2-1) -> 499581.98 | I7: =(H7+H11*Предпосылки!$D$122)/(1+Предпосылки!$D$172/12)^(I$2-1) -> 525944.22 | J7: =(I7+I11*Предпосылки!$D$122)/(1+Предпосылки!$D$172/12)^(J$2-1) -> 545318.23 | ... M7: =(L7+L11*Предпосылки!$D$122)/(1+Предпосылки!$D$172/12)^(M$2-1) -> 659932.87 | O7: =(N11*Предпосылки!$D$122)/(1+Предпосылки!$D$92/12)^(O$2-1) -> 80000 | P7: =(O11*Предпосылки!$D$122)/(1+Предпосылки!$D$92/12)^(P$2-1) -> 176000 | Q7: =(P11*Предпосылки!$D$122)/(1+Предпосылки!$D$92/12)^(Q$2-1) -> 74000 | R7: =(Q11*Предпосылки!$D$122)/(1+Предпосылки!$D$92/12)^(R$2-1) -> 153000 | S7: =(R11*Предпосылки!$D$122)/(1+Предпосылки!$D$92/12)^(S$2-1) -> 153000 | T7: =(S11*Предпосылки!$D$122)/(1+Предпосылки!$D$92/12)^(T$2-1) -> 74000 | U7: =(T11*Предпосылки!$D$122)/(1+Предпосылки!$D$92/12)^(U$2-1) -> 153000 | V7: =(U7+U11*Предпосылки!$D$122)/(1+Предпосылки!$D$173/12)^(U$2-1) -> 270132.26 | W7: =(V7+V11*Предпосылки!$D$122)/(1+Предпосылки!$D$173/12)^(C$2-1) -> 505802.4 | X7: =(W7+W11*Предпосылки!$D$122)/(1+Предпосылки!$D$173/12)^(D$2-1) -> 666004.47 | Y7: =(X7+X11*Предпосылки!$D$122)/(1+Предпосылки!$D$173/12)^(E$2-1) -> 732443.28 | Z7: =(Y7+Y11*Предпосылки!$D$122)/(1+Предпосылки!$D$173/12)^(F$2-1) -> 884909.53 | AA7: =(Z11*Предпосылки!$D$122)/(1+Предпосылки!$D$174/12)^(G$2-1) -> 170955.29 | AB7: =(AA7+AA11*Предпосылки!$D$122)/(1+Предпосылки!$D$174/12)^(H$2-1) -> 252005.47 | AC7: =(AB7+AB11*Предпосылки!$D$122)/(1+Предпосылки!$D$174/12)^(I$2-1) -> 397487.9 | AD7: =(AC7+AC11*Предпосылки!$D$122)/(1+Предпосылки!$D$174/12)^(J$2-1) -> 534050.72 | AE7: =(AD7+AD11*Предпосылки!$D$122)/(1+Предпосылки!$D$174/12)^(K$2-1) -> 725083.41 | AF7: =(AE7+AE11*Предпосылки!$D$122)/(1+Предпосылки!$D$174/12)^(L$2-1) -> 901116.75 | AG7: =(AF7+AF11*Предпосылки!$D$122)/(1+Предпосылки!$D$174/12)^(M$2-1) -> 997228.53 | AH7: =(AG7+AG11*Предпосылки!$D$122)/(1+Предпосылки!$D$174/12)^(N$2-1) -> 1002740.4 | AI7: =(AH7+AH11*Предпосылки!$D$122)/(1+Предпосылки!$D$174/12)^(O$2-1) -> 1095680 | ... AL7: =(AK7+AK11*Предпосылки!$D$122)/(1+Предпосылки!$D$174/12)^(R$2-1) -> 1223331.7
A8: Сумма к выплате по Fan-токенам | B8: 0 | C8: =(B8+B12*Предпосылки!$D$122)/(1+Предпосылки!$D$172/12)^(C$2-1) -> 79234.071 | D8: =(C8+C12*Предпосылки!$D$122)/(1+Предпосылки!$D$172/12)^(D$2-1) -> 156199.62 | E8: =(D8+D12*Предпосылки!$D$122)/(1+Предпосылки!$D$172/12)^(E$2-1) -> 292631.02 | F8: =(E8+E12*Предпосылки!$D$122)/(1+Предпосылки!$D$172/12)^(F$2-1) -> 348941.7 | G8: =(F8+F12*Предпосылки!$D$122)/(1+Предпосылки!$D$172/12)^(G$2-1) -> 399267.08 | H8: =(G8+G12*Предпосылки!$D$122)/(1+Предпосылки!$D$172/12)^(H$2-1) -> 499581.98 | I8: =(H8+H12*Предпосылки!$D$122)/(1+Предпосылки!$D$172/12)^(I$2-1) -> 525944.22 | J8: =(I8+I12*Предпосылки!$D$122)/(1+Предпосылки!$D$172/12)^(J$2-1) -> 545318.23 | ... N8: =(M8+M12*Предпосылки!$D$122)/(1+Предпосылки!$D$172/12)^(N$2-1) -> 735882.58 | O8: =(N12*Предпосылки!$D$122)/(1+Предпосылки!$D$173/12)^(O$2-1) -> 73458.732 | P8: =(O12*Предпосылки!$D$122)/(1+Предпосылки!$D$173/12)^(P$2-1) -> 160552.24 | Q8: =(P12*Предпосылки!$D$122)/(1+Предпосылки!$D$173/12)^(Q$2-1) -> 67063.419 | R8: =(Q12*Предпосылки!$D$122)/(1+Предпосылки!$D$173/12)^(R$2-1) -> 137751.29 | S8: =(R12*Предпосылки!$D$122)/(1+Предпосылки!$D$173/12)^(S$2-1) -> 136850.36 | T8: =(S12*Предпосылки!$D$122)/(1+Предпосылки!$D$173/12)^(T$2-1) -> 65756.166 | U8: =(T12*Предпосылки!$D$122)/(1+Предпосылки!$D$173/12)^(U$2-1) -> 135066.13 | V8: =(U8+U12*Предпосылки!$D$122)/(1+Предпосылки!$D$173/12)^(U$2-1) -> 254300.51 | W8: =(V8+V12*Предпосылки!$D$122)/(1+Предпосылки!$D$173/12)^(C$2-1) -> 490074.19 | X8: =(W8+W12*Предпосылки!$D$122)/(1+Предпосылки!$D$173/12)^(D$2-1) -> 650481.33 | Y8: =(X8+X12*Предпосылки!$D$122)/(1+Предпосылки!$D$173/12)^(E$2-1) -> 717222.72 | Z8: =(Y8+Y12*Предпосылки!$D$122)/(1+Предпосылки!$D$173/12)^(F$2-1) -> 870083.27 | AA8: =(Z12*Предпосылки!$D$122)/(1+Предпосылки!$D$174/12)^(G$2-1) -> 170955.29 | AB8: =AA8+(AA12*Предпосылки!$D$122)/(1+Предпосылки!$D$174/12)^(H$2-1) -> 257868.62 | AC8: =AB8+(AB12*Предпосылки!$D$122)/(1+Предпосылки!$D$174/12)^(I$2-1) -> 413405.3 | AD8: =AC8+(AC12*Предпосылки!$D$122)/(1+Предпосылки!$D$174/12)^(J$2-1) -> 568039.96 | AE8: =AD8+(AD12*Предпосылки!$D$122)/(1+Предпосылки!$D$174/12)^(K$2-1) -> 786309.74 | AF8: =AE8+(AE12*Предпосылки!$D$122)/(1+Предпосылки!$D$174/12)^(L$2-1) -> 1003313.7 | AG8: =AF8+(AF12*Предпосылки!$D$122)/(1+Предпосылки!$D$174/12)^(M$2-1) -> 1155273.5 | AH8: =AG8+(AG12*Предпосылки!$D$122)/(1+Предпосылки!$D$174/12)^(N$2-1) -> 1228015 | AI8: =AH8+(AH12*Предпосылки!$D$122)/(1+Предпосылки!$D$174/12)^(O$2-1) -> 1393979.3 | ... AL8: =AK8+(AK12*Предпосылки!$D$122)/(1+Предпосылки!$D$174/12)^(R$2-1) -> 1808178.6
A9: Сумма к выплате по классическим ЦФА | B9: 0 | C9: =(B9+B13*Предпосылки!$D$122)/(1+Предпосылки!$D$172/12)^(C$2-1) -> 113898.98 | D9: =(C9+C13*Предпосылки!$D$122)/(1+Предпосылки!$D$172/12)^(D$2-1) -> 224536.95 | E9: =(D9+D13*Предпосылки!$D$122)/(1+Предпосылки!$D$172/12)^(E$2-1) -> 359024.27 | F9: =(E9+E13*Предпосылки!$D$122)/(1+Предпосылки!$D$172/12)^(F$2-1) -> 441696.11 | G9: =(F9+F13*Предпосылки!$D$122)/(1+Предпосылки!$D$172/12)^(G$2-1) -> 516256.61 | H9: =(G9+G13*Предпосылки!$D$122)/(1+Предпосылки!$D$172/12)^(H$2-1) -> 610009.9 | I9: =(H9+H13*Предпосылки!$D$122)/(1+Предпосылки!$D$172/12)^(I$2-1) -> 654422.25 | J9: =(I9+I13*Предпосылки!$D$122)/(1+Предпосылки!$D$172/12)^(J$2-1) -> 689279.23 | ... N9: =(M9+M13*Предпосылки!$D$122)/(1+Предпосылки!$D$172/12)^(N$2-1) -> 882465.77 | O9: =(N13*Предпосылки!$D$122)/(1+Предпосылки!$D$173/12)^(O$2-1) -> 105596.93 | P9: =(O13*Предпосылки!$D$122)/(1+Предпосылки!$D$173/12)^(P$2-1) -> 160552.24 | Q9: =(P13*Предпосылки!$D$122)/(1+Предпосылки!$D$173/12)^(Q$2-1) -> 86094.93 | R9: =(Q13*Предпосылки!$D$122)/(1+Предпосылки!$D$173/12)^(R$2-1) -> 137751.29 | S9: =(R13*Предпосылки!$D$122)/(1+Предпосылки!$D$173/12)^(S$2-1) -> 136850.36 | T9: =(S13*Предпосылки!$D$122)/(1+Предпосылки!$D$173/12)^(T$2-1) -> 84416.7 | U9: =(T13*Предпосылки!$D$122)/(1+Предпосылки!$D$173/12)^(U$2-1) -> 135066.13 | V9: =(U9+U13*Предпосылки!$D$122)/(1+Предпосылки!$D$173/12)^(U$2-1) -> 254300.51 | W9: =(V9+V13*Предпосылки!$D$122)/(1+Предпосылки!$D$173/12)^(C$2-1) -> 524845.28 | X9: =(W9+W13*Предпосылки!$D$122)/(1+Предпосылки!$D$173/12)^(D$2-1) -> 684799.08 | Y9: =(X9+X13*Предпосылки!$D$122)/(1+Предпосылки!$D$173/12)^(E$2-1) -> 785189.28 | Z9: =(Y9+Y13*Предпосылки!$D$122)/(1+Предпосылки!$D$173/12)^(F$2-1) -> 936289.12 | AA9: =(Z13*Предпосылки!$D$122)/(1+Предпосылки!$D$174/12)^(G$2-1) -> 170955.29 | AB9: =AA9+(AA13*Предпосылки!$D$122)/(1+Предпосылки!$D$174/12)^(H$2-1) -> 295531.06 | AC9: =AB9+(AB13*Предпосылки!$D$122)/(1+Предпосылки!$D$174/12)^(I$2-1) -> 451067.75 | AD9: =AC9+(AC13*Предпосылки!$D$122)/(1+Предпосылки!$D$174/12)^(J$2-1) -> 605702.4 | AE9: =AD9+(AD13*Предпосылки!$D$122)/(1+Предпосылки!$D$174/12)^(K$2-1) -> 856238.15 | AF9: =AE9+(AE13*Предпосылки!$D$122)/(1+Предпосылки!$D$174/12)^(L$2-1) -> 1105320.9 | AG9: =AF9+(AF13*Предпосылки!$D$122)/(1+Предпосылки!$D$174/12)^(M$2-1) -> 1257280.7 | AH9: =AG9+(AG13*Предпосылки!$D$122)/(1+Предпосылки!$D$174/12)^(N$2-1) -> 1361730.1 | AI9: =AH9+(AH13*Предпосылки!$D$122)/(1+Предпосылки!$D$174/12)^(O$2-1) -> 1527694.4 | ... AL9: =AK9+(AK13*Предпосылки!$D$122)/(1+Предпосылки!$D$174/12)^(R$2-1) -> 1975802.4
A10: Количество купленных ЦФА | B10: =SUM(B11:B13) -> 275 | C10: =SUM(C11:C13) -> 275 | D10: =SUM(D11:D13) -> 435 | E10: =SUM(E11:E13) -> 240 | F10: =SUM(F11:F13) -> 240 | G10: =SUM(G11:G13) -> 390 | H10: =SUM(H11:H13) -> 216 | I10: =SUM(I11:I13) -> 216 | ... AK10: =SUM(AK11:AK13) -> 561
A11: Количество купленных ЦФА на скины | B11: =ROUNDDOWN(B3*IF(COUNT(B23:B27)>0,Предпосылки!$B$150,IF(COUNT(B23:B27)>3,Предпосылки!$B$151,Предпосылки!$B$149))*Предпосылки!$E$122,0) -> 80 | C11: =ROUNDDOWN(C3*IF(COUNT(C23:C27)>0,Предпосылки!$B$150,IF(COUNT(C23:C27)>3,Предпосылки!$B$151,Предпосылки!$B$149))*Предпосылки!$E$122,0) -> 80 | D11: =ROUNDDOWN(D3*IF(COUNT(D23:D27)>0,Предпосылки!$B$150,IF(COUNT(D23:D27)>3,Предпосылки!$B$151,Предпосылки!$B$149))*Предпосылки!$E$122,0) -> 145 | E11: =ROUNDDOWN(E3*IF(COUNT(E23:E27)>0,Предпосылки!$B$150,IF(COUNT(E23:E27)>3,Предпосылки!$B$151,Предпосылки!$B$149))*Предпосылки!$E$122,0) -> 70 | F11: =ROUNDDOWN(F3*IF(COUNT(F23:F27)>0,Предпосылки!$B$150,IF(COUNT(F23:F27)>3,Предпосылки!$B$151,Предпосылки!$B$149))*Предпосылки!$E$122,0) -> 70 | G11: =ROUNDDOWN(G3*IF(COUNT(G23:G27)>0,Предпосылки!$B$150,IF(COUNT(G23:G27)>3,Предпосылки!$B$151,Предпосылки!$B$149))*Предпосылки!$E$122,0) -> 130 | H11: =ROUNDDOWN(H3*IF(COUNT(H23:H27)>0,Предпосылки!$B$150,IF(COUNT(H23:H27)>3,Предпосылки!$B$151,Предпосылки!$B$149))*Предпосылки!$E$122,0) -> 63 | I11: =ROUNDDOWN(I3*IF(COUNT(I23:I27)>0,Предпосылки!$B$150,IF(COUNT(I23:I27)>3,Предпосылки!$B$151,Предпосылки!$B$149))*Предпосылки!$E$122,0) -> 63 | ... N11: =ROUNDDOWN(N3*IF(COUNT(N23:N27)>0,Предпосылки!$B$150,IF(COUNT(N23:N27)>3,Предпосылки!$B$151,Предпосылки!$B$149))*Предпосылки!$E$122,0) -> 80 | O11: =ROUNDDOWN(O3*IF(COUNT(O23:O27)<3,Предпосылки!$B$150,IF(COUNT(O23:O27)>3,Предпосылки!$B$151,Предпосылки!$B$149))*Предпосылки!$E$122*(1+Предпосылки!$B$152),0) -> 176 | P11: =ROUNDDOWN(P3*IF(COUNT(P23:P27)<3,Предпосылки!$B$150,IF(COUNT(P23:P27)>3,Предпосылки!$B$151,Предпосылки!$B$149))*Предпосылки!$E$122*(1+Предпосылки!$B$152),0) -> 74 | Q11: =ROUNDDOWN(Q3*IF(COUNT(Q23:Q27)<3,Предпосылки!$B$150,IF(COUNT(Q23:Q27)>3,Предпосылки!$B$151,Предпосылки!$B$149))*Предпосылки!$E$122*(1+Предпосылки!$B$152),0) -> 153 | R11: =ROUNDDOWN(R3*IF(COUNT(R23:R27)<3,Предпосылки!$B$150,IF(COUNT(R23:R27)>3,Предпосылки!$B$151,Предпосылки!$B$149))*Предпосылки!$E$122*(1+Предпосылки!$B$152),0) -> 153 | S11: =ROUNDDOWN(S3*IF(COUNT(S23:S27)<3,Предпосылки!$B$150,IF(COUNT(S23:S27)>3,Предпосылки!$B$151,Предпосылки!$B$149))*Предпосылки!$E$122*(1+Предпосылки!$B$152),0) -> 74 | T11: =ROUNDDOWN(T3*IF(COUNT(T23:T27)<3,Предпосылки!$B$150,IF(COUNT(T23:T27)>3,Предпосылки!$B$151,Предпосылки!$B$149))*Предпосылки!$E$122*(1+Предпосылки!$B$152),0) -> 153 | U11: =ROUNDDOWN(U3*IF(COUNT(U23:U27)<3,Предпосылки!$B$150,IF(COUNT(U23:U27)>3,Предпосылки!$B$151,Предпосылки!$B$149))*Предпосылки!$E$122*(1+Предпосылки!$B$152),0) -> 153 | V11: =ROUNDDOWN(V3*IF(COUNT(V23:V27)<3,Предпосылки!$B$150,IF(COUNT(V23:V27)>3,Предпосылки!$B$151,Предпосылки!$B$149))*Предпосылки!$E$122*(1+Предпосылки!$B$152),0) -> 239 | ... Z11: =ROUNDDOWN(Z3*IF(COUNT(Z23:Z27)<3,Предпосылки!$B$150,IF(COUNT(Z23:Z27)>3,Предпосылки!$B$151,Предпосылки!$B$149))*Предпосылки!$E$122*(1+Предпосылки!$B$152),0) -> 176 | AA11: =ROUNDDOWN(AA3*IF(COUNT(AA23:AA27)<3,Предпосылки!$B$150,IF(COUNT(AA23:AA27)>3,Предпосылки!$B$151,Предпосылки!$B$149))*Предпосылки!$E$122*(1+Предпосылки!$B$152)^2,0) -> 90 | AB11: =ROUNDDOWN(AB3*IF(COUNT(AB23:AB27)<3,Предпосылки!$B$150,IF(COUNT(AB23:AB27)>3,Предпосылки!$B$151,Предпосылки!$B$149))*Предпосылки!$E$122*(1+Предпосылки!$B$152)^2,0) -> 162 | AC11: =ROUNDDOWN(AC3*IF(COUNT(AC23:AC27)<3,Предпосылки!$B$150,IF(COUNT(AC23:AC27)>3,Предпосылки!$B$151,Предпосылки!$B$149))*Предпосылки!$E$122*(1+Предпосылки!$B$152)^2,0) -> 162 | AD11: =ROUNDDOWN(AD3*IF(COUNT(AD23:AD27)<3,Предпосылки!$B$150,IF(COUNT(AD23:AD27)>3,Предпосылки!$B$151,Предпосылки!$B$149))*Предпосылки!$E$122*(1+Предпосылки!$B$152)^2,0) -> 230 | AE11: =ROUNDDOWN(AE3*IF(COUNT(AE23:AE27)<3,Предпосылки!$B$150,IF(COUNT(AE23:AE27)>3,Предпосылки!$B$151,Предпосылки!$B$149))*Предпосылки!$E$122*(1+Предпосылки!$B$152)^2,0) -> 230 | AF11: =ROUNDDOWN(AF3*IF(COUNT(AF23:AF27)<3,Предпосылки!$B$150,IF(COUNT(AF23:AF27)>3,Предпосылки!$B$151,Предпосылки!$B$149))*Предпосылки!$E$122*(1+Предпосылки!$B$152)^2,0) -> 162 | AG11: =ROUNDDOWN(AG3*IF(COUNT(AG23:AG27)<3,Предпосылки!$B$150,IF(COUNT(AG23:AG27)>3,Предпосылки!$B$151,Предпосылки!$B$149))*Предпосылки!$E$122*(1+Предпосылки!$B$152)^2,0) -> 78 | AH11: =ROUNDDOWN(AH3*IF(COUNT(AH23:AH27)<3,Предпосылки!$B$150,IF(COUNT(AH23:AH27)>3,Предпосылки!$B$151,Предпосылки!$B$149))*Предпосылки!$E$122*(1+Предпосылки!$B$152)^2,0) -> 179 | ... AK11: =ROUNDDOWN(AK3*IF(COUNT(AK23:AK27)<3,Предпосылки!$B$150,IF(COUNT(AK23:AK27)>3,Предпосылки!$B$151,Предпосылки!$B$149))*Предпосылки!$E$122*(1+Предпосылки!$B$152)^2,0) -> 187
A12: Количество купленных Fan-токенов | B12: =ROUNDDOWN(B3*IF(COUNT(B23:B27)>0,Предпосылки!$B$150,IF(COUNT(B23:B27)>3,Предпосылки!$B$151,Предпосылки!$B$149))*Предпосылки!$E$123,0) -> 80 | C12: =ROUNDDOWN(C3*IF(COUNT(C23:C27)>0,Предпосылки!$B$150,IF(COUNT(C23:C27)>3,Предпосылки!$B$151,Предпосылки!$B$149))*Предпосылки!$E$123,0) -> 80 | D12: =ROUNDDOWN(D3*IF(COUNT(D23:D27)>0,Предпосылки!$B$150,IF(COUNT(D23:D27)>3,Предпосылки!$B$151,Предпосылки!$B$149))*Предпосылки!$E$123,0) -> 145 | E12: =ROUNDDOWN(E3*IF(COUNT(E23:E27)>0,Предпосылки!$B$150,IF(COUNT(E23:E27)>3,Предпосылки!$B$151,Предпосылки!$B$149))*Предпосылки!$E$123,0) -> 70 | F12: =ROUNDDOWN(F3*IF(COUNT(F23:F27)>0,Предпосылки!$B$150,IF(COUNT(F23:F27)>3,Предпосылки!$B$151,Предпосылки!$B$149))*Предпосылки!$E$123,0) -> 70 | G12: =ROUNDDOWN(G3*IF(COUNT(G23:G27)>0,Предпосылки!$B$150,IF(COUNT(G23:G27)>3,Предпосылки!$B$151,Предпосылки!$B$149))*Предпосылки!$E$123,0) -> 130 | H12: =ROUNDDOWN(H3*IF(COUNT(H23:H27)>0,Предпосылки!$B$150,IF(COUNT(H23:H27)>3,Предпосылки!$B$151,Предпосылки!$B$149))*Предпосылки!$E$123,0) -> 63 | I12: =ROUNDDOWN(I3*IF(COUNT(I23:I27)>0,Предпосылки!$B$150,IF(COUNT(I23:I27)>3,Предпосылки!$B$151,Предпосылки!$B$149))*Предпосылки!$E$123,0) -> 63 | ... N12: =ROUNDDOWN(N3*IF(COUNT(N23:N27)>0,Предпосылки!$B$150,IF(COUNT(N23:N27)>3,Предпосылки!$B$151,Предпосылки!$B$149))*Предпосылки!$E$123,0) -> 80 | O12: =ROUNDDOWN(O3*IF(COUNT(O23:O27)<3,Предпосылки!$B$150,IF(COUNT(O23:O27)>3,Предпосылки!$B$151,Предпосылки!$B$149))*Предпосылки!$E$123*(1+Предпосылки!$B$152),0) -> 176 | P12: =ROUNDDOWN(P3*IF(COUNT(P23:P27)<3,Предпосылки!$B$150,IF(COUNT(P23:P27)>3,Предпосылки!$B$151,Предпосылки!$B$149))*Предпосылки!$E$123*(1+Предпосылки!$B$152),0) -> 74 | Q12: =ROUNDDOWN(Q3*IF(COUNT(Q23:Q27)<3,Предпосылки!$B$150,IF(COUNT(Q23:Q27)>3,Предпосылки!$B$151,Предпосылки!$B$149))*Предпосылки!$E$123*(1+Предпосылки!$B$152),0) -> 153 | R12: =ROUNDDOWN(R3*IF(COUNT(R23:R27)<3,Предпосылки!$B$150,IF(COUNT(R23:R27)>3,Предпосылки!$B$151,Предпосылки!$B$149))*Предпосылки!$E$123*(1+Предпосылки!$B$152),0) -> 153 | S12: =ROUNDDOWN(S3*IF(COUNT(S23:S27)<3,Предпосылки!$B$150,IF(COUNT(S23:S27)>3,Предпосылки!$B$151,Предпосылки!$B$149))*Предпосылки!$E$123*(1+Предпосылки!$B$152),0) -> 74 | T12: =ROUNDDOWN(T3*IF(COUNT(T23:T27)<3,Предпосылки!$B$150,IF(COUNT(T23:T27)>3,Предпосылки!$B$151,Предпосылки!$B$149))*Предпосылки!$E$123*(1+Предпосылки!$B$152),0) -> 153 | U12: =ROUNDDOWN(U3*IF(COUNT(U23:U27)<3,Предпосылки!$B$150,IF(COUNT(U23:U27)>3,Предпосылки!$B$151,Предпосылки!$B$149))*Предпосылки!$E$123*(1+Предпосылки!$B$152),0) -> 153 | V12: =ROUNDDOWN(V3*IF(COUNT(V23:V27)<3,Предпосылки!$B$150,IF(COUNT(V23:V27)>3,Предпосылки!$B$151,Предпосылки!$B$149))*Предпосылки!$E$123*(1+Предпосылки!$B$152),0) -> 239 | ... Z12: =ROUNDDOWN(Z3*IF(COUNT(Z23:Z27)<3,Предпосылки!$B$150,IF(COUNT(Z23:Z27)>3,Предпосылки!$B$151,Предпосылки!$B$149))*Предпосылки!$E$123*(1+Предпосылки!$B$152),0) -> 176 | AA12: =ROUNDDOWN(AA3*IF(COUNT(AA23:AA27)<3,Предпосылки!$B$150,IF(COUNT(AA23:AA27)>3,Предпосылки!$B$151,Предпосылки!$B$149))*Предпосылки!$E$123*(1+Предпосылки!$B$152)^2,0) -> 90 | AB12: =ROUNDDOWN(AB3*IF(COUNT(AB23:AB27)<3,Предпосылки!$B$150,IF(COUNT(AB23:AB27)>3,Предпосылки!$B$151,Предпосылки!$B$149))*Предпосылки!$E$123*(1+Предпосылки!$B$152)^2,0) -> 162 | AC12: =ROUNDDOWN(AC3*IF(COUNT(AC23:AC27)<3,Предпосылки!$B$150,IF(COUNT(AC23:AC27)>3,Предпосылки!$B$151,Предпосылки!$B$149))*Предпосылки!$E$123*(1+Предпосылки!$B$152)^2,0) -> 162 | AD12: =ROUNDDOWN(AD3*IF(COUNT(AD23:AD27)<3,Предпосылки!$B$150,IF(COUNT(AD23:AD27)>3,Предпосылки!$B$151,Предпосылки!$B$149))*Предпосылки!$E$123*(1+Предпосылки!$B$152)^2,0) -> 230 | AE12: =ROUNDDOWN(AE3*IF(COUNT(AE23:AE27)<3,Предпосылки!$B$150,IF(COUNT(AE23:AE27)>3,Предпосылки!$B$151,Предпосылки!$B$149))*Предпосылки!$E$123*(1+Предпосылки!$B$152)^2,0) -> 230 | AF12: =ROUNDDOWN(AF3*IF(COUNT(AF23:AF27)<3,Предпосылки!$B$150,IF(COUNT(AF23:AF27)>3,Предпосылки!$B$151,Предпосылки!$B$149))*Предпосылки!$E$123*(1+Предпосылки!$B$152)^2,0) -> 162 | AG12: =ROUNDDOWN(AG3*IF(COUNT(AG23:AG27)<3,Предпосылки!$B$150,IF(COUNT(AG23:AG27)>3,Предпосылки!$B$151,Предпосылки!$B$149))*Предпосылки!$E$123*(1+Предпосылки!$B$152)^2,0) -> 78 | AH12: =ROUNDDOWN(AH3*IF(COUNT(AH23:AH27)<3,Предпосылки!$B$150,IF(COUNT(AH23:AH27)>3,Предпосылки!$B$151,Предпосылки!$B$149))*Предпосылки!$E$123*(1+Предпосылки!$B$152)^2,0) -> 179 | ... AK12: =ROUNDDOWN(AK3*IF(COUNT(AK23:AK27)<3,Предпосылки!$B$150,IF(COUNT(AK23:AK27)>3,Предпосылки!$B$151,Предпосылки!$B$149))*Предпосылки!$E$123*(1+Предпосылки!$B$152)^2,0) -> 187
A13: Количество купленных классических ЦФА | B13: =ROUNDDOWN(B3*IF(COUNT(B23:B27)>0,Предпосылки!$B$150,(IF(COUNT(B23:B27)>3,Предпосылки!$B$151,Предпосылки!$B$149))+3%)*Предпосылки!$E$124,0) -> 115 | C13: =ROUNDDOWN(C3*IF(COUNT(C23:C27)>0,Предпосылки!$B$150,(IF(COUNT(C23:C27)>3,Предпосылки!$B$151,Предпосылки!$B$149))+3%)*Предпосылки!$E$124,0) -> 115 | D13: =ROUNDDOWN(D3*IF(COUNT(D23:D27)>0,Предпосылки!$B$150,(IF(COUNT(D23:D27)>3,Предпосылки!$B$151,Предпосылки!$B$149))+3%)*Предпосылки!$E$124,0) -> 145 | E13: =ROUNDDOWN(E3*IF(COUNT(E23:E27)>0,Предпосылки!$B$150,(IF(COUNT(E23:E27)>3,Предпосылки!$B$151,Предпосылки!$B$149))+3%)*Предпосылки!$E$124,0) -> 100 | F13: =ROUNDDOWN(F3*IF(COUNT(F23:F27)>0,Предпосылки!$B$150,(IF(COUNT(F23:F27)>3,Предпосылки!$B$151,Предпосылки!$B$149))+3%)*Предпосылки!$E$124,0) -> 100 | G13: =ROUNDDOWN(G3*IF(COUNT(G23:G27)>0,Предпосылки!$B$150,(IF(COUNT(G23:G27)>3,Предпосылки!$B$151,Предпосылки!$B$149))+3%)*Предпосылки!$E$124,0) -> 130 | H13: =ROUNDDOWN(H3*IF(COUNT(H23:H27)>0,Предпосылки!$B$150,(IF(COUNT(H23:H27)>3,Предпосылки!$B$151,Предпосылки!$B$149))+3%)*Предпосылки!$E$124,0) -> 90 | I13: =ROUNDDOWN(I3*IF(COUNT(I23:I27)>0,Предпосылки!$B$150,(IF(COUNT(I23:I27)>3,Предпосылки!$B$151,Предпосылки!$B$149))+3%)*Предпосылки!$E$124,0) -> 90 | ... N13: =ROUNDDOWN(N3*IF(COUNT(N23:N27)>0,Предпосылки!$B$150,(IF(COUNT(N23:N27)>3,Предпосылки!$B$151,Предпосылки!$B$149))+3%)*Предпосылки!$E$124,0) -> 115 | O13: =ROUNDDOWN(O3*IF(COUNT(O23:O27)<3,Предпосылки!$B$150,(IF(COUNT(O23:O27)>3,Предпосылки!$B$151,Предпосылки!$B$149))+2%)*Предпосылки!$E$124*(1+Предпосылки!$B$152),0) -> 176 | P13: =ROUNDDOWN(P3*IF(COUNT(P23:P27)<3,Предпосылки!$B$150,(IF(COUNT(P23:P27)>3,Предпосылки!$B$151,Предпосылки!$B$149))+2%)*Предпосылки!$E$124*(1+Предпосылки!$B$152),0) -> 95 | Q13: =ROUNDDOWN(Q3*IF(COUNT(Q23:Q27)<3,Предпосылки!$B$150,(IF(COUNT(Q23:Q27)>3,Предпосылки!$B$151,Предпосылки!$B$149))+2%)*Предпосылки!$E$124*(1+Предпосылки!$B$152),0) -> 153 | R13: =ROUNDDOWN(R3*IF(COUNT(R23:R27)<3,Предпосылки!$B$150,(IF(COUNT(R23:R27)>3,Предпосылки!$B$151,Предпосылки!$B$149))+2%)*Предпосылки!$E$124*(1+Предпосылки!$B$152),0) -> 153 | S13: =ROUNDDOWN(S3*IF(COUNT(S23:S27)<3,Предпосылки!$B$150,(IF(COUNT(S23:S27)>3,Предпосылки!$B$151,Предпосылки!$B$149))+2%)*Предпосылки!$E$124*(1+Предпосылки!$B$152),0) -> 95 | T13: =ROUNDDOWN(T3*IF(COUNT(T23:T27)<3,Предпосылки!$B$150,(IF(COUNT(T23:T27)>3,Предпосылки!$B$151,Предпосылки!$B$149))+2%)*Предпосылки!$E$124*(1+Предпосылки!$B$152),0) -> 153 | U13: =ROUNDDOWN(U3*IF(COUNT(U23:U27)<3,Предпосылки!$B$150,(IF(COUNT(U23:U27)>3,Предпосылки!$B$151,Предпосылки!$B$149))+2%)*Предпосылки!$E$124*(1+Предпосылки!$B$152),0) -> 153 | V13: =ROUNDDOWN(V3*IF(COUNT(V23:V27)<3,Предпосылки!$B$150,(IF(COUNT(V23:V27)>3,Предпосылки!$B$151,Предпосылки!$B$149))+3%)*Предпосылки!$E$124*(1+Предпосылки!$B$152),0) -> 274 | W13: =ROUNDDOWN(W3*IF(COUNT(W23:W27)<3,Предпосылки!$B$150,(IF(COUNT(W23:W27)>3,Предпосылки!$B$151,Предпосылки!$B$149))+3%)*Предпосылки!$E$124*(1+Предпосылки!$B$152),0) -> 169 | X13: =ROUNDDOWN(X3*IF(COUNT(X23:X27)<3,Предпосылки!$B$150,(IF(COUNT(X23:X27)>3,Предпосылки!$B$151,Предпосылки!$B$149))+3%)*Предпосылки!$E$124*(1+Предпосылки!$B$152),0) -> 116 | Y13: =ROUNDDOWN(Y3*IF(COUNT(Y23:Y27)<3,Предпосылки!$B$150,(IF(COUNT(Y23:Y27)>3,Предпосылки!$B$151,Предпосылки!$B$149))+3%)*Предпосылки!$E$124*(1+Предпосылки!$B$152),0) -> 176 | Z13: =ROUNDDOWN(Z3*IF(COUNT(Z23:Z27)<3,Предпосылки!$B$150,(IF(COUNT(Z23:Z27)>3,Предпосылки!$B$151,Предпосылки!$B$149))+3%)*Предпосылки!$E$124*(1+Предпосылки!$B$152),0) -> 176 | AA13: =ROUNDDOWN(AA3*IF(COUNT(AA23:AA27)<3,Предпосылки!$B$150,(IF(COUNT(AA23:AA27)>3,Предпосылки!$B$151,Предпосылки!$B$149))+3%)*Предпосылки!$E$124*(1+Предпосылки!$B$152)^2,0) -> 129 | AB13: =ROUNDDOWN(AB3*IF(COUNT(AB23:AB27)<3,Предпосылки!$B$150,(IF(COUNT(AB23:AB27)>3,Предпосылки!$B$151,Предпосылки!$B$149))+3%)*Предпосылки!$E$124*(1+Предпосылки!$B$152)^2,0) -> 162 | AC13: =ROUNDDOWN(AC3*IF(COUNT(AC23:AC27)<3,Предпосылки!$B$150,(IF(COUNT(AC23:AC27)>3,Предпосылки!$B$151,Предпосылки!$B$149))+3%)*Предпосылки!$E$124*(1+Предпосылки!$B$152)^2,0) -> 162 | AD13: =ROUNDDOWN(AD3*IF(COUNT(AD23:AD27)<3,Предпосылки!$B$150,(IF(COUNT(AD23:AD27)>3,Предпосылки!$B$151,Предпосылки!$B$149))+3%)*Предпосылки!$E$124*(1+Предпосылки!$B$152)^2,0) -> 264 | AE13: =ROUNDDOWN(AE3*IF(COUNT(AE23:AE27)<3,Предпосылки!$B$150,(IF(COUNT(AE23:AE27)>3,Предпосылки!$B$151,Предпосылки!$B$149))+3%)*Предпосылки!$E$124*(1+Предпосылки!$B$152)^2,0) -> 264 | AF13: =ROUNDDOWN(AF3*IF(COUNT(AF23:AF27)<3,Предпосылки!$B$150,(IF(COUNT(AF23:AF27)>3,Предпосылки!$B$151,Предпосылки!$B$149))+3%)*Предпосылки!$E$124*(1+Предпосылки!$B$152)^2,0) -> 162 | AG13: =ROUNDDOWN(AG3*IF(COUNT(AG23:AG27)<3,Предпосылки!$B$150,(IF(COUNT(AG23:AG27)>3,Предпосылки!$B$151,Предпосылки!$B$149))+3%)*Предпосылки!$E$124*(1+Предпосылки!$B$152)^2,0) -> 112 | AH13: =ROUNDDOWN(AH3*IF(COUNT(AH23:AH27)<3,Предпосылки!$B$150,(IF(COUNT(AH23:AH27)>3,Предпосылки!$B$151,Предпосылки!$B$149))+3%)*Предпосылки!$E$124*(1+Предпосылки!$B$152)^2,0) -> 179 | ... AK13: =ROUNDDOWN(AK3*IF(COUNT(AK23:AK27)<3,Предпосылки!$B$150,(IF(COUNT(AK23:AK27)>3,Предпосылки!$B$151,Предпосылки!$B$149))+3%)*Предпосылки!$E$124*(1+Предпосылки!$B$152)^2,0) -> 187
A14: Сумма приобретенных ЦФА | B14: =B$10*Предпосылки!$D$122 -> 275000 | C14: =C$10*Предпосылки!$D$122 -> 275000 | D14: =D$10*Предпосылки!$D$122 -> 435000 | E14: =E$10*Предпосылки!$D$122 -> 240000 | F14: =F$10*Предпосылки!$D$122 -> 240000 | G14: =G$10*Предпосылки!$D$122 -> 390000 | H14: =H$10*Предпосылки!$D$122 -> 216000 | I14: =I$10*Предпосылки!$D$122 -> 216000 | ... N14: =N$10*Предпосылки!$D$122 -> 275000 | O14: =O$10*1000 -> 528000 | P14: =P$10*1000 -> 243000 | Q14: =Q$10*1000 -> 459000 | R14: =R$10*1000 -> 459000 | S14: =S$10*1000 -> 243000 | T14: =T$10*1000 -> 459000 | U14: =U$10*1000 -> 459000 | V14: =V10*Предпосылки!$D$122 -> 752000 | W14: =W10*Предпосылки!$D$122 -> 507000 | X14: =X10*Предпосылки!$D$122 -> 278000 | Y14: =Y10*Предпосылки!$D$122 -> 528000 | Z14: =Z10*Предпосылки!$D$122 -> 528000 | AA14: =AA10*Предпосылки!$D$122 -> 309000 | AB14: =AB10*Предпосылки!$D$122 -> 486000 | AC14: =AC10*Предпосылки!$D$122 -> 486000 | ... AL14: =AL10*Предпосылки!$D$122 -> 0
A15: Сумма к выплате по ЦФА на скины | N15: =N7*(1+Предпосылки!$N$122) -> 0
A16: Сумма к выплате по Fan-токенам | N16: =N8*(1+Предпосылки!$N$123) -> 875700.28 | Z16: =Z8*(1+Предпосылки!$N$123) -> 1035399.1 | AL16: =AL8*(1+Предпосылки!$N$123) -> 2151732.5
A17: Сумма к выплате по классическим ЦФА | N17: =N9*(1+Предпосылки!$N$124) -> 1058958.9 | Z17: =Z9*(1+Предпосылки!$N$124) -> 1123546.9 | AL17: =AL9*(1+Предпосылки!$N$124) -> 2370962.8
A18: Интеграция Alfa ID в платформу покупки внутриигровых продуктов | B18: =Расходы!$C$15 -> -500000
A19: Выплата ЦФА | N19: =-(SUM(N15:N17)) -> -1934659.2 | Z19: =-SUM(Z15:Z17) -> -2158946 | AH19: =-(SUM(AH15:AH17)) -> 0 | AL19: =-SUM(AL15:AL17) -> -4522695.3
A20: Аналитика | B20: =Расходы!D4 -> -100000 | C20: =B20 -> -100000 | D20: =C20 -> -100000 | E20: =D20 -> -100000 | F20: =E20 -> -100000 | G20: =F20 -> -100000 | H20: =G20 -> -100000 | I20: =H20 -> -100000 | J20: =I20 -> -100000 | ... S20: =R20 -> -100000 | T20: 0 | U20: =T20 -> 0 | V20: 0 | W20: =V20 -> 0 | X20: =W20 -> 0 | Y20: =X20 -> 0 | Z20: =Y20 -> 0 | AA20: =Z20 -> 0 | AB20: =AA20 -> 0 | AC20: =AB20 -> 0 | AD20: =AC20 -> 0 | ... AK20: =AJ20 -> 0 | AL20: 0
A21: Интернет-маркетинг | B21: =Расходы!D5 -> -150000 | C21: =B21 -> -150000 | D21: =C21 -> -150000 | E21: =D21 -> -150000 | F21: =E21 -> -150000 | G21: =F21 -> -150000 | H21: =G21 -> -150000 | I21: =H21 -> -150000 | J21: =I21 -> -150000 | ... S21: =R21 -> -150000 | T21: 0 | U21: =T21 -> 0 | V21: 0 | W21: =V21 -> 0 | X21: =W21 -> 0 | Y21: =X21 -> 0 | Z21: =Y21 -> 0 | AA21: =Z21 -> 0 | AB21: =AA21 -> 0 | AC21: =AB21 -> 0 | AD21: =AC21 -> 0 | ... AK21: =AJ21 -> 0 | AL21: 0
A22: Юридическая и экономическая подготовка | B22: =Расходы!D6 -> -150000 | C22: =B22 -> -150000 | D22: =C22 -> -150000 | E22: =D22 -> -150000 | F22: =E22 -> -150000 | G22: =F22 -> -150000 | H22: =G22 -> -150000 | I22: =H22 -> -150000 | J22: =I22 -> -150000 | ... S22: =R22 -> -150000 | T22: 0 | U22: =T22 -> 0 | V22: 0 | W22: =V22 -> 0 | X22: =W22 -> 0 | Y22: =X22 -> 0 | Z22: =Y22 -> 0 | AA22: =Z22 -> 0 | AB22: =AA22 -> 0 | AC22: =AB22 -> 0 | AD22: =AC22 -> 0 | ... AK22: =AJ22 -> 0 | AL22: 0
A23: Контент и образование 1 | D23: =Расходы!D8 -> -500000 | G23: 0 | J23: =G23 -> 0 | M23: =J23 -> 0 | P23: =M23 -> 0 | S23: =P23 -> 0 | V23: 0 | X23: =Расходы!C42 -> 0 | Y23: 0 | AA23: =X23 -> 0 | AB23: 0 | AD23: =AA23 -> 0 | AE23: 0 | AG23: =AD23 -> 0 | AJ23: =AG23 -> 0
A24: Контент и образование 2 | D24: =Расходы!C9 -> 0 | G24: 0 | J24: 0 | M24: =Расходы!D9 -> -500000 | P24: =M24 -> -500000 | S24: =P24 -> -500000 | V24: 0 | X24: =Расходы!C43 -> 0 | Y24: 0 | AA24: =X24 -> 0 | AB24: 0 | AD24: =AA24 -> 0 | AE24: 0 | AG24: =AD24 -> 0 | AJ24: =AG24 -> 0
A25: PR и репутационные активности 1 | D25: =Расходы!C10 -> 0 | G25: =D25 -> 0 | J25: =G25 -> 0 | M25: =J25 -> 0 | P25: =M25 -> 0 | S25: =P25 -> 0 | V25: 0 | X25: =Расходы!C44 -> 0 | AA25: =X25 -> 0 | AD25: =AA25 -> 0 | AE25: 0 | AG25: =AD25 -> 0 | AJ25: =AG25 -> 0
A26: Контент и образование 3 | J26: =Расходы!C12 -> -50000 | V26: =Расходы!D12 -> -1500000 | AD26: =Расходы!C46 -> 0 | AE26: 0
A27: PR и репутационные активности 2 | J27: =Расходы!C13 -> -200000 | V27: 0 | AD27: =Расходы!C47 -> 0 | AE27: =Расходы!D13 -> -1000000
A28: Комиссия Оператора | B28: =-B$14*Расходы!$C$17 -> -5500 | C28: =-C$14*Расходы!$C$17 -> -5500 | D28: =-D$14*Расходы!$C$17 -> -8700 | E28: =-E$14*Расходы!$C$17 -> -4800 | F28: =-F$14*Расходы!$C$17 -> -4800 | G28: =-G$14*Расходы!$C$17 -> -7800 | H28: =-H$14*Расходы!$C$17 -> -4320 | I28: =-I$14*Расходы!$C$17 -> -4320 | ... U28: =-U$14*Расходы!$C$17 -> -9180 | V28: =-V14*Расходы!$C$17 -> -15040 | W28: =-W14*Расходы!$C$17 -> -10140 | X28: =-X14*Расходы!$C$17 -> -5560 | Y28: =-Y14*Расходы!$C$17 -> -10560 | Z28: =-Z14*Расходы!$C$17 -> -10560 | AA28: =-AA14*Расходы!$C$17 -> -6180 | AB28: =-AB14*Расходы!$C$17 -> -9720 | AC28: =-AC14*Расходы!$C$17 -> -9720 | ... AL28: =-AL14*Расходы!$C$17 -> 0
A29: Экстраординарные затраты | B29: =-Расходы!$C$21*B$14 -> -13750 | C29: =-Расходы!$C$21*C$14 -> -13750 | D29: =-Расходы!$C$21*D$14 -> -21750 | E29: =-Расходы!$C$21*E$14 -> -12000 | F29: =-Расходы!$C$21*F$14 -> -12000 | G29: =-Расходы!$C$21*G$14 -> -19500 | H29: =-Расходы!$C$21*H$14 -> -10800 | I29: =-Расходы!$C$21*I$14 -> -10800 | ... U29: =-Расходы!$C$21*U$14 -> -22950 | V29: =-Расходы!$C$21*V14 -> -37600 | W29: =-Расходы!$C$21*W14 -> -25350 | X29: =-Расходы!$C$21*X14 -> -13900 | Y29: =-Расходы!$C$21*Y14 -> -26400 | Z29: =-Расходы!$C$21*Z14 -> -26400 | AA29: =-Расходы!$C$21*AA14 -> -15450 | AB29: =-Расходы!$C$21*AB14 -> -24300 | AC29: =-Расходы!$C$21*AC14 -> -24300 | ... AL29: =-Расходы!$C$21*AL14 -> 0
A30: Сумма издержек | B30: =SUM(B18:B29) -> -919250 | C30: =SUM(C18:C29) -> -419250 | D30: =SUM(D18:D29) -> -930450 | E30: =SUM(E18:E29) -> -416800 | F30: =SUM(F18:F29) -> -416800 | G30: =SUM(G18:G29) -> -427300 | H30: =SUM(H18:H29) -> -415120 | I30: =SUM(I18:I29) -> -415120 | ... N30: =SUM(N18:N29) -> -2353909.2 | O30: =SUM(O20:O29) -> -436960 | P30: =SUM(P20:P29) -> -917010 | Q30: =SUM(Q20:Q29) -> -432130 | R30: =SUM(R20:R29) -> -432130 | S30: =SUM(S20:S29) -> -917010 | T30: =SUM(T20:T29) -> -32130 | U30: =SUM(U20:U29) -> -32130 | V30: =SUM(V18:V29) -> -1552640 | W30: =SUM(W18:W29) -> -35490 | X30: =SUM(X18:X29) -> -19460 | Y30: =SUM(Y18:Y29) -> -36960 | Z30: =SUM(Z18:Z29) -> -2195906 | AA30: =SUM(AA18:AA29) -> -21630 | AB30: =SUM(AB18:AB29) -> -34020 | AC30: =SUM(AC18:AC29) -> -34020 | ... AL30: =SUM(AL18:AL29) -> -4522695.3
A31: Прибыль до налогооблажения | B31: =B14+B30 -> -644250 | C31: =C14+C30 -> -144250 | D31: =D14+D30 -> -495450 | E31: =E14+E30 -> -176800 | F31: =F14+F30 -> -176800 | G31: =G14+G30 -> -37300 | H31: =H14+H30 -> -199120 | I31: =I14+I30 -> -199120 | ... M31: =M14+M30 -> -436860 | N31: =N18+N14+N30 -> -2078909.2 | O31: =O18+O14+O30 -> 91040 | P31: =P18+P14+P30 -> -674010 | Q31: =Q18+Q14+Q30 -> 26870 | R31: =R18+R14+R30 -> 26870 | S31: =S18+S14+S30 -> -674010 | T31: =T18+T14+T30 -> 426870 | U31: =U18+U14+U30 -> 426870 | V31: =V14+V30 -> -800640 | W31: =W14+W30 -> 471510 | X31: =X14+X30 -> 258540 | Y31: =Y14+Y30 -> 491040 | Z31: =Z14+Z30 -> -1667906 | AA31: =AA14+AA30 -> 287370 | AB31: =AB14+AB30 -> 451980 | AC31: =AC14+AC30 -> 451980 | ... AL31: =AL14+AL30 -> -4522695.3
A32: Налог на прибыль | B32: =IF(B$31>0,B$31*Расходы!$C$22,0) -> 0 | C32: =IF(C$31>0,C$31*Расходы!$C$22,0) -> 0 | D32: =IF(D$31>0,D$31*Расходы!$C$22,0) -> 0 | E32: =IF(E$31>0,E$31*Расходы!$C$22,0) -> 0 | F32: =IF(F$31>0,F$31*Расходы!$C$22,0) -> 0 | G32: =IF(G$31>0,G$31*Расходы!$C$22,0) -> 0 | H32: =IF(H$31>0,H$31*Расходы!$C$22,0) -> 0 | I32: =IF(I$31>0,I$31*Расходы!$C$22,0) -> 0 | ... U32: =IF(U$31>0,U$31*Расходы!$C$22,0) -> 21343.5 | V32: =IF(V31>0,V31*Расходы!$C$22,0) -> 0 | W32: =IF(W31>0,W31*Расходы!$C$22,0) -> 23575.5 | X32: =IF(X31>0,X31*Расходы!$C$22,0) -> 12927 | Y32: =IF(Y31>0,Y31*Расходы!$C$22,0) -> 24552 | Z32: =IF(Z31>0,Z31*Расходы!$C$22,0) -> 0 | AA32: =IF(AA31>0,AA31*Расходы!$C$22,0) -> 14368.5 | AB32: =IF(AB31>0,AB31*Расходы!$C$22,0) -> 22599 | AC32: =IF(AC31>0,AC31*Расходы!$C$22,0) -> 22599 | ... AL32: =IF(AL31>0,AL31*Расходы!$C$22,0) -> 0
A33: Чистая прибыль | B33: =B31-B32 -> -644250 | C33: =C31-C32 -> -144250 | D33: =D31-D32 -> -495450 | E33: =E31-E32 -> -176800 | F33: =F31-F32 -> -176800 | G33: =G31-G32 -> -37300 | H33: =H31-H32 -> -199120 | I33: =I31-I32 -> -199120 | ... AL33: =AL31-AL32 -> -4522695.3
A35: Прибыль за 3 года | B35: =SUM(B33:U33,V33:AL33) -> -7518789.6
A37: Основные выводы | B37: Пессимистичный сценарий раскрывает основные уязвимости проекта. Он описывает ситуацию вялого, инертного спроса, при котором для привлечения инвесторов требуются постоянные и значительные усилия по просвещению аудитории и доказательству инвестиционной привлекательности ЦФА в игровой индустрии. Низкая начальная конверсия (0,07%) и высокие барьеры в виде недоверия пользователей приводят к тому, что на старте ядро покупателей составляют почти исключительно квалифицированные инвесторы. Массовая игровая аудитория подключается медленно и только после продолжительных разъяснительных работ. В этих условиях прибыль проекта минимальна, а срок окупаемости значительно увеличивается. Для успеха в таком сценарии критически важныдополнительные меры поддержки и акцент на стратегическом планировании и анализе, а не на агрессивных продажах. Этот сценарий демонстрирует, что без сформированного рыночного спроса проект сталкивается с серьезными финансовыми вызовами. При таком сценарии проект генерирует значительные убытки, что делает его непривлекательным для инвестирования.
B38: Рекомендация: в Сценарии 3 нецелесообразна без кардинальной переработки бизнес-модели — в частности, снижения фиксированных затрат и ориентация на большие пиар-компании для повышения конверсии или пересмотра условий привлечения неквалифицированных инвесторов. В текущем виде сценарий следует рассматривать как стресс-тест на устойчивость к неблагоприятным рыночным условиям.

Sheet Свод Cash-Flow
A1: Свод различных сценариев Cash-Flow
A2: Чистая прибыль по сценариям | L2: Основные выводы:
A3: Месяц | B3: Сценарий 1 | C3: Сценарий 2 | D3: Сценарий 3 | G3: Сценарий 1 | H3: Сценарий 2 | I3: Сценарий 3 | L3: Сценарий 1 (оптимистичный) демонстрирует высокую инвестиционную привлекательность: IRR = 23 %, положительные значения NPV при всех используемых ставках дисконтирования (от 1,45 млн до 1,63 млн руб.).
A4: 1 | B4: {=TRANSPOSE('Cash-Flow 1'!$B$32:$U$32)} -> -19190 | C4: {=TRANSPOSE('Cash-Flow 2'!B32:U32)} -> -244250 | D4: {=TRANSPOSE('Cash-Flow 3'!B33:U33)} -> -644250 | F4: IRR | G4: =IF(G5>0,IRR(B4:B40),0) -> 23.161135 | H4: =IF(H5>0,IRR(C4:C40),0) -> 1.1223179 | I4: =IF(I5>0,IRR(D4:D40),0) -> 0
A5: 2 | B5: 447051 | C5: 242962.5 | D5: -144250 | F5: NPV (ставка ЦБ) | G5: {=NPV(Предпосылки!$M$123,B4,B5,B6,B7,B8,B9,B10,B11,B12,B13,B14,B15,B16,B17,B18,B19,B20,B21,B22,B23,B24,B25,B26,B27,B28,B29,B30,B31,B32,B33,B34,B35,B36,B37,B38,B39,B40)} -> 1454773.6 | H5: {=NPV(Предпосылки!$M$123,C4,C5,C6,C7,C8,C9,C10,C11,C12,C13,C14,C15,C16,C17,C18,C19,C20,C21,C22,C23,C24,C25,C26,C27,C28,C29,C30,C31,C32,C33,C34,C35,C36,C37,C38,C39,C40)} -> 789238.03 | I5: {=NPV(Предпосылки!$M$123,D4,D5,D6,D7,D8,D9,D10,D11,D12,D13,D14,D15,D16,D17,D18,D19,D20,D21,D22,D23,D24,D25,D26,D27,D28,D29,D30,D31,D32,D33,D34,D35,D36,D37,D38,D39,D40)} -> -1788603.3 | J5: Общие максимальные значения | L5: Сценарий 2 экономически менее эффективен: IRR = 1 %, NPV положителен, но значительно ниже (от 0,79 млн до 0,91 млн руб.). Здесь допускается активность аудитории на уровне пессимистичного сценария, но отсутсвие использования дополнительных финансов для увеличения привлекательности продуктов.
A6: 3 | B6: 384322.5 | C6: 384322.5 | D6: -495450 | F6: NPV (RUONIA) | G6: {=NPV(Предпосылки!$M$124,B4,B5,B6,B7,B8,B9,B10,B11,B12,B13,B14,B15,B16,B17,B18,B19,B20,B21,B22,B23,B24,B25,B26,B27,B28,B29,B30,B31,B32,B33,B34,B35,B36,B37,B38,B39,B40)} -> 1454773.6 | H6: {=NPV(Предпосылки!$M$124,C4,C5,C6,C7,C8,C9,C10,C11,C12,C13,C14,C15,C16,C17,C18,C19,C20,C21,C22,C23,C24,C25,C26,C27,C28,C29,C30,C31,C32,C33,C34,C35,C36,C37,C38,C39,C40)} -> 789238.03 | I6: {=NPV(Предпосылки!$M$124,D4,D5,D6,D7,D8,D9,D10,D11,D12,D13,D14,D15,D16,D17,D18,D19,D20,D21,D22,D23,D24,D25,D26,D27,D28,D29,D30,D31,D32,D33,D34,D35,D36,D37,D38,D39,D40)} -> -1788603.3
A7: 4 | B7: 388740 | C7: 212040 | D7: -176800 | F7: NPV (по ОФЗ) | G7: {=NPV(Предпосылки!$M$122,B4,B5,B6,B7,B8,B9,B10,B11,B12,B13,B14,B15,B16,B17,B18,B19,B20,B21,B22,B23,B24,B25,B26,B27,B28,B29,B30,B31,B32,B33,B34,B35,B36,B37,B38,B39,B40)} -> 1631015.1 | H7: {=NPV(Предпосылки!$M$122,C4,C5,C6,C7,C8,C9,C10,C11,C12,C13,C14,C15,C16,C17,C18,C19,C20,C21,C22,C23,C24,C25,C26,C27,C28,C29,C30,C31,C32,C33,C34,C35,C36,C37,C38,C39,C40)} -> 906205.94 | I7: {=NPV(Предпосылки!$M$122,D4,D5,D6,D7,D8,D9,D10,D11,D12,D13,D14,D15,D16,D17,D18,D19,D20,D21,D22,D23,D24,D25,D26,D27,D28,D29,D30,D31,D32,D33,D34,D35,D36,D37,D38,D39,D40)} -> -2015951.1
A8: 5 | B8: 388740 | C8: 212040 | D8: -176800 | F8: Максимальная прибыль | G8: =MAX(B4:B40) -> 639654 | H8: =MAX(C4:C40) -> 639654 | I8: =MAX(D4:D40) -> 639654 | J8: =MAX(G8:I9) -> 639654 | L8: Сценарий 3 является убыточным: IRR = 0 %, NPV отрицателен при всех ставках дисконтирования (от –1,79 млн до –2,02 млн руб.). Здесь применяется использование дополнительных рычагов по привлечению аудитории, что увеличивает издержки на ведение проекта.
A9: 6 | B9: 344565 | C9: 344565 | D9: -37300
A10: 7 | B10: 349866 | C10: 190836 | D10: -199120 | F10: Максимальная сумма издержек с учетом выплат | G10: =MIN(B4:B40) -> -5905740 | H10: =MIN(C4:C40) -> -5942983.5 | I10: =MIN(D4:D40) -> -4522695.3 | J10: =MIN(G10:I12) -> -5942983.5
A11: 8 | B11: 349866 | C11: 190836 | D11: -199120
A12: 9 | B12: 378299.5 | C12: 183929.5 | D12: -206390 | L12: Максимальная прибыль одинакова во всех сценариях (639 654 руб.), что указывает на единый потенциальный доход от проекта независимо от выбранного сценария. Следовательно, различия в финансовых результатах обусловлены не доходами, а структурой и объёмом издержек.
A13: 10 | B13: 421429.5 | C13: 233244 | D13: -154480
A14: 11 | B14: 421429.5 | C14: 233244 | D14: -154480
A15: 12 | B15: 447051 | C15: 439983 | D15: -436860 | L15: Наибольшие суммарные издержки с учётом выплат зафиксированы в Сценарии 2 (–5 942 983 руб.), несмотря на то, что он менее прибылен по NPV, чем Сценарий 1.
A16: 13 | B16: -3002240.1 | C16: -2106089 | D16: -2078909.2
A17: 14 | B17: 439983 | C17: 439983 | D17: 86488 | L17: Наименьшие издержки — в Сценарии 3 (–4 522 695 руб.), однако даже при этом проект оказывается убыточным по NPV, что может свидетельствовать о неэффективном распределении ресурсов или недостаточном объёме привлечённых инвестиций.
A18: 15 | B18: 388740 | C18: 203205 | D18: -674010
A19: 16 | B19: 384322.5 | C19: 384322.5 | D19: 25526.5
A20: 17 | B20: 384322.5 | C20: 384322.5 | D20: 25526.5
A21: 18 | B21: 388740 | C21: 203205 | D21: -674010
A22: 19 | B22: 384322.5 | C22: 384322.5 | D22: 405526.5
A23: 20 | B23: 384322.5 | C23: 384322.5 | D23: 405526.5
A24: 21 | B24: {=TRANSPOSE('Cash-Flow 1'!V32:AL32)} -> 426892 | C24: {=TRANSPOSE('Cash-Flow 2'!V32:AL32)} -> 426892 | D24: {=TRANSPOSE('Cash-Flow 3'!V33:AL33)} -> -800640
A25: 22 | B25: 447934.5 | C25: 447934.5 | D25: 447934.5
A26: 23 | B26: 462954 | C26: 245613 | D26: 245613
A27: 24 | B27: 466488 | C27: 466488 | D27: 466488
A28: 25 | B28: -2376802.4 | C28: -2650168 | D28: -1667906
A29: 26 | B29: 511546.5 | C29: 273001.5 | D29: 273001.5
A30: 27 | B30: 429381 | C30: 429381 | D30: 429381
A31: 28 | B31: 429381 | C31: 429381 | D31: 429381
A32: 29 | B32: 639654 | C32: 639654 | D32: 639654
A33: 30 | B33: 402154 | C33: 402154 | D33: -326680
A34: 31 | B34: 429381 | C34: 429381 | D34: 429381
A35: 32 | B35: 446167.5 | C35: 236778 | D35: 236778
A36: 33 | B36: 474439.5 | C36: 474439.5 | D36: 474439.5
... A40: 37 | B40: -5905740 | C40: -5942983.5 | D40: -4522695.3

Sheet Unit-экономика
A1: Unit-экономика
A2: 2 | B2: Выбор сценария (можно выбрать: 1, 2 или 3)
A3: Продукт | B3: CAC | C3: LTV | D3: Обоснование LTV | E3: LTV-CAC | F3: UA | G3: CTR | H3: CR | I3: ARPPU | J3: APC | K3: AvP | L3: CPA | M3: MR
A4: ЦФА на скины | B4: =IF(A2=1,-SUM('Cash-Flow 1'!B19:M26,'Cash-Flow 1'!N19:N26,'Cash-Flow 1'!O19:U26,'Cash-Flow 1'!V17:Y28,'Cash-Flow 1'!Z19:Z28,'Cash-Flow 1'!AA17:AK28)/(SUM('Cash-Flow 1'!$V$9:$AK$9,'Cash-Flow 1'!B9:U9)*3),IF(A2=2,-SUM('Cash-Flow 2'!B19:M26,'Cash-Flow 2'!N19:N26,'Cash-Flow 2'!O19:U26,'Cash-Flow 2'!V17:Y28,'Cash-Flow 2'!Z19:Z28,'Cash-Flow 2'!AA17:AK28)/(SUM('Cash-Flow 2'!V9:AK9,'Cash-Flow 2'!B9:U9)*3),-SUM('Cash-Flow 3'!B20:AL25)/(SUM('Cash-Flow 3'!B11:AK11)*3))) -> 29.575914 | C4: =Предпосылки!$D$122/12 -> 83.333333 | D4: Данный продукт характеризуется одноразовой или кратковременной моделью потребления. Игрок совершает покупку 1-2 раза, после чего теряет интерес к продукту. (Поэтому предполагаем, что на данный продукт по одному уникальному пользователю). | E4: =C4-B4 -> 53.75742 | F4: При расчетах Cash-flow было допущение, что каждый инвестор уникальный (покупает по одному ЦФА). | G4: При расчетах Cash-flow было допущение, что конверсия после рекламы и пиар компаний является задаваемой переменной. | H4: =IF(A2=1,(Предпосылки!$B$148*12+Предпосылки!$B$150*12+Предпосылки!$B$151*2)/36,IF(A2=2,(Предпосылки!$B$149*12+Предпосылки!$B$150*12+Предпосылки!$B$151*2)/36,IF(A2=3,(Предпосылки!$B$149*12+Предпосылки!$B$150*12+Предпосылки!$B$151*2)/36))) -> 0.083055556 | I4: =Предпосылки!$D$122 -> 1000 | J4: В нашем сценарии: 1 инвестор = 1 покупка ЦФА. | K4: =Предпосылки!$D$122-Предпосылки!$D$122*Предпосылки!$N$122/((1+Предпосылки!$D$172)*(1+Предпосылки!$D$173)*(1+Предпосылки!$D$174)) -> 875.04419 | L4: В нашем случае "действием" является покупка ЦФА. Тогда CPA будет равен CAC. | M4: =IF(A2=1,SUM('Cash-Flow 1'!B10:U10,'Cash-Flow 1'!V10:AK10)*1000+(SUM('Cash-Flow 1'!B27:U28,'Cash-Flow 1'!V27:AL28)/3)-'Cash-Flow 1'!N14-'Cash-Flow 1'!$Z14-'Cash-Flow 1'!$AL14,IF(A2=2,SUM('Cash-Flow 2'!B10:U10,'Cash-Flow 2'!V10:AK10)*1000+(SUM('Cash-Flow 2'!B27:U28,'Cash-Flow 2'!V27:AK28)/3)-'Cash-Flow 2'!N14-'Cash-Flow 2'!Z14-'Cash-Flow 2'!AL14,SUM('Cash-Flow 3'!B11:U11,'Cash-Flow 3'!V11:AK11)*1000+(SUM('Cash-Flow 3'!B28:U29,'Cash-Flow 3'!V28:AH29)/3)-'Cash-Flow 3'!AL15-'Cash-Flow 3'!Z15-'Cash-Flow 3'!N15)) -> 1527899.2
A5: Fan-токен | B5: =IF(A2=1,-SUM('Cash-Flow 1'!B19:M26,'Cash-Flow 1'!N19:N26,'Cash-Flow 1'!O19:U26,'Cash-Flow 1'!V17:Y28,'Cash-Flow 1'!Z19:Z28,'Cash-Flow 1'!AA17:AK28)/(SUM('Cash-Flow 1'!$V$9:$AK$9,'Cash-Flow 1'!B9:U9)*3),IF(A2=2,-SUM('Cash-Flow 2'!B19:M26,'Cash-Flow 2'!N19:N26,'Cash-Flow 2'!O19:U26,'Cash-Flow 2'!V17:Y28,'Cash-Flow 2'!Z19:Z28,'Cash-Flow 2'!AA17:AK28)/(SUM('Cash-Flow 2'!V9:AK9,'Cash-Flow 2'!B9:U9)*3),-SUM('Cash-Flow 3'!B20:AL25)/(SUM('Cash-Flow 3'!B12:AK12)*3))) -> 29.575914 | C5: =Предпосылки!$D$122/12*2 -> 166.66667 | D5: Продукт основан на эмоциональной привязанности и долгосрочной вовлеченности с сообществом (разработчики и игроманы). Это мотивирует играющих на повторные покупки (голосования, эксклюзивный контент) и способствует более длительному удержанию по сравнению со скинами. (Предполагаем, что один пользователь делает в среднемоколо 2 покупок данного ЦФА) | E5: =C5-B5 -> 137.09075 | H5: =IF(A2=1,(Предпосылки!$B$148*12+Предпосылки!$B$150*12+Предпосылки!$B$151*2)/36,IF(A2=2,(Предпосылки!$B$149*12+Предпосылки!$B$150*12+Предпосылки!$B$151*2)/36,IF(A2=3,(Предпосылки!$B$149*12+Предпосылки!$B$150*12+Предпосылки!$B$151*2)/36))) -> 0.083055556 | I5: =I4 -> 1000 | K5: =Предпосылки!$D$122-Предпосылки!$D$122*Предпосылки!$N$123/((1+Предпосылки!$D$172)*(1+Предпосылки!$D$173)*(1+Предпосылки!$D$174)) -> 852.53662 | M5: =IF(A2=1,SUM('Cash-Flow 1'!B11:U11,'Cash-Flow 1'!V11:AK11)*1000+(SUM('Cash-Flow 1'!B27:U28,'Cash-Flow 1'!V27:AL28)/3)-'Cash-Flow 1'!N15-'Cash-Flow 1'!$Z15-'Cash-Flow 1'!$AL15,IF(A2=2,SUM('Cash-Flow 2'!B11:U11,'Cash-Flow 2'!V11:AK11)*1000+(SUM('Cash-Flow 2'!B27:U28,'Cash-Flow 2'!V27:AK28)/3)-'Cash-Flow 2'!N15-'Cash-Flow 2'!Z15-'Cash-Flow 2'!AL15,SUM('Cash-Flow 3'!B12:U12,'Cash-Flow 3'!V12:AK12)*1000+(SUM('Cash-Flow 3'!B28:U29,'Cash-Flow 3'!V28:AH29)/3)-'Cash-Flow 3'!AL16-'Cash-Flow 3'!Z16-'Cash-Flow 3'!N16)) -> 339376.34
A6: Классический ЦФА | B6: =IF(A2=1,-SUM('Cash-Flow 1'!B19:M26,'Cash-Flow 1'!N19:N26,'Cash-Flow 1'!O19:U26,'Cash-Flow 1'!V17:Y28,'Cash-Flow 1'!Z19:Z28,'Cash-Flow 1'!AA17:AK28)/(SUM('Cash-Flow 1'!$V$9:$AK$9,'Cash-Flow 1'!B9:U9)*3),IF(A2=2,-SUM('Cash-Flow 2'!B19:M26,'Cash-Flow 2'!N19:N26,'Cash-Flow 2'!O19:U26,'Cash-Flow 2'!V17:Y28,'Cash-Flow 2'!Z19:Z28,'Cash-Flow 2'!AA17:AK28)/(SUM('Cash-Flow 2'!V9:AK9,'Cash-Flow 2'!B9:U9)*3),-SUM('Cash-Flow 3'!B20:AL25)/(SUM('Cash-Flow 3'!B13:AK13)*3))) -> 29.575914 | C6: =Предпосылки!$D$122/12*3 -> 250 | D6: Классический ЦФА обладает инвестиционной ценностью. Держатели приобретают актив не для разовой операции, а для долгосрочного хранения и диверсификации портфеля с целью получения процентов или роста курсовой стоимости. Это создает максимально длинный жизненный цикл клиента и постоянный поток комиссий за покупку ЦФА. (Предполагаем, что в среднем каждый инвестор приобретает новый ЦФА каждый выпуск ~ 3). | E6: =C6-B6 -> 220.42409 | H6: =IF(A2=1,((Предпосылки!$B$148+3%)*12+Предпосылки!$B$150*12+Предпосылки!$B$151*2)/36,IF(A2=2,((Предпосылки!$B$149+3%)*12+Предпосылки!$B$150*12+Предпосылки!$B$151*2)/36,IF(A2=3,((Предпосылки!$B$149+3%)*12+Предпосылки!$B$150*12+Предпосылки!$B$151*2)/36))) -> 0.093055556 | I6: =I5 -> 1000 | K6: =Предпосылки!$D$122-Предпосылки!$D$122*Предпосылки!$N$124/((1+Предпосылки!$D$172)*(1+Предпосылки!$D$173)*(1+Предпосылки!$D$174)) -> 844.77539 | M6: =IF(A2=1,SUM('Cash-Flow 1'!B12:U12,'Cash-Flow 1'!V12:AK12)*1000+(SUM('Cash-Flow 1'!B27:U28,'Cash-Flow 1'!V27:AL28)/3)-'Cash-Flow 1'!N16-'Cash-Flow 1'!$Z16-'Cash-Flow 1'!$AL16,IF(A2=2,SUM('Cash-Flow 2'!B11:U11,'Cash-Flow 2'!V11:AK11)*1000+(SUM('Cash-Flow 2'!B26:U27,'Cash-Flow 2'!V26:AK27)/3)-'Cash-Flow 2'!N15-'Cash-Flow 2'!Z15-'Cash-Flow 2'!AL15,SUM('Cash-Flow 3'!B13:U13,'Cash-Flow 3'!V13:AK13)*1000+(SUM('Cash-Flow 3'!B28:U29,'Cash-Flow 3'!V28:AH29)/3)-'Cash-Flow 3'!AL17-'Cash-Flow 3'!Z17-'Cash-Flow 3'!N17)) -> 385526.34
A8: Основные выводы
A9: Сценарий 1 | B9: Предполагается, что каждый инвестор совершает одну покупку (1 клиент = 1 ЦФА), что упрощает расчёт, но консервативно занижает LTV (реинвестирование не учитывается).
B10: В отличие от Сценариев 2 и 3, в Сценарии 1 не предусмотрены дополнительные регулярные расходы на интернет-маркетинг, PR и образовательный контент. Это означает, что привлечение инвесторов происходит органически или через партнёрские/платформенные каналы (например, через интеграцию с Alfa ID и игровые платформы).
B12: CAC здесь отражает только операционные издержки на оформление и обслуживание сделки, а не рекламу.
A13: Сценарий 2 | B13: Повышенный CAC (по сравнению с Сценарием 1) косвенно отражает более высокую стоимость привлечения. Это связано с менее «горячим» интересом аудитории (предпосылка, которую мы заложили в сценарий), требующим дополнительных усилий (например, через платформенные комиссии, партнёрские бонусы или лёгкий PR).
A15: Сценарий 3 | B15: Данный сценарий предполагает активное привлечение аудитории через пиар-компании. Поэтому получается очень высокий CAC (выше LTV). Здесь лучший фокус - снижение фиксированных издержек и направление затрат на более эффективные каналы привлечения аудитории.
